Workbook

Sheet Full survey table
C1: Q1: Name + Job title | F1: Q2: Knowledge of GMA status? | I1: Q3: Population growth? | R1: Q4: Selling water to other towns? | V1: Q5: Recent expansion? | AE1: Q6: How do you raise funds for water infrastructure expansion? | AO1: Q7: Calculation knowledge? | AU1: Q8: GIS tool use? | BA1: Q9: Anything you want to add? | BD1: EDB_1: Budget & Debt External data
A2: County | B2: Town | C2: Useful Survey Participation <DI> (Y/N) | D2: Cleaned | E2: Notes / Transcription [Raw] | F2: Knowledge of GMA Status <IR> (Y/N) | G2: Notes / Transcription [Raw] | H2: Fact Check [Post-Survey]: Actual County GMA status | I2: Did Population grow in the last 10 years? <IR> (Y/N) | J2: Notes / Transcription [Raw] | K2: Fact Check Comparison [Post-Survey] | L2: Pre-growth population <FI> [2014, per OFM] | M2: 2024 Population <FI> | N2: 2014 - 2024 Population Growth % <CM> | O2: 2024 Population Greater than median? <CM> (Y/N) | P2: Pop. growth equal to or above White Salmon's? [10.15] <CM> (Y/N) | Q2: Population growth above median? [2.89] <CM> (Y/N) | R2: Selling water to other towns? <IR> (Y/N) | S2: Notes / Transcription [Raw] | T2: Selling to individual customers? <IR> (Y/N) | U2: edge case? Is this qualitatively interesting? <DI> (Y/N) | V2: Water Infrastructure expansion within the last 10 years? <IR> (Y/N) | W2: Notes / Transcription [Raw] | X2: A bit more than 10 years ago? <IR> (Y/N) | Y2: Not Including Connections? <IR> (Y/N) | Z2: Connections expansion? <IR> (Y/N) | AA2: Aquifer Storage expansion? <IR> (Y/N) | AB2: Water Sources expansion? <IR> (Y/N) | AC2: Water Treatment expansion? <IR> (Y/N) | AD2: Sewage expansion [not connections]? <IR> (Y/N) | AE2: Knowledge of funding methodology? <IR> (Y/N) | AF2: Notes / Transcription [Raw] | AG2: Tax rates [explicit] <IR> (Y/N) | AH2: Development charge [unsure] <IR> (Y/N) | AI2: Connection fee <IR> (Y/N) | AJ2: SDC [explicit] <IR> (Y/N) | AK2: CFC [explicit] <IR> (Y/N) | AL2: Impact fee [explicit] <IR> (Y/N) | AM2: Grants? <IR> (Y/N) | AN2: Other/ edge case [explicit] <DI> (Y/N) | AO2: Knowledge of calculation specifics involved in funding methodology? <IR> (Y/N) | AP2: Notes / Transcription [Raw] | AQ2: Meter size [primarily] <IR> (Y/N) | AR2: ERUs [primarily] <IR> (Y/N) | AS2: Grandfathered / inflation adjusted <IR> (Y/N) | AT2: Overall cost analysis [primarily] <IR> (Y/N) | AU2: GIS tool use? <IR> (Y/N) | AV2: Notes / Transcription [Raw] | AW2: For meter location? <IR> (Y/N) | AX2: For asset valuation & fee calculations? <IR> (Y/N) | AY2: Separate tool for asset valuation? <IR> (Y/N) | AZ2: Name of GIS tool, name of separate asset valuation tool | BA2: Notes / Transcription [Raw] | BB2: Important details from secondary interviewee [usually info on who to actually interview instead of them] | BC2: Additional comments/ notes from interviewee [me] | BD2: Total Budget ($) FY2024 actual total expenditures, all funds <FI> | BE2: Budget – Source & Year | BF2: Capital & Bonded Debt ($) [CALCULATED — debt-type filter, excl. pension/OPEB] <FI> | BG2: Capital & Bonded Debt per capita <CM> | BH2: Official Total Liabilities ($) [DIRECT — official Schedule 09 filed total, all liabilities] <FI> | BI2: Filtered Debt ($) [CALCULATED — keyword filter, including only charges related to water infrastructure ] <FI> | BJ2: Debt – Source, Water/Sewer Portion & Context | BK2: Full Debt per capita <CM> | BL2: Debt to Population regression residuals <CM>
A3: Adams | B3: Othello | C3: Y | E3: public works director for Othello | F3: N | H3: Partially Planning | I3: Y | J3: 9,000 now, were closer to 7,500 | K3: Survey had 7,500 / 9,000 (close to OFM 7,780 / 9,210) | L3: 7695 | M3: 9145 | N3: =((M3 - L3) / L3) * 100 -> 18.843405 | O3: {=IF(M3 > MEDIAN(_xlfn._xlws.FILTER(M:M, C:C="Y")),"Y","N")} -> Y | P3: =IF(N3 >= 10.15, "Y", "N") -> Y | Q3: {=IF(N3 > MEDIAN(_xlfn._xlws.FILTER(N:N, C:C="Y")), "Y", "N")} -> Y | R3: N | T3: N | U3: N | V3: Y | W3: developments are responsible for adding infrastructure not us, but we have added 2 new wells. | X3: N | Y3: =IF(C3="N", "", IF(AND(C3="Y", OR(AA3="Y", AB3="Y", AC3="Y", AD3="Y")), "Y", "N")) -> Y | Z3: Y | AA3: N | AB3: Y | AC3: N | AD3: N | AE3: Y | AF3: These were calculated prior to me, not sure how this was developed. Part of our development fees, (not sure what formal name is for these) | AG3: N | AH3: Y | AI3: N | AJ3: N | AK3: N | AL3: N | AM3: N | AN3: N | AO3: Y | AP3: fees for developers are 2% for whatever the infrastructure cost is. | AQ3: N | AR3: N | AS3: N | AT3: Y | AU3: N | AW3: N/A | AX3: N/A | AY3: N/A | AZ3: N/A | BC3: third survey | BD3: 22250763 | BE3: FY2024 actual total expenditures, all funds (operating + capital/debt service). Source: WA State Auditor FIT, schedule1AggregationsByGovt (sections 30+35), MCAG 0188. portal.sao.wa.gov/FIT. | BF3: 4238690 | BG3: =BF3 /M3 -> 463.49809 | BH3: 7816828 | BI3: 2427269 | BJ3: FY2024 Schedule 09 via SAO FIT API (Snapshots/Schedule9s, MCAG 0188). Col E 'Outstanding Debt' = CALCULATED: total LT principal EXCLUDING pension/OPEB/compensated absences (excluded by debt-type code — reliable). Col F 'Official Total Liabilities' = DIRECT: grand total of the Schedule 09 as filed with SAO (all liabilities incl. pension/OPEB; no pattern matching). WATER/SEWER portion ~$2,427,269 [REGEX/KEYWORD — IMPRECISE: matched on debt-description text only (no fund tag in FIT); approximate]. | BK3: =BH3 / M3 -> 854.76523 | BL3: ='log(debt) vs log(pop.) normaliz'!H3 -> -0.35664911
A4: Adams | B4: Ritzville | C4: N | H4: Partially Planning | L4: 1680 | M4: 1790 | N4: =((M4 - L4) / L4) * 100 -> 6.547619 | O4: {=IF(M4 > MEDIAN(_xlfn._xlws.FILTER(M:M, C:C="Y")),"Y","N")} -> N | P4: =IF(N4 >= 10.15, "Y", "N") -> N | Q4: {=IF(N4 > MEDIAN(_xlfn._xlws.FILTER(N:N, C:C="Y")), "Y", "N")} -> Y | Y4: =IF(C4="N", "", IF(AND(C4="Y", OR(AA4="Y", AB4="Y", AC4="Y", AD4="Y")), "Y", "N")) | BD4: 7938329 | BE4: FY2024 actual total expenditures, all funds (operating + capital/debt service). Source: WA State Auditor FIT, schedule1AggregationsByGovt (sections 30+35), MCAG 0191. portal.sao.wa.gov/FIT. | BF4: 7316901 | BG4: =BF4 /M4 -> 4087.6542 | BH4: 7424624 | BI4: 2098924 | BJ4: FY2024 Schedule 09 via SAO FIT API (Snapshots/Schedule9s, MCAG 0191). Col E 'Outstanding Debt' = CALCULATED: total LT principal EXCLUDING pension/OPEB/compensated absences (excluded by debt-type code — reliable). Col F 'Official Total Liabilities' = DIRECT: grand total of the Schedule 09 as filed with SAO (all liabilities incl. pension/OPEB; no pattern matching). WATER/SEWER portion ~$2,098,924 [REGEX/KEYWORD — IMPRECISE: matched on debt-description text only (no fund tag in FIT); approximate]. | BK4: =BH4 / M4 -> 4147.8346 | BL4: ='log(debt) vs log(pop.) normaliz'!H4 -> 1.3250712
A5: Asotin | B5: Clarkston [Asotin PUD] | C5: Y | E5: Bob Sischo, Director of finance and administration for the public utilities district of Asotin. Handles water utilities for all of the towns & communities in Asotin. | F5: N | H5: Partially Planning | I5: N | J5: Some influx during COVID, nothing significant though in terms of population growth. Large geographic county, population base is well centered in Asotin (city) and Clarkston. | L5: 7225 | M5: 7240 | N5: =((M5 - L5) / L5) * 100 -> 0.20761246 | O5: {=IF(M5 > MEDIAN(_xlfn._xlws.FILTER(M:M, C:C="Y")),"Y","N")} -> Y | P5: =IF(N5 >= 10.15, "Y", "N") -> N | Q5: {=IF(N5 > MEDIAN(_xlfn._xlws.FILTER(N:N, C:C="Y")), "Y", "N")} -> N | R5: Y | S5: Based upon their consumption beyond their alloted amount. Asotin has a water system that gives alloted amounts of water to residents, excess is handled by the utilities district. | T5: Y | U5: Y | V5: Y | W5: No, a couple of subdivisions (multiple connections) but nothing major | X5: N | Y5: =IF(C5="N", "", IF(AND(C5="Y", OR(AA5="Y", AB5="Y", AC5="Y", AD5="Y")), "Y", "N")) -> N | Z5: Y | AA5: N | AB5: N | AC5: N | AD5: N | AE5: Y | AF5: Development pays for development approach. If someone require a subdivions, the developer is required to devlop it for us, then they hand it to us. We don’t put up funds or anything like that. SDCs are wrapped into the connection fees, but we arent really building out, so we never have capacity issues, only at 50%. | AG5: N | AH5: N | AI5: Y | AJ5: Y | AK5: N | AL5: N | AM5: N | AN5: N | AO5: Y | AP5: Connection fees are based more consumption, and cost of the connection. What is it costing us in terms of maintence? We arent dealing with capacity or urban sprawl, so our fees can be almost entirely around our cost base and maintenance projections. | AQ5: N | AR5: N | AS5: N | AT5: Y | AU5: Y | AV5: Yes, kind of for asset valuation. Mostly to maintain our system, pressure zones. | AW5: Y | AX5: Y | AY5: N | BC5: Good survey with the Public utilities district director Bob Sischo (people who actually handle water utiliteis in Asotin, not the public works director in this case.) | BD5: 18032979 | BE5: FY2024 actual total expenditures, all funds (operating + capital/debt service). Source: WA State Auditor FIT, schedule1AggregationsByGovt (sections 30+35), MCAG 0197. portal.sao.wa.gov/FIT. | BF5: 558518 | BG5: =BF5 /M5 -> 77.14337 | BH5: 5933169 | BI5: 0 | BJ5: FY2024 Schedule 09 via SAO FIT API (Snapshots/Schedule9s, MCAG 0197). Col E 'Outstanding Debt' = CALCULATED: total LT principal EXCLUDING pension/OPEB/compensated absences (excluded by debt-type code — reliable). Col F 'Official Total Liabilities' = DIRECT: grand total of the Schedule 09 as filed with SAO (all liabilities incl. pension/OPEB; no pattern matching). WATER/SEWER portion: none identifiable by keyword (may be $0, generically labeled, or held by a separate entity) [REGEX/KEYWORD — IMPRECISE]. W/S keyword=$0: water supplied by Asotin County PUD No.1 (separate entity). | BK5: =BH5 / M5 -> 819.49848 | BL5: ='log(debt) vs log(pop.) normaliz'!H5 -> -0.38414583
A6: Woodland | B6: Longview | C6: Y | E6: public works director, as well as asistant city manager | F6: Y | G6: non gma | H6: *Pending | I6: N | J6: not significant growth, about 1 percent average per anum growth | L6: 37040 | M6: 38230 | N6: =((M6 - L6) / L6) * 100 -> 3.212743 | O6: {=IF(M6 > MEDIAN(_xlfn._xlws.FILTER(M:M, C:C="Y")),"Y","N")} -> Y | P6: =IF(N6 >= 10.15, "Y", "N") -> N | Q6: {=IF(N6 > MEDIAN(_xlfn._xlws.FILTER(N:N, C:C="Y")), "Y", "N")} -> Y | R6: Y | S6: we provide water to beacon hill water sewer district, they are a 15 percent owner, their ditribution is tied to ours we charge them for their distribution. We have an agreement with kelso for high well water. We have an inter connect where they can pull water from our system at a retail rate (whenever we have excess). | T6: N | U6: Y | V6: Y | W6: Yes we have, a little more than 10 years ago we switched to ground wells from surface waters. We expanded our sytem to accomodate for that . | X6: Y | Y6: =IF(C6="N", "", IF(AND(C6="Y", OR(AA6="Y", AB6="Y", AC6="Y", AD6="Y")), "Y", "N")) -> Y | Z6: Y | AA6: N | AB6: Y | AC6: N | AD6: N | AE6: Y | AF6: If its developer driven they pay for it. If its infrastructure investment then we pay it. We issue debt to pay for those large expenses, or we pull from capital reserves. Connection fee for freshwater only, SDC for sewer only. | AG6: N | AH6: N | AI6: Y | AJ6: Y | AK6: N | AL6: N | AM6: N | AN6: N | AO6: Y | AP6: we have sdcs on sewer, no impact, connection charges on water. SDCs are calculated off of ERUs and connection charges are calculated off of size of connection. So charges for freshwater are based on size, sewer is standardized | AQ6: Y (fresh water connection fees) | AR6: Y (sewer SDC) | AS6: N | AT6: N | AU6: Y | AV6: Yes we use a Gis tool. We have an asset management system. Its lucidy, a work order and asset management program (Not gis). As far as our system value, we produce and maintain water and sewer system plans that go into more detail on the value of the system. that is the doc that guides more of our long erm planning. | AW6: Y | AX6: N | AY6: Y | AZ6: Lucidy (asset valuation) | BC6: write here after the car interview | BD6: 145614128 | BE6: FY2024 actual total expenditures, all funds (operating + capital/debt service). Source: WA State Auditor FIT, schedule1AggregationsByGovt (sections 30+35), MCAG 0267. portal.sao.wa.gov/FIT. | BF6: 30408003 | BG6: =BF6 /M6 -> 795.39636 | BH6: 63665714 | BI6: 0 | BJ6: FY2024 Schedule 09 via SAO FIT API (Snapshots/Schedule9s, MCAG 0267). Col E 'Outstanding Debt' = CALCULATED: total LT principal EXCLUDING pension/OPEB/compensated absences (excluded by debt-type code — reliable). Col F 'Official Total Liabilities' = DIRECT: grand total of the Schedule 09 as filed with SAO (all liabilities incl. pension/OPEB; no pattern matching). WATER/SEWER portion: none identifiable by keyword (may be $0, generically labeled, or held by a separate entity) [REGEX/KEYWORD — IMPRECISE]. W/S keyword=$0: city co-owns Mint Farm Regional WTP w/ Beacon Hill W&S District; water debt largely on the regional entity. Verify in ACFR. | BK6: =BH6 / M6 -> 1665.3339 | BL6: ='log(debt) vs log(pop.) normaliz'!H6 -> 0.22066871
A7: Cowlitz | B7: Kelso | C7: N | H7: *Pending | L7: 11960 | M7: 12780 | N7: =((M7 - L7) / L7) * 100 -> 6.8561873 | O7: {=IF(M7 > MEDIAN(_xlfn._xlws.FILTER(M:M, C:C="Y")),"Y","N")} -> Y | P7: =IF(N7 >= 10.15, "Y", "N") -> N | Q7: {=IF(N7 > MEDIAN(_xlfn._xlws.FILTER(N:N, C:C="Y")), "Y", "N")} -> Y | Y7: =IF(C7="N", "", IF(AND(C7="Y", OR(AA7="Y", AB7="Y", AC7="Y", AD7="Y")), "Y", "N")) | BD7: 49960615 | BE7: FY2024 actual total expenditures, all funds (operating + capital/debt service). Source: WA State Auditor FIT, schedule1AggregationsByGovt (sections 30+35), MCAG 0264. portal.sao.wa.gov/FIT. | BF7: 10933802 | BG7: =BF7 /M7 -> 855.54006 | BH7: 18018433 | BI7: 2819084 | BJ7: FY2024 Schedule 09 via SAO FIT API (Snapshots/Schedule9s, MCAG 0264). Col E 'Outstanding Debt' = CALCULATED: total LT principal EXCLUDING pension/OPEB/compensated absences (excluded by debt-type code — reliable). Col F 'Official Total Liabilities' = DIRECT: grand total of the Schedule 09 as filed with SAO (all liabilities incl. pension/OPEB; no pattern matching). WATER/SEWER portion ~$2,819,084 [REGEX/KEYWORD — IMPRECISE: matched on debt-description text only (no fund tag in FIT); approximate]. | BK7: =BH7 / M7 -> 1409.893 | BL7: ='log(debt) vs log(pop.) normaliz'!H7 -> 0.12282095
A8: Cowlitz | B8: Castle Rock | C8: N | H8: *Pending | L8: 2145 | M8: 2465 | N8: =((M8 - L8) / L8) * 100 -> 14.918415 | O8: {=IF(M8 > MEDIAN(_xlfn._xlws.FILTER(M:M, C:C="Y")),"Y","N")} -> Y | P8: =IF(N8 >= 10.15, "Y", "N") -> Y | Q8: {=IF(N8 > MEDIAN(_xlfn._xlws.FILTER(N:N, C:C="Y")), "Y", "N")} -> Y | Y8: =IF(C8="N", "", IF(AND(C8="Y", OR(AA8="Y", AB8="Y", AC8="Y", AD8="Y")), "Y", "N")) | BD8: 7639897 | BE8: FY2024 actual total expenditures, all funds (operating + capital/debt service). Source: WA State Auditor FIT, schedule1AggregationsByGovt (sections 30+35), MCAG 0260. portal.sao.wa.gov/FIT. | BF8: 5766734 | BG8: =BF8 /M8 -> 2339.4458 | BH8: 6060122 | BI8: 286841 | BJ8: FY2024 Schedule 09 via SAO FIT API (Snapshots/Schedule9s, MCAG 0260). Col E 'Outstanding Debt' = CALCULATED: total LT principal EXCLUDING pension/OPEB/compensated absences (excluded by debt-type code — reliable). Col F 'Official Total Liabilities' = DIRECT: grand total of the Schedule 09 as filed with SAO (all liabilities incl. pension/OPEB; no pattern matching). WATER/SEWER portion ~$286,841 [REGEX/KEYWORD — IMPRECISE: matched on debt-description text only (no fund tag in FIT); approximate]. | BK8: =BH8 / M8 -> 2458.4673 | BL8: ='log(debt) vs log(pop.) normaliz'!H8 -> 0.78197168
A9: Cowlitz | B9: Woodland | C9: Y | F9: Y | G9: pending status for GMA. | H9: *Pending | I9: Y | J9: Yes. | K9: Woodland straddles Cowlitz/Clark; figures are full-city totals | L9: 5695 | M9: 6575 | N9: =((M9 - L9) / L9) * 100 -> 15.452151 | O9: {=IF(M9 > MEDIAN(_xlfn._xlws.FILTER(M:M, C:C="Y")),"Y","N")} -> Y | P9: =IF(N9 >= 10.15, "Y", "N") -> Y | Q9: {=IF(N9 > MEDIAN(_xlfn._xlws.FILTER(N:N, C:C="Y")), "Y", "N")} -> Y | R9: Y | S9: We do service for a small housing development in clark county | T9: N | U9: N | V9: Y | W9: City of woodland has not done any internal expansion, but residential has (for connections and water sewage infrastructure). The water main is private, they then relinquish infrastructure to our department. They charge SDCs to new developers, we do not. | X9: N | Y9: =IF(C9="N", "", IF(AND(C9="Y", OR(AA9="Y", AB9="Y", AC9="Y", AD9="Y")), "Y", "N")) -> Y | Z9: Y | AA9: N | AB9: N | AC9: N | AD9: Y | AE9: N | AF9: City does not pay for any of the expansion costs, all developer driven | AG9: N | AH9: N/A | AI9: N/A | AJ9: N/A | AK9: N/A | AL9: N/A | AM9: N/A | AN9: N/A | AO9: N/A | AP9: (they don’t handle these, so I didn’t ask because its not their jurisdiction in this case) | AQ9: N/A | AR9: N/A | AS9: N/A | AT9: N/A | AU9: Y | AV9: We use GIS ezeree. We are looking to update. We just use it informationally, no asset valuation, unless its sewer INI | AW9: Y | AX9: N | AY9: N | BA9: would recommend to look at capital improvement list, what are the current system constraints? Put a denomination next to what projects are most importanmt. Every 5 years we do a third party review for capital improvement projects. FCJ they come in as a third party. | BC9: Good | BD9: 18142398 | BE9: FY2024 actual total expenditures, all funds (operating + capital/debt service). Source: WA State Auditor FIT, schedule1AggregationsByGovt (sections 30+35), MCAG 0271. portal.sao.wa.gov/FIT. | BF9: 5778202 | BG9: =BF9 /M9 -> 878.81399 | BH9: 7023570 | BI9: 294582 | BJ9: FY2024 Schedule 09 via SAO FIT API (Snapshots/Schedule9s, MCAG 0271). Col E 'Outstanding Debt' = CALCULATED: total LT principal EXCLUDING pension/OPEB/compensated absences (excluded by debt-type code — reliable). Col F 'Official Total Liabilities' = DIRECT: grand total of the Schedule 09 as filed with SAO (all liabilities incl. pension/OPEB; no pattern matching). WATER/SEWER portion ~$294,582 [REGEX/KEYWORD — IMPRECISE: matched on debt-description text only (no fund tag in FIT); approximate]. | BK9: =BH9 / M9 -> 1068.2236 | BL9: ='log(debt) vs log(pop.) normaliz'!H9 -> -0.11304852
A10: Cowlitz | B10: Kalama | C10: N | H10: *Pending | L10: 2430 | M10: 3160 | N10: =((M10 - L10) / L10) * 100 -> 30.041152 | O10: {=IF(M10 > MEDIAN(_xlfn._xlws.FILTER(M:M, C:C="Y")),"Y","N")} -> Y | P10: =IF(N10 >= 10.15, "Y", "N") -> Y | Q10: {=IF(N10 > MEDIAN(_xlfn._xlws.FILTER(N:N, C:C="Y")), "Y", "N")} -> Y | Y10: =IF(C10="N", "", IF(AND(C10="Y", OR(AA10="Y", AB10="Y", AC10="Y", AD10="Y")), "Y", "N")) | BD10: 10910954 | BE10: FY2024 actual total expenditures, all funds (operating + capital/debt service). Source: WA State Auditor FIT, schedule1AggregationsByGovt (sections 30+35), MCAG 0262. portal.sao.wa.gov/FIT. | BF10: 3807013 | BG10: =BF10 /M10 -> 1204.7509 | BH10: 4170942 | BI10: 1177934 | BJ10: FY2024 Schedule 09 via SAO FIT API (Snapshots/Schedule9s, MCAG 0262). Col E 'Outstanding Debt' = CALCULATED: total LT principal EXCLUDING pension/OPEB/compensated absences (excluded by debt-type code — reliable). Col F 'Official Total Liabilities' = DIRECT: grand total of the Schedule 09 as filed with SAO (all liabilities incl. pension/OPEB; no pattern matching). WATER/SEWER portion ~$1,177,934 [REGEX/KEYWORD — IMPRECISE: matched on debt-description text only (no fund tag in FIT); approximate]. | BK10: =BH10 / M10 -> 1319.9184 | BL10: ='log(debt) vs log(pop.) normaliz'!H10 -> 0.1444388
A11: Ferry | B11: Republic | C11: Y | E11: Public works director, Republic | F11: N | G11: Doesn’t know, new to position. [they are ___] | H11: *Partially Planning | I11: N | J11: No | K11: *Ferry County is the only "voluntary GMA" county that later opted out (RCW 36.70A.040(2)(b)) | L11: 1100 | M11: 1005 | N11: =((M11 - L11) / L11) * 100 -> -8.6363636 | O11: {=IF(M11 > MEDIAN(_xlfn._xlws.FILTER(M:M, C:C="Y")),"Y","N")} -> N | P11: =IF(N11 >= 10.15, "Y", "N") -> N | Q11: {=IF(N11 > MEDIAN(_xlfn._xlws.FILTER(N:N, C:C="Y")), "Y", "N")} -> N | R11: N | S11: No | T11: N | U11: N | V11: N | W11: No, using about 60% of capacity | X11: N | Y11: =IF(C11="N", "", IF(AND(C11="Y", OR(AA11="Y", AB11="Y", AC11="Y", AD11="Y")), "Y", "N")) -> N | Z11: N/A | AA11: N/A | AB11: N/A | AC11: N/A | AD11: N/A | AE11: Y | AF11: Engineering firm, in spokane, they do it. We get charged for their development. County tax vbas, hotel motel tax, typically sewer water rates pay for everything. | AG11: Y | AH11: N | AI11: N | AJ11: N | AK11: N | AL11: N | AM11: N | AN11: Y | AO11: N/A | AQ11: N/A | AR11: N/A | AS11: N/A | AT11: N/A | AU11: Y | AV11: Just recently got GIS set up. Primarily for locating, no bluetooth meters. Only had it about 8-9 months. Mainly for locating valves for streets in valves. We pay a monthly, only 3 grand payment, 1300 residence 600 meters. Poorest county in state. | AW11: Y | AX11: N | AY11: N | BA11: Been public works director for year in a half 60 with 40 years in construction, think its helped a lot with problem solving skills. 125 year old town, 6-7 years ago case of embezzlment, now we get audited every year. Young mayor, fantastic city clerk. main source of leaks is steel pipes, pumpibng 130m gallons a year, wasting 27%. 6 inch pvc, wasting a lot of money on contractors. | BC11: All went well, first survey. | BD11: 4919773 | BE11: FY2024 actual total expenditures, all funds (operating + capital/debt service). Source: WA State Auditor FIT, schedule1AggregationsByGovt (sections 30+35), MCAG 0284. portal.sao.wa.gov/FIT. | BF11: 400766 | BG11: =BF11 /M11 -> 398.77214 | BH11: 432112 | BI11: 297105 | BJ11: FY2024 Schedule 09 via SAO FIT API (Snapshots/Schedule9s, MCAG 0284). Col E 'Outstanding Debt' = CALCULATED: total LT principal EXCLUDING pension/OPEB/compensated absences (excluded by debt-type code — reliable). Col F 'Official Total Liabilities' = DIRECT: grand total of the Schedule 09 as filed with SAO (all liabilities incl. pension/OPEB; no pattern matching). WATER/SEWER portion ~$297,105 [REGEX/KEYWORD — IMPRECISE: matched on debt-description text only (no fund tag in FIT); approximate]. | BK11: =BH11 / M11 -> 429.96219 | BL11: ='log(debt) vs log(pop.) normaliz'!H11 -> -0.90540152
A12: Grays Harbor | B12: Aberdeen | C12: Y | E12: Public works director of Aberdeen | F12: N | G12: [They are ___] | H12: Partially Planning | I12: N | J12: Maybe 500 new ppl, lots of new development though, around 40 new projects | L12: 16850 | M12: 17100 | N12: =((M12 - L12) / L12) * 100 -> 1.4836795 | O12: {=IF(M12 > MEDIAN(_xlfn._xlws.FILTER(M:M, C:C="Y")),"Y","N")} -> Y | P12: =IF(N12 >= 10.15, "Y", "N") -> N | Q12: {=IF(N12 > MEDIAN(_xlfn._xlws.FILTER(N:N, C:C="Y")), "Y", "N")} -> N | R12: N | S12: not currently, in negotiation to buy / be in same contract as cosmopolis' water system | T12: N | U12: N | V12: N | W12: No. | X12: N | Y12: =IF(C12="N", "", IF(AND(C12="Y", OR(AA12="Y", AB12="Y", AC12="Y", AD12="Y")), "Y", "N")) -> N | Z12: N/A | AA12: N/A | AB12: N/A | AC12: N/A | AD12: N/A | AE12: Y | AF12: Future growth covered completely by rates. About 2,000 acres of timber, town considered a small landowner. Can harvest every other year. We are upgrading roads to support this. Planning on selling and using timber to draw interest which would then go to water, but could be used more generally. They do SDC by meter, its about 35 hundred dollars. Depends on size of meter. No latecomers agreement | AG12: Y | AH12: N | AI12: N | AJ12: Y | AK12: N | AL12: N | AM12: N | AN12: Y | AO12: Y | AP12: primarily based on meter size. 6 inch lines for fire dept., developers pay in full for additional costs associated with fire protection developments if necessary. | AQ12: Y | AR12: N | AS12: N | AT12: N | AU12: Y | AV12: yes, we use it for location. Havent used for asset valuation yet, but they can. If meter is not used for 6 months, its worth more to take it out. Not an expert on this. AMES software is more for the valuation stuff | AW12: Y | AX12: N | AY12: Y | AZ12: AMES (asset valuation) | BC12: Went well, second survey | BD12: 62604391 | BE12: FY2024 actual total expenditures, all funds (operating + capital/debt service). Source: WA State Auditor FIT, schedule1AggregationsByGovt (sections 30+35), MCAG 0331. portal.sao.wa.gov/FIT. | BF12: 10472462 | BG12: =BF12 /M12 -> 612.42468 | BH12: 38656768 | BI12: 9764209 | BJ12: FY2024 Schedule 09 via SAO FIT API (Snapshots/Schedule9s, MCAG 0331). Col E 'Outstanding Debt' = CALCULATED: total LT principal EXCLUDING pension/OPEB/compensated absences (excluded by debt-type code — reliable). Col F 'Official Total Liabilities' = DIRECT: grand total of the Schedule 09 as filed with SAO (all liabilities incl. pension/OPEB; no pattern matching). WATER/SEWER portion ~$9,764,209 [REGEX/KEYWORD — IMPRECISE: matched on debt-description text only (no fund tag in FIT); approximate]. Debt overwhelmingly water/sewer (8->12 MGD Water Reclamation Plant + WWTP/reservoir DOE/DOH loans). | BK12: =BH12 / M12 -> 2260.6297 | BL12: ='log(debt) vs log(pop.) normaliz'!H12 -> 0.57670278
A13: Grays Harbor | B13: Hoquiam | C13: N | H13: Partially Planning | L13: 8625 | M13: 8800 | N13: =((M13 - L13) / L13) * 100 -> 2.0289855 | O13: {=IF(M13 > MEDIAN(_xlfn._xlws.FILTER(M:M, C:C="Y")),"Y","N")} -> Y | P13: =IF(N13 >= 10.15, "Y", "N") -> N | Q13: {=IF(N13 > MEDIAN(_xlfn._xlws.FILTER(N:N, C:C="Y")), "Y", "N")} -> N | Y13: =IF(C13="N", "", IF(AND(C13="Y", OR(AA13="Y", AB13="Y", AC13="Y", AD13="Y")), "Y", "N")) | BD13: 35544582 | BE13: FY2024 actual total expenditures, all funds (operating + capital/debt service). Source: WA State Auditor FIT, schedule1AggregationsByGovt (sections 30+35), MCAG 0340. portal.sao.wa.gov/FIT. | BF13: 14189572 | BG13: =BF13 /M13 -> 1612.4514 | BH13: 25208098 | BI13: 11630621 | BJ13: FY2024 Schedule 09 via SAO FIT API (Snapshots/Schedule9s, MCAG 0340). Col E 'Outstanding Debt' = CALCULATED: total LT principal EXCLUDING pension/OPEB/compensated absences (excluded by debt-type code — reliable). Col F 'Official Total Liabilities' = DIRECT: grand total of the Schedule 09 as filed with SAO (all liabilities incl. pension/OPEB; no pattern matching). WATER/SEWER portion ~$11,630,621 [REGEX/KEYWORD — IMPRECISE: matched on debt-description text only (no fund tag in FIT); approximate]. | BK13: =BH13 / M13 -> 2864.5566 | BL13: ='log(debt) vs log(pop.) normaliz'!H13 -> 0.8551027
A14: Grays Harbor | B14: Ocean Shores | C14: N | H14: Partially Planning | L14: 5880 | M14: 7630 | N14: =((M14 - L14) / L14) * 100 -> 29.761905 | O14: {=IF(M14 > MEDIAN(_xlfn._xlws.FILTER(M:M, C:C="Y")),"Y","N")} -> Y | P14: =IF(N14 >= 10.15, "Y", "N") -> Y | Q14: {=IF(N14 > MEDIAN(_xlfn._xlws.FILTER(N:N, C:C="Y")), "Y", "N")} -> Y | Y14: =IF(C14="N", "", IF(AND(C14="Y", OR(AA14="Y", AB14="Y", AC14="Y", AD14="Y")), "Y", "N")) | BD14: 30517848 | BE14: FY2024 actual total expenditures, all funds (operating + capital/debt service). Source: WA State Auditor FIT, schedule1AggregationsByGovt (sections 30+35), MCAG 0352. portal.sao.wa.gov/FIT. | BF14: 10179412 | BG14: =BF14 /M14 -> 1334.13 | BH14: 14252693 | BI14: 1298157 | BJ14: FY2024 Schedule 09 via SAO FIT API (Snapshots/Schedule9s, MCAG 0352). Col E 'Outstanding Debt' = CALCULATED: total LT principal EXCLUDING pension/OPEB/compensated absences (excluded by debt-type code — reliable). Col F 'Official Total Liabilities' = DIRECT: grand total of the Schedule 09 as filed with SAO (all liabilities incl. pension/OPEB; no pattern matching). WATER/SEWER portion ~$1,298,157 [REGEX/KEYWORD — IMPRECISE: matched on debt-description text only (no fund tag in FIT); approximate]. | BK14: =BH14 / M14 -> 1867.9807 | BL14: ='log(debt) vs log(pop.) normaliz'!H14 -> 0.43648713
A15: Grays Harbor | B15: Montesano | C15: N | H15: Partially Planning | L15: 4075 | M15: 4135 | N15: =((M15 - L15) / L15) * 100 -> 1.4723926 | O15: {=IF(M15 > MEDIAN(_xlfn._xlws.FILTER(M:M, C:C="Y")),"Y","N")} -> Y | P15: =IF(N15 >= 10.15, "Y", "N") -> N | Q15: {=IF(N15 > MEDIAN(_xlfn._xlws.FILTER(N:N, C:C="Y")), "Y", "N")} -> N | Y15: =IF(C15="N", "", IF(AND(C15="Y", OR(AA15="Y", AB15="Y", AC15="Y", AD15="Y")), "Y", "N")) | BD15: 12726205 | BE15: FY2024 actual total expenditures, all funds (operating + capital/debt service). Source: WA State Auditor FIT, schedule1AggregationsByGovt (sections 30+35), MCAG 0347. portal.sao.wa.gov/FIT. | BF15: 2072244 | BG15: =BF15 /M15 -> 501.14728 | BH15: 3976430 | BI15: 78947 | BJ15: FY2024 Schedule 09 via SAO FIT API (Snapshots/Schedule9s, MCAG 0347). Col E 'Outstanding Debt' = CALCULATED: total LT principal EXCLUDING pension/OPEB/compensated absences (excluded by debt-type code — reliable). Col F 'Official Total Liabilities' = DIRECT: grand total of the Schedule 09 as filed with SAO (all liabilities incl. pension/OPEB; no pattern matching). WATER/SEWER portion ~$78,947 [REGEX/KEYWORD — IMPRECISE: matched on debt-description text only (no fund tag in FIT); approximate]. | BK15: =BH15 / M15 -> 961.65175 | BL15: ='log(debt) vs log(pop.) normaliz'!H15 -> -0.18908544
A16: Grays Harbor | B16: Elma | C16: Y | E16: Public works director of Elma | F16: Y | G16: non growth management act | H16: Partially Planning | I16: N | J16: not gone up much, still around 35 hundred people | K16: Survey had ~3,500 / ~3,500 (2015 was actually 3,135; 2025 is 3,535) | L16: 3130 | M16: 3505 | N16: =((M16 - L16) / L16) * 100 -> 11.980831 | O16: {=IF(M16 > MEDIAN(_xlfn._xlws.FILTER(M:M, C:C="Y")),"Y","N")} -> Y | P16: =IF(N16 >= 10.15, "Y", "N") -> Y | Q16: {=IF(N16 > MEDIAN(_xlfn._xlws.FILTER(N:N, C:C="Y")), "Y", "N")} -> Y | R16: N | S16: No other towns, do provide outside of city limits though within where the service area limits extend. | T16: N | U16: N | V16: Y | W16: mostly to accommodate some development, no water rights expansion, mostly connections | X16: N | Y16: =IF(C16="N", "", IF(AND(C16="Y", OR(AA16="Y", AB16="Y", AC16="Y", AD16="Y")), "Y", "N")) -> N | Z16: Y | AA16: N | AB16: N | AC16: N | AD16: N | AE16: Y | AF16: couple different ways. Contributions to our capital accounts. Connection fees. We seek out grants from state revolving. Try to get as much free money as we can. | AG16: N | AH16: N | AI16: Y | AJ16: N | AK16: Y | AL16: N | AM16: Y | AN16: N | AO16: Y | AP16: Was calculated before I took this position. Now we just do yearly increases for inflation. Normally you would figure out operating costs divided by each connection, then charge that for each new connection. These are capital facility fees | AQ16: N | AR16: N | AS16: Y | AT16: Y | AU16: Y | AV16: Currently in development of GIS. Will use both for billing and for geographical understanding of the meters | AW16: Y | AX16: Y | AY16: N | BA16: Something to take into account in general, most of that expansion is on the developer to cover in terms of fees. If infrastructre isnt there the developer pays. Especially happens in small municipalities. | BC16: fourth done. | BD16: 7995149 | BE16: FY2024 actual total expenditures, all funds (operating + capital/debt service). Source: WA State Auditor FIT, schedule1AggregationsByGovt (sections 30+35), MCAG 0338. portal.sao.wa.gov/FIT. | BF16: 437395 | BG16: =BF16 /M16 -> 124.79173 | BH16: 1840144 | BI16: 0 | BJ16: FY2024 Schedule 09 via SAO FIT API (Snapshots/Schedule9s, MCAG 0338). Col E 'Outstanding Debt' = CALCULATED: total LT principal EXCLUDING pension/OPEB/compensated absences (excluded by debt-type code — reliable). Col F 'Official Total Liabilities' = DIRECT: grand total of the Schedule 09 as filed with SAO (all liabilities incl. pension/OPEB; no pattern matching). WATER/SEWER portion: none identifiable by keyword (may be $0, generically labeled, or held by a separate entity) [REGEX/KEYWORD — IMPRECISE]. | BK16: =BH16 / M16 -> 525.00542 | BL16: ='log(debt) vs log(pop.) normaliz'!H16 -> -0.78397098
A17: Grays Harbor | B17: Westport | C17: N | H17: Partially Planning | L17: 2110 | M17: 2325 | N17: =((M17 - L17) / L17) * 100 -> 10.189573 | O17: {=IF(M17 > MEDIAN(_xlfn._xlws.FILTER(M:M, C:C="Y")),"Y","N")} -> Y | P17: =IF(N17 >= 10.15, "Y", "N") -> Y | Q17: {=IF(N17 > MEDIAN(_xlfn._xlws.FILTER(N:N, C:C="Y")), "Y", "N")} -> Y | Y17: =IF(C17="N", "", IF(AND(C17="Y", OR(AA17="Y", AB17="Y", AC17="Y", AD17="Y")), "Y", "N")) | BD17: 13777291 | BE17: FY2024 actual total expenditures, all funds (operating + capital/debt service). Source: WA State Auditor FIT, schedule1AggregationsByGovt (sections 30+35), MCAG 0355. portal.sao.wa.gov/FIT. | BF17: 12636881 | BG17: =BF17 /M17 -> 5435.2176 | BH17: 13565568 | BI17: 5368311 | BJ17: FY2024 Schedule 09 via SAO FIT API (Snapshots/Schedule9s, MCAG 0355). Col E 'Outstanding Debt' = CALCULATED: total LT principal EXCLUDING pension/OPEB/compensated absences (excluded by debt-type code — reliable). Col F 'Official Total Liabilities' = DIRECT: grand total of the Schedule 09 as filed with SAO (all liabilities incl. pension/OPEB; no pattern matching). WATER/SEWER portion ~$5,368,311 [REGEX/KEYWORD — IMPRECISE: matched on debt-description text only (no fund tag in FIT); approximate]. | BK17: =BH17 / M17 -> 5834.6529 | BL17: ='log(debt) vs log(pop.) normaliz'!H17 -> 1.6499124
A18: Grays Harbor | B18: Cosmopolis | C18: N | H18: Partially Planning | L18: 1645 | M18: 1680 | N18: =((M18 - L18) / L18) * 100 -> 2.1276596 | O18: {=IF(M18 > MEDIAN(_xlfn._xlws.FILTER(M:M, C:C="Y")),"Y","N")} -> N | P18: =IF(N18 >= 10.15, "Y", "N") -> N | Q18: {=IF(N18 > MEDIAN(_xlfn._xlws.FILTER(N:N, C:C="Y")), "Y", "N")} -> N | Y18: =IF(C18="N", "", IF(AND(C18="Y", OR(AA18="Y", AB18="Y", AC18="Y", AD18="Y")), "Y", "N")) | BD18: 5923178 | BE18: FY2024 actual total expenditures, all funds (operating + capital/debt service). Source: WA State Auditor FIT, schedule1AggregationsByGovt (sections 30+35), MCAG 0336. portal.sao.wa.gov/FIT. | BF18: 3233192 | BG18: =BF18 /M18 -> 1924.519 | BH18: 3400333 | BI18: 349428 | BJ18: FY2024 Schedule 09 via SAO FIT API (Snapshots/Schedule9s, MCAG 0336). Col E 'Outstanding Debt' = CALCULATED: total LT principal EXCLUDING pension/OPEB/compensated absences (excluded by debt-type code — reliable). Col F 'Official Total Liabilities' = DIRECT: grand total of the Schedule 09 as filed with SAO (all liabilities incl. pension/OPEB; no pattern matching). WATER/SEWER portion ~$349,428 [REGEX/KEYWORD — IMPRECISE: matched on debt-description text only (no fund tag in FIT); approximate]. | BK18: =BH18 / M18 -> 2024.0077 | BL18: ='log(debt) vs log(pop.) normaliz'!H18 -> 0.61153861
A19: Klickitat | B19: Goldendale | C19: N | H19: Partially Planning | L19: 3420 | M19: 3515 | N19: =((M19 - L19) / L19) * 100 -> 2.7777778 | O19: {=IF(M19 > MEDIAN(_xlfn._xlws.FILTER(M:M, C:C="Y")),"Y","N")} -> Y | P19: =IF(N19 >= 10.15, "Y", "N") -> N | Q19: {=IF(N19 > MEDIAN(_xlfn._xlws.FILTER(N:N, C:C="Y")), "Y", "N")} -> N | Y19: =IF(C19="N", "", IF(AND(C19="Y", OR(AA19="Y", AB19="Y", AC19="Y", AD19="Y")), "Y", "N")) | BD19: 10271678 | BE19: FY2024 actual total expenditures, all funds (operating + capital/debt service). Source: WA State Auditor FIT, schedule1AggregationsByGovt (sections 30+35), MCAG 0479. portal.sao.wa.gov/FIT. | BF19: 9246237 | BG19: =BF19 /M19 -> 2630.5084 | BH19: 10136406 | BI19: 5593718 | BJ19: FY2024 Schedule 09 via SAO FIT API (Snapshots/Schedule9s, MCAG 0479). Col E 'Outstanding Debt' = CALCULATED: total LT principal EXCLUDING pension/OPEB/compensated absences (excluded by debt-type code — reliable). Col F 'Official Total Liabilities' = DIRECT: grand total of the Schedule 09 as filed with SAO (all liabilities incl. pension/OPEB; no pattern matching). WATER/SEWER portion ~$5,593,718 [REGEX/KEYWORD — IMPRECISE: matched on debt-description text only (no fund tag in FIT); approximate]. | BK19: =BH19 / M19 -> 2883.757 | BL19: ='log(debt) vs log(pop.) normaliz'!H19 -> 0.91929115
A20: Klickitat | B20: White Salmon | C20: N | H20: Partially Planning | L20: 2315 | M20: 2550 | N20: =((M20 - L20) / L20) * 100 -> 10.151188 | O20: {=IF(M20 > MEDIAN(_xlfn._xlws.FILTER(M:M, C:C="Y")),"Y","N")} -> Y | P20: =IF(N20 >= 10.15, "Y", "N") -> Y | Q20: {=IF(N20 > MEDIAN(_xlfn._xlws.FILTER(N:N, C:C="Y")), "Y", "N")} -> Y | Y20: =IF(C20="N", "", IF(AND(C20="Y", OR(AA20="Y", AB20="Y", AC20="Y", AD20="Y")), "Y", "N")) | BD20: 11885246 | BE20: FY2024 actual total expenditures, all funds (operating + capital/debt service). Source: WA State Auditor FIT, schedule1AggregationsByGovt (sections 30+35), MCAG 0481. portal.sao.wa.gov/FIT. | BF20: 9502535 | BG20: =BF20 /M20 -> 3726.4843 | BH20: 10849934 | BI20: 929624 | BJ20: FY2024 Schedule 09 via SAO FIT API (Snapshots/Schedule9s, MCAG 0481). Col E 'Outstanding Debt' = CALCULATED: total LT principal EXCLUDING pension/OPEB/compensated absences (excluded by debt-type code — reliable). Col F 'Official Total Liabilities' = DIRECT: grand total of the Schedule 09 as filed with SAO (all liabilities incl. pension/OPEB; no pattern matching). WATER/SEWER portion ~$929,624 [REGEX/KEYWORD — IMPRECISE: matched on debt-description text only (no fund tag in FIT); approximate]. $6M DWSRF loan (Contract DWL31566-0) for Transmission Main Phase 2B. | BK20: =BH20 / M20 -> 4254.8761 | BL20: ='log(debt) vs log(pop.) normaliz'!H20 -> 1.3283748
A21: Klickitat | B21: Bingen | C21: N | H21: Partially Planning | L21: 730 | M21: 780 | N21: =((M21 - L21) / L21) * 100 -> 6.8493151 | O21: {=IF(M21 > MEDIAN(_xlfn._xlws.FILTER(M:M, C:C="Y")),"Y","N")} -> N | P21: =IF(N21 >= 10.15, "Y", "N") -> N | Q21: {=IF(N21 > MEDIAN(_xlfn._xlws.FILTER(N:N, C:C="Y")), "Y", "N")} -> Y | Y21: =IF(C21="N", "", IF(AND(C21="Y", OR(AA21="Y", AB21="Y", AC21="Y", AD21="Y")), "Y", "N")) | BD21: 4933703 | BE21: FY2024 actual total expenditures, all funds (operating + capital/debt service). Source: WA State Auditor FIT, schedule1AggregationsByGovt (sections 30+35), MCAG 0477. portal.sao.wa.gov/FIT. | BF21: 4945198 | BG21: =BF21 /M21 -> 6339.9974 | BH21: 5049557 | BI21: 4934844 | BJ21: FY2024 Schedule 09 via SAO FIT API (Snapshots/Schedule9s, MCAG 0477). Col E 'Outstanding Debt' = CALCULATED: total LT principal EXCLUDING pension/OPEB/compensated absences (excluded by debt-type code — reliable). Col F 'Official Total Liabilities' = DIRECT: grand total of the Schedule 09 as filed with SAO (all liabilities incl. pension/OPEB; no pattern matching). WATER/SEWER portion ~$4,934,844 [REGEX/KEYWORD — IMPRECISE: matched on debt-description text only (no fund tag in FIT); approximate]. | BK21: =BH21 / M21 -> 6473.791 | BL21: ='log(debt) vs log(pop.) normaliz'!H21 -> 1.8223006
A22: Lincoln | B22: Davenport | C22: Y | E22: Public Works director for Davenport | F22: NR | G22: (didn’t ask), Not Recorded (NR) | H22: Partially Planning | I22: Y | J22: Had a good amount of people move here for political reasons during and after COVID. usually issue around 100 "right of way"/ "approach" permits a year, which is fairly limited. 70 percent of the land is farm land, very large county, bigger than rhode island or delaware, only around 1,250 people | K22: Survey had 1,250 for current — incorrect; actual OFM 2025 is 1,720 | L22: 1685 | M22: 1730 | N22: =((M22 - L22) / L22) * 100 -> 2.6706231 | O22: {=IF(M22 > MEDIAN(_xlfn._xlws.FILTER(M:M, C:C="Y")),"Y","N")} -> N | P22: =IF(N22 >= 10.15, "Y", "N") -> N | Q22: {=IF(N22 > MEDIAN(_xlfn._xlws.FILTER(N:N, C:C="Y")), "Y", "N")} -> N | R22: N | S22: We do not sell water to other towns. | T22: N | U22: N | V22: N | W22: This town does not have a utilities system for freshwater in the traditional sense (therefore they never are the ones dealing with infrastructure expansions directly). The health department deals with the Sewage. We do deal with irrigation. We franchise with a utilities / engineering corp. that privately owns the water infrastructure. Franchising is working with a contractor under contract to do all work within a county right of way, good for 10 years. THIS TOWN IS AN OUTLIER AND SHOULD BE MARKED AS SUCH. | X22: N | Y22: =IF(C22="N", "", IF(AND(C22="Y", OR(AA22="Y", AB22="Y", AC22="Y", AD22="Y")), "Y", "N")) -> N | Z22: N/A | AA22: N/A | AB22: N/A | AC22: N/A | AD22: N/A | AE22: Y | AF22: We connect development to the private water network via "approaches" on a case by case basis. Piping size is simply based on what is best for the surrounding area (making sure we arent erroding any roads). We charge a "right of way fee" for new approaches based on the type of development ($50 for farmers $100 for residential, $150 for businesses rough numbers) | AG22: N | AH22: N | AI22: N | AJ22: N | AK22: N | AL22: N | AM22: N | AN22: Y | AU22: N | AV22: No GIS tool, because there are no meters | AW22: N/A | AX22: N/A | AY22: N/A | AZ22: N/A | BC22: Survey was not suited to the town's situation. May need to circle back on this county due to how its lack of public utilities district. | BD22: 3782651 | BE22: FY2024 actual total expenditures, all funds (operating + capital/debt service). Source: WA State Auditor FIT, schedule1AggregationsByGovt (sections 30+35), MCAG 0508. portal.sao.wa.gov/FIT. | BF22: 315000 | BG22: =BF22 /M22 -> 182.08092 | BH22: 461657 | BI22: 0 | BJ22: FY2024 Schedule 09 via SAO FIT API (Snapshots/Schedule9s, MCAG 0508). Col E 'Outstanding Debt' = CALCULATED: total LT principal EXCLUDING pension/OPEB/compensated absences (excluded by debt-type code — reliable). Col F 'Official Total Liabilities' = DIRECT: grand total of the Schedule 09 as filed with SAO (all liabilities incl. pension/OPEB; no pattern matching). WATER/SEWER portion: none identifiable by keyword (may be $0, generically labeled, or held by a separate entity) [REGEX/KEYWORD — IMPRECISE]. | BK22: =BH22 / M22 -> 266.85376 | BL22: ='log(debt) vs log(pop.) normaliz'!H22 -> -1.4164333
A23: Lincoln | B23: Odessa | C23: N | H23: Partially Planning | L23: 900 | M23: 895 | N23: =((M23 - L23) / L23) * 100 -> -0.55555556 | O23: {=IF(M23 > MEDIAN(_xlfn._xlws.FILTER(M:M, C:C="Y")),"Y","N")} -> N | P23: =IF(N23 >= 10.15, "Y", "N") -> N | Q23: {=IF(N23 > MEDIAN(_xlfn._xlws.FILTER(N:N, C:C="Y")), "Y", "N")} -> N | Y23: =IF(C23="N", "", IF(AND(C23="Y", OR(AA23="Y", AB23="Y", AC23="Y", AD23="Y")), "Y", "N")) | BD23: 3728724 | BE23: FY2024 actual total expenditures, all funds (operating + capital/debt service). Source: WA State Auditor FIT, schedule1AggregationsByGovt (sections 30+35), MCAG 0512. portal.sao.wa.gov/FIT. | BF23: 2789157 | BG23: =BF23 /M23 -> 3116.3765 | BH23: 2879663 | BI23: 476275 | BJ23: FY2024 Schedule 09 via SAO FIT API (Snapshots/Schedule9s, MCAG 0512). Col E 'Outstanding Debt' = CALCULATED: total LT principal EXCLUDING pension/OPEB/compensated absences (excluded by debt-type code — reliable). Col F 'Official Total Liabilities' = DIRECT: grand total of the Schedule 09 as filed with SAO (all liabilities incl. pension/OPEB; no pattern matching). WATER/SEWER portion ~$476,275 [REGEX/KEYWORD — IMPRECISE: matched on debt-description text only (no fund tag in FIT); approximate]. | BK23: =BH23 / M23 -> 3217.5006 | BL23: ='log(debt) vs log(pop.) normaliz'!H23 -> 1.1145253
A24: Lincoln | B24: Harrington | C24: N | H24: Partially Planning | L24: 415 | M24: 435 | N24: =((M24 - L24) / L24) * 100 -> 4.8192771 | O24: {=IF(M24 > MEDIAN(_xlfn._xlws.FILTER(M:M, C:C="Y")),"Y","N")} -> N | P24: =IF(N24 >= 10.15, "Y", "N") -> N | Q24: {=IF(N24 > MEDIAN(_xlfn._xlws.FILTER(N:N, C:C="Y")), "Y", "N")} -> Y | Y24: =IF(C24="N", "", IF(AND(C24="Y", OR(AA24="Y", AB24="Y", AC24="Y", AD24="Y")), "Y", "N")) | BD24: 1166193 | BE24: FY2024 actual total expenditures, all funds (operating + capital/debt service). Source: WA State Auditor FIT, schedule1AggregationsByGovt (sections 30+35), MCAG 0510. portal.sao.wa.gov/FIT. | BF24: 27356 | BG24: =BF24 /M24 -> 62.887356 | BH24: 36817 | BI24: 0 | BJ24: FY2024 Schedule 09 via SAO FIT API (Snapshots/Schedule9s, MCAG 0510). Col E 'Outstanding Debt' = CALCULATED: total LT principal EXCLUDING pension/OPEB/compensated absences (excluded by debt-type code — reliable). Col F 'Official Total Liabilities' = DIRECT: grand total of the Schedule 09 as filed with SAO (all liabilities incl. pension/OPEB; no pattern matching). WATER/SEWER portion: none identifiable by keyword (may be $0, generically labeled, or held by a separate entity) [REGEX/KEYWORD — IMPRECISE]. | BK24: =BH24 / M24 -> 84.636782 | BL24: ='log(debt) vs log(pop.) normaliz'!H24 -> -2.4782547
A25: Lincoln | B25: Reardan | C25: N | H25: Partially Planning | L25: 570 | M25: 655 | N25: =((M25 - L25) / L25) * 100 -> 14.912281 | O25: {=IF(M25 > MEDIAN(_xlfn._xlws.FILTER(M:M, C:C="Y")),"Y","N")} -> N | P25: =IF(N25 >= 10.15, "Y", "N") -> Y | Q25: {=IF(N25 > MEDIAN(_xlfn._xlws.FILTER(N:N, C:C="Y")), "Y", "N")} -> Y | Y25: =IF(C25="N", "", IF(AND(C25="Y", OR(AA25="Y", AB25="Y", AC25="Y", AD25="Y")), "Y", "N")) | BD25: 2469620 | BE25: FY2024 actual total expenditures, all funds (operating + capital/debt service). Source: WA State Auditor FIT, schedule1AggregationsByGovt (sections 30+35), MCAG 0514. portal.sao.wa.gov/FIT. | BF25: 382742 | BG25: =BF25 /M25 -> 584.33893 | BH25: 407362 | BI25: 0 | BJ25: FY2024 Schedule 09 via SAO FIT API (Snapshots/Schedule9s, MCAG 0514). Col E 'Outstanding Debt' = CALCULATED: total LT principal EXCLUDING pension/OPEB/compensated absences (excluded by debt-type code — reliable). Col F 'Official Total Liabilities' = DIRECT: grand total of the Schedule 09 as filed with SAO (all liabilities incl. pension/OPEB; no pattern matching). WATER/SEWER portion: none identifiable by keyword (may be $0, generically labeled, or held by a separate entity) [REGEX/KEYWORD — IMPRECISE]. | BK25: =BH25 / M25 -> 621.92672 | BL25: ='log(debt) vs log(pop.) normaliz'!H25 -> -0.50944934
A26: Lincoln | B26: Wilbur | C26: Y | E26: clerk treasurer, Melissa Bulger | F26: Y | G26: Partial planning | H26: Partially Planning | I26: N | J26: No. Very minimal growth | L26: 875 | M26: 900 | N26: =((M26 - L26) / L26) * 100 -> 2.8571429 | O26: {=IF(M26 > MEDIAN(_xlfn._xlws.FILTER(M:M, C:C="Y")),"Y","N")} -> N | P26: =IF(N26 >= 10.15, "Y", "N") -> N | Q26: {=IF(N26 > MEDIAN(_xlfn._xlws.FILTER(N:N, C:C="Y")), "Y", "N")} -> N | R26: N | S26: No | T26: N | U26: N | V26: Y | W26: always hooking up new construction, nothing significant though. New units, new connections, nothing else. | X26: N | Y26: =IF(C26="N", "", IF(AND(C26="Y", OR(AA26="Y", AB26="Y", AC26="Y", AD26="Y")), "Y", "N")) -> N | Z26: Y | AA26: N | AB26: N | AC26: N | AD26: N | AE26: Y | AF26: We implemented an impact fee. They are specifically to go to future expansion in water, sewer and streets. Things are starting to get expensive so they are worth planning for. | AG26: N | AH26: N | AI26: N | AJ26: N | AK26: N | AL26: Y | AM26: N | AN26: N | AO26: N | AP26: We went off of what is similar to the county | AQ26: NR | AR26: NR | AS26: Y | AT26: NR | AU26: Y | AV26: We do have a GIS system, not suited for basic water metering, mostly used for construction. Never used for asset valuation | AW26: N | AX26: N | AY26: N | BA26: When I do the budgetting for water, what we are looking at is how expenditures are chantging over the last year. Anything that we can forsee, like gas prices jumping, anything we think will be an impact we try to add that as a thought process for our budget. | BC26: went well. Interestingly the only partial planning GMA town that utilizes impact fees | BD26: 2158021 | BE26: FY2024 actual total expenditures, all funds (operating + capital/debt service). Source: WA State Auditor FIT, schedule1AggregationsByGovt (sections 30+35), MCAG 0518. portal.sao.wa.gov/FIT. | BF26: 75365 | BG26: =BF26 /M26 -> 83.738889 | BH26: 82353 | BI26: 0 | BJ26: FY2024 Schedule 09 via SAO FIT API (Snapshots/Schedule9s, MCAG 0518). Col E 'Outstanding Debt' = CALCULATED: total LT principal EXCLUDING pension/OPEB/compensated absences (excluded by debt-type code — reliable). Col F 'Official Total Liabilities' = DIRECT: grand total of the Schedule 09 as filed with SAO (all liabilities incl. pension/OPEB; no pattern matching). WATER/SEWER portion: none identifiable by keyword (may be $0, generically labeled, or held by a separate entity) [REGEX/KEYWORD — IMPRECISE]. | BK26: =BH26 / M26 -> 91.503333 | BL26: ='log(debt) vs log(pop.) normaliz'!H26 -> -2.4458085
A27: Okanogan | B27: Omak | C27: Y | F27: N | H27: Partially Planning | I27: N | L27: 4840 | M27: 4980 | N27: =((M27 - L27) / L27) * 100 -> 2.892562 | O27: {=IF(M27 > MEDIAN(_xlfn._xlws.FILTER(M:M, C:C="Y")),"Y","N")} -> Y | P27: =IF(N27 >= 10.15, "Y", "N") -> N | Q27: {=IF(N27 > MEDIAN(_xlfn._xlws.FILTER(N:N, C:C="Y")), "Y", "N")} -> N | R27: N | S27: No | T27: N | U27: N | V27: Y | W27: Developer driven. Just new connections | X27: N | Y27: =IF(C27="N", "", IF(AND(C27="Y", OR(AA27="Y", AB27="Y", AC27="Y", AD27="Y")), "Y", "N")) -> N | Z27: Y | AA27: N | AB27: N | AC27: N | AD27: N | AE27: Y | AF27: Developers develop it to our standards then we take it over. We use development fees for commissions, not sure what it is exactly though (between SDCs and CFCs). | AG27: N | AH27: Y | AI27: N | AJ27: N | AK27: N | AL27: N | AM27: N | AN27: N | AO27: N | AQ27: N/A | AR27: N/A | AS27: N/A | AT27: N/A | AU27: Y | AV27: We use G works for assets, GIS is a part of that too | AW27: Y | AX27: Y | AY27: N | BA27: [very short and to the point] | BC27: went alright, short and to the point | BD27: 19841594 | BE27: FY2024 actual total expenditures, all funds (operating + capital/debt service). Source: WA State Auditor FIT, schedule1AggregationsByGovt (sections 30+35), MCAG 0533. portal.sao.wa.gov/FIT. | BF27: 7519836 | BG27: =BF27 /M27 -> 1510.0072 | BH27: 10183577 | BI27: 1970301 | BJ27: FY2024 Schedule 09 via SAO FIT API (Snapshots/Schedule9s, MCAG 0533). Col E 'Outstanding Debt' = CALCULATED: total LT principal EXCLUDING pension/OPEB/compensated absences (excluded by debt-type code — reliable). Col F 'Official Total Liabilities' = DIRECT: grand total of the Schedule 09 as filed with SAO (all liabilities incl. pension/OPEB; no pattern matching). WATER/SEWER portion ~$1,970,301 [REGEX/KEYWORD — IMPRECISE: matched on debt-description text only (no fund tag in FIT); approximate]. | BK27: =BH27 / M27 -> 2044.895 | BL27: ='log(debt) vs log(pop.) normaliz'!H27 -> 0.55371187
A28: Okanogan | B28: Okanogan (city) | C28: N | H28: Partially Planning | L28: 2595 | M28: 2420 | N28: =((M28 - L28) / L28) * 100 -> -6.743738 | O28: {=IF(M28 > MEDIAN(_xlfn._xlws.FILTER(M:M, C:C="Y")),"Y","N")} -> Y | P28: =IF(N28 >= 10.15, "Y", "N") -> N | Q28: {=IF(N28 > MEDIAN(_xlfn._xlws.FILTER(N:N, C:C="Y")), "Y", "N")} -> N | Y28: =IF(C28="N", "", IF(AND(C28="Y", OR(AA28="Y", AB28="Y", AC28="Y", AD28="Y")), "Y", "N")) | BD28: 6189987 | BE28: FY2024 actual total expenditures, all funds (operating + capital/debt service). Source: WA State Auditor FIT, schedule1AggregationsByGovt (sections 30+35), MCAG 0531. portal.sao.wa.gov/FIT. | BF28: 1310586 | BG28: =BF28 /M28 -> 541.56446 | BH28: 1618092 | BI28: 947727 | BJ28: FY2024 Schedule 09 via SAO FIT API (Snapshots/Schedule9s, MCAG 0531). Col E 'Outstanding Debt' = CALCULATED: total LT principal EXCLUDING pension/OPEB/compensated absences (excluded by debt-type code — reliable). Col F 'Official Total Liabilities' = DIRECT: grand total of the Schedule 09 as filed with SAO (all liabilities incl. pension/OPEB; no pattern matching). WATER/SEWER portion ~$947,727 [REGEX/KEYWORD — IMPRECISE: matched on debt-description text only (no fund tag in FIT); approximate]. | BK28: =BH28 / M28 -> 668.63306 | BL28: ='log(debt) vs log(pop.) normaliz'!H28 -> -0.51893175
A29: Okanogan | B29: Brewster | C29: N | H29: Partially Planning | L29: 2380 | M29: 1995 | N29: =((M29 - L29) / L29) * 100 -> -16.176471 | O29: {=IF(M29 > MEDIAN(_xlfn._xlws.FILTER(M:M, C:C="Y")),"Y","N")} -> Y | P29: =IF(N29 >= 10.15, "Y", "N") -> N | Q29: {=IF(N29 > MEDIAN(_xlfn._xlws.FILTER(N:N, C:C="Y")), "Y", "N")} -> N | Y29: =IF(C29="N", "", IF(AND(C29="Y", OR(AA29="Y", AB29="Y", AC29="Y", AD29="Y")), "Y", "N")) | BD29: 8231324 | BE29: FY2024 actual total expenditures, all funds (operating + capital/debt service). Source: WA State Auditor FIT, schedule1AggregationsByGovt (sections 30+35), MCAG 0523. portal.sao.wa.gov/FIT. | BF29: 4054132 | BG29: =BF29 /M29 -> 2032.1464 | BH29: 5251721 | BI29: 806343 | BJ29: FY2024 Schedule 09 via SAO FIT API (Snapshots/Schedule9s, MCAG 0523). Col E 'Outstanding Debt' = CALCULATED: total LT principal EXCLUDING pension/OPEB/compensated absences (excluded by debt-type code — reliable). Col F 'Official Total Liabilities' = DIRECT: grand total of the Schedule 09 as filed with SAO (all liabilities incl. pension/OPEB; no pattern matching). WATER/SEWER portion ~$806,343 [REGEX/KEYWORD — IMPRECISE: matched on debt-description text only (no fund tag in FIT); approximate]. | BK29: =BH29 / M29 -> 2632.4416 | BL29: ='log(debt) vs log(pop.) normaliz'!H29 -> 0.86360189
A30: Okanogan | B30: Oroville | C30: Y | E30: city superintendent | F30: Y | G30: we are following it but we don’t have to | H30: Partially Planning | I30: N | J30: No | L30: 1700 | M30: 1815 | N30: =((M30 - L30) / L30) * 100 -> 6.7647059 | O30: {=IF(M30 > MEDIAN(_xlfn._xlws.FILTER(M:M, C:C="Y")),"Y","N")} -> N | P30: =IF(N30 >= 10.15, "Y", "N") -> N | Q30: {=IF(N30 > MEDIAN(_xlfn._xlws.FILTER(N:N, C:C="Y")), "Y", "N")} -> Y | R30: N | S30: Provide some to the county but not other towns | T30: N | U30: Y | V30: N | W30: Renewing mainlines. We have a graph that is supposed to run a larger line | X30: N | Y30: =IF(C30="N", "", IF(AND(C30="Y", OR(AA30="Y", AB30="Y", AC30="Y", AD30="Y")), "Y", "N")) -> N | Z30: Y | AA30: N | AB30: N | AC30: N | AD30: N | AE30: Y | AF30: We charge upfront fees (SDC or CFC), Not sure exactly what they are though | AG30: N | AH30: Y | AI30: N | AJ30: N | AK30: N | AL30: N | AM30: N | AN30: N | AO30: N | AP30: Doesn’t know | AQ30: N/A | AR30: N/A | AS30: N/A | AT30: N/A | AU30: Y | AV30: mainly for geographic understanding, not as much for asset valuation | AW30: Y | AX30: N | AY30: N | BC30: Short and to the point | BD30: 4802892 | BE30: FY2024 actual total expenditures, all funds (operating + capital/debt service). Source: WA State Auditor FIT, schedule1AggregationsByGovt (sections 30+35), MCAG 0535. portal.sao.wa.gov/FIT. | BF30: 959289 | BG30: =BF30 /M30 -> 528.53388 | BH30: 1751239 | BI30: 0 | BJ30: FY2024 Schedule 09 via SAO FIT API (Snapshots/Schedule9s, MCAG 0535). Col E 'Outstanding Debt' = CALCULATED: total LT principal EXCLUDING pension/OPEB/compensated absences (excluded by debt-type code — reliable). Col F 'Official Total Liabilities' = DIRECT: grand total of the Schedule 09 as filed with SAO (all liabilities incl. pension/OPEB; no pattern matching). WATER/SEWER portion: none identifiable by keyword (may be $0, generically labeled, or held by a separate entity) [REGEX/KEYWORD — IMPRECISE]. | BK30: =BH30 / M30 -> 964.86997 | BL30: ='log(debt) vs log(pop.) normaliz'!H30 -> -0.13414635
A31: Okanogan | B31: Tonasket | C31: Y | E31: City superintendent | F31: N | H31: Partially Planning | I31: N | J31: No, population stays right where its at. If anything it may have gone down because apple warehouses have shutdown and moved to chelan and wenatchee | K31: Survey had ~1,100 / ~1,100 — correct as rounded; OFM 1,110 / 1,090 | L31: 1110 | M31: 1085 | N31: =((M31 - L31) / L31) * 100 -> -2.2522523 | O31: {=IF(M31 > MEDIAN(_xlfn._xlws.FILTER(M:M, C:C="Y")),"Y","N")} -> N | P31: =IF(N31 >= 10.15, "Y", "N") -> N | Q31: {=IF(N31 > MEDIAN(_xlfn._xlws.FILTER(N:N, C:C="Y")), "Y", "N")} -> N | R31: N | S31: We do sell to people that are off grid, so they get a water permit and get some amount of water at a time. We don’t sell to any towns or organizations though. | T31: Y | U31: N | V31: N | W31: No. | X31: N | Y31: =IF(C31="N", "", IF(AND(C31="Y", OR(AA31="Y", AB31="Y", AC31="Y", AD31="Y")), "Y", "N")) -> N | Z31: N/A | AA31: N/A | AB31: N/A | AC31: N/A | AD31: N/A | AE31: Y | AF31: There is a hookup fee. Varies by pipe size. | AG31: N | AH31: N | AI31: Y | AJ31: N | AK31: N | AL31: N | AM31: N | AN31: N | AO31: Y | AP31: Standard fee for 3 quarter inch, then you pay the difference on if you want a bigger size. Called a Connection Fee. | AQ31: Y | AR31: N | AS31: N | AT31: N | AU31: Y | AV31: In the progress of putting something like that together. Probably will be used both for assets and for meters. Used to be hand read meters, now we use radio read which makes GIS necessary. | AW31: Y | AX31: Y | AY31: N | BC31: went well. | BD31: 4967321 | BE31: FY2024 actual total expenditures, all funds (operating + capital/debt service). Source: WA State Auditor FIT, schedule1AggregationsByGovt (sections 30+35), MCAG 0541. portal.sao.wa.gov/FIT. | BF31: 2774647 | BG31: =BF31 /M31 -> 2557.2783 | BH31: 3170033 | BI31: 2715727 | BJ31: FY2024 Schedule 09 via SAO FIT API (Snapshots/Schedule9s, MCAG 0541). Col E 'Outstanding Debt' = CALCULATED: total LT principal EXCLUDING pension/OPEB/compensated absences (excluded by debt-type code — reliable). Col F 'Official Total Liabilities' = DIRECT: grand total of the Schedule 09 as filed with SAO (all liabilities incl. pension/OPEB; no pattern matching). WATER/SEWER portion ~$2,715,727 [REGEX/KEYWORD — IMPRECISE: matched on debt-description text only (no fund tag in FIT); approximate]. | BK31: =BH31 / M31 -> 2921.6894 | BL31: ='log(debt) vs log(pop.) normaliz'!H31 -> 1.0060189
A32: Okanogan | B32: Pateros | C32: Y | E32: Jord, City Manager | F32: Y | G32: not required to comply to gma | H32: Partially Planning | I32: N | J32: 10 people have come, so no. We have around 600 people total. | K32: Survey had 590 / 600. OFM shows 525 (2015) → 610 (2025). 2015 figure differs due to a state-certified special census | L32: 665 | M32: 600 | N32: =((M32 - L32) / L32) * 100 -> -9.7744361 | O32: {=IF(M32 > MEDIAN(_xlfn._xlws.FILTER(M:M, C:C="Y")),"Y","N")} -> N | P32: =IF(N32 >= 10.15, "Y", "N") -> N | Q32: {=IF(N32 > MEDIAN(_xlfn._xlws.FILTER(N:N, C:C="Y")), "Y", "N")} -> N | R32: N | S32: no. | T32: N | U32: N | V32: Y | W32: one major expansion. Finished it in 2019 | X32: Y | Y32: =IF(C32="N", "", IF(AND(C32="Y", OR(AA32="Y", AB32="Y", AC32="Y", AD32="Y")), "Y", "N")) -> N | Z32: NR | AA32: NR | AB32: NR | AC32: NR | AD32: NR | AE32: Y | AF32: off the top of my head, It was a $7.2 million project, we borrowed 1 million. The rest was through legislative appropriations and grants. No levying of upfront devlopment fees. We are maxed out on developmnet, due to our geography (mountains on one side, water on the other). We only have about 40 acres left for potential development. | AG32: N | AH32: N | AI32: N | AJ32: N | AK32: N | AL32: N | AM32: Y | AN32: Y | AO32: N/A | AQ32: N/A | AR32: N/A | AS32: N/A | AT32: N/A | AU32: Y | AV32: Yes we use a GIS, we have an asset management program. We have GIS locations on them. We also use a radio read for meters. We have asset management in our Gis, but we don’t really use it for budgetting. We mainly use it as a historical tool to know what happened in the ground | AW32: Y | AX32: N | AY32: Y | BA32: [nothing more to add] | BC32: went well. | BD32: 2868407 | BE32: FY2024 actual total expenditures, all funds (operating + capital/debt service). Source: WA State Auditor FIT, schedule1AggregationsByGovt (sections 30+35), MCAG 0537. portal.sao.wa.gov/FIT. | BF32: 1740031 | BG32: =BF32 /M32 -> 2900.0517 | BH32: 1823648 | BI32: 1729798 | BJ32: FY2024 Schedule 09 via SAO FIT API (Snapshots/Schedule9s, MCAG 0537). Col E 'Outstanding Debt' = CALCULATED: total LT principal EXCLUDING pension/OPEB/compensated absences (excluded by debt-type code — reliable). Col F 'Official Total Liabilities' = DIRECT: grand total of the Schedule 09 as filed with SAO (all liabilities incl. pension/OPEB; no pattern matching). WATER/SEWER portion ~$1,729,798 [REGEX/KEYWORD — IMPRECISE: matched on debt-description text only (no fund tag in FIT); approximate]. | BK32: =BH32 / M32 -> 3039.4133 | BL32: ='log(debt) vs log(pop.) normaliz'!H32 -> 1.0826442
A33: Okanogan | B33: Twisp | C33: N | H33: Partially Planning | L33: 945 | M33: 1095 | N33: =((M33 - L33) / L33) * 100 -> 15.873016 | O33: {=IF(M33 > MEDIAN(_xlfn._xlws.FILTER(M:M, C:C="Y")),"Y","N")} -> N | P33: =IF(N33 >= 10.15, "Y", "N") -> Y | Q33: {=IF(N33 > MEDIAN(_xlfn._xlws.FILTER(N:N, C:C="Y")), "Y", "N")} -> Y | Y33: =IF(C33="N", "", IF(AND(C33="Y", OR(AA33="Y", AB33="Y", AC33="Y", AD33="Y")), "Y", "N")) | BD33: 9387311 | BE33: FY2024 actual total expenditures, all funds (operating + capital/debt service). Source: WA State Auditor FIT, schedule1AggregationsByGovt (sections 30+35), MCAG 0543. portal.sao.wa.gov/FIT. | BF33: 9540024 | BG33: =BF33 /M33 -> 8712.3507 | BH33: 9620144 | BI33: 3694016 | BJ33: FY2024 Schedule 09 via SAO FIT API (Snapshots/Schedule9s, MCAG 0543). Col E 'Outstanding Debt' = CALCULATED: total LT principal EXCLUDING pension/OPEB/compensated absences (excluded by debt-type code — reliable). Col F 'Official Total Liabilities' = DIRECT: grand total of the Schedule 09 as filed with SAO (all liabilities incl. pension/OPEB; no pattern matching). WATER/SEWER portion ~$3,694,016 [REGEX/KEYWORD — IMPRECISE: matched on debt-description text only (no fund tag in FIT); approximate]. | BK33: =BH33 / M33 -> 8785.5196 | BL33: ='log(debt) vs log(pop.) normaliz'!H33 -> 2.1063868
A34: Okanogan | B34: Winthrop | C34: Y | E34: superintendent, same as director | F34: N | G34: not growth management | H34: Partially Planning | I34: Y | J34: grown by 3 percent | L34: 435 | M34: 590 | N34: =((M34 - L34) / L34) * 100 -> 35.632184 | O34: {=IF(M34 > MEDIAN(_xlfn._xlws.FILTER(M:M, C:C="Y")),"Y","N")} -> N | P34: =IF(N34 >= 10.15, "Y", "N") -> Y | Q34: {=IF(N34 > MEDIAN(_xlfn._xlws.FILTER(N:N, C:C="Y")), "Y", "N")} -> Y | R34: N | S34: Sell bulk water to wells and people whos water goes dry | T34: Y | U34: Y | V34: Y | W34: We are in the process of expanding right now. Expanding by 263 connections last year, working on a second well, and rights for a third well, second well goes in in the summer | X34: N | Y34: =IF(C34="N", "", IF(AND(C34="Y", OR(AA34="Y", AB34="Y", AC34="Y", AD34="Y")), "Y", "N")) -> Y | Z34: Y | AA34: N | AB34: Y | AC34: N | AD34: N | AE34: Y | AF34: We use system development charges, we also upped our rate by 12 dollars. For the water distribution we take out loans from federal, we take as many grants as we can, but it’s a small population so hard to get that funding | AG34: Y | AH34: N | AI34: N | AJ34: Y | AK34: N | AL34: N | AM34: Y | AN34: N | AO34: Y | AP34: Through ERUs, just ERUs | AQ34: N | AR34: Y | AS34: N | AT34: N | AU34: Y | AV34: Presently working on that. WE will mostly be using for asset valuation. | AW34: Y | AX34: Y | AY34: N | BC34: Went well. Make sure to go by Jake not Jacob. | BD34: 5345426 | BE34: FY2024 actual total expenditures, all funds (operating + capital/debt service). Source: WA State Auditor FIT, schedule1AggregationsByGovt (sections 30+35), MCAG 0545. portal.sao.wa.gov/FIT. | BF34: 1430195 | BG34: =BF34 /M34 -> 2424.0593 | BH34: 1593864 | BI34: 1402487 | BJ34: FY2024 Schedule 09 via SAO FIT API (Snapshots/Schedule9s, MCAG 0545). Col E 'Outstanding Debt' = CALCULATED: total LT principal EXCLUDING pension/OPEB/compensated absences (excluded by debt-type code — reliable). Col F 'Official Total Liabilities' = DIRECT: grand total of the Schedule 09 as filed with SAO (all liabilities incl. pension/OPEB; no pattern matching). WATER/SEWER portion ~$1,402,487 [REGEX/KEYWORD — IMPRECISE: matched on debt-description text only (no fund tag in FIT); approximate]. | BK34: =BH34 / M34 -> 2701.4644 | BL34: ='log(debt) vs log(pop.) normaliz'!H34 -> 0.96582691
A35: Skamania | B35: Skamania County - General Public | C35: Y | E35: water manager | F35: Y | G35: non Gma. We're only managing water for carson and underwood | H35: Partially Planning | I35: N | J35: growth is not significant in comparison. | K35: Full county population (2015 → 2025) | L35: 11370 | M35: 12075 | N35: =((M35 - L35) / L35) * 100 -> 6.2005277 | O35: {=IF(M35 > MEDIAN(_xlfn._xlws.FILTER(M:M, C:C="Y")),"Y","N")} -> Y | P35: =IF(N35 >= 10.15, "Y", "N") -> N | Q35: {=IF(N35 > MEDIAN(_xlfn._xlws.FILTER(N:N, C:C="Y")), "Y", "N")} -> Y | R35: N | S35: no. | T35: N | U35: N | V35: Y | W35: yes. Continually expanding. Mostly just new connections | X35: N | Y35: =IF(C35="N", "", IF(AND(C35="Y", OR(AA35="Y", AB35="Y", AC35="Y", AD35="Y")), "Y", "N")) -> N | Z35: Y | AA35: N | AB35: N | AC35: N | AD35: N | AE35: Y | AF35: service area boundary isnt expanding. Upgrades to treatment plants, connection fees. | AG35: N | AH35: N | AI35: Y | AJ35: Y | AK35: N | AL35: N | AM35: N | AN35: N | AO35: Y | AP35: we cost of service analysis, huge number of variables. Calculated based off of growth primarily. We use system development fees | AQ35: N | AR35: N | AS35: N | AT35: Y | AU35: Y | AV35: yes, we use a gis tool for water metering. Used for customer billing in all of our enterprise software system | AW35: Y | AX35: Y | AY35: N | BA35: our fees are pretty high. Big variety of SDCs. We do whole electric systm, water is more localized. Stevenson and north bonnevile ddo their own. Skamania landing has their own water system. Rural systems do their own thing. They sometimes hire out contracotrs if they are real small. We are taking a preactive approach for repairs and older things breaking. | BB35: Skamania county public utilities district. Both towns manage their own. Gneral water utilities for other communities is the skamnaia county public utilities district. 5094275126. city of bonneville Cody rosander (5094275970). Not sure who to contact for bonneville. | BC35: Skamania county public utilities district. Both towns manage their own. Gneral water utilities for other communities is the skamnaia county public utilities district. 5094275126. city of bonneville Cody rosander (5094275970). Not sure who to contact for bonneville. | BD35: 23030924 | BE35: FIGURES ARE FOR Public Utility District No. 1 of Skamania County (MCAG 1798), the county's utility provider (per request). FY2024 total expenditures, all funds (FIT, sections 30+35). | BF35: 14107731 | BG35: =BF35 /M35 -> 1168.3421 | BH35: 15525458 | BI35: 3555783 | BJ35: Public Utility District No. 1 of Skamania County FY2024 Schedule 09 via FIT (MCAG 1798). Col E = CALCULATED debt excl. pension/OPEB/comp. absences; Col F = DIRECT filed Schedule 09 total. NOTE: a PUD is PRIMARILY AN ELECTRIC utility — most debt is electric, not water/sewer; not cleanly separable. WATER/SEWER portion ~$3,555,783 [REGEX/KEYWORD — IMPRECISE]. | BK35: =BH35 / M35 -> 1285.7522 | BL35: ='log(debt) vs log(pop.) normaliz'!H35 -> 0.034206895
A36: Skamania | B36: Stevenson | C36: Y | E36: Cody Rosander, Public works director of Stevenson | F36: N | G36: Found old census, still didn’t really understand what is meant by this. [giving him full wording "Growth management Act" didn’t change that] | H36: Partially Planning | I36: Y | J36: yes its grown pretty significantly. | L36: 1510 | M36: 1590 | N36: =((M36 - L36) / L36) * 100 -> 5.2980132 | O36: {=IF(M36 > MEDIAN(_xlfn._xlws.FILTER(M:M, C:C="Y")),"Y","N")} -> N | P36: =IF(N36 >= 10.15, "Y", "N") -> N | Q36: {=IF(N36 > MEDIAN(_xlfn._xlws.FILTER(N:N, C:C="Y")), "Y", "N")} -> Y | R36: N | S36: we have hydrant meters, not necessarily selling to other towns, but ppl can purchase water and we have out of boundary connections. We have some grandfathered in in connections that otherwise wouldnt be allowed today | T36: Y | U36: Y | V36: Y | W36: We've done a water main expansion. We replaced it with bigger size pipe. We are currently a surface level facility, with a failing water intake, loosing capacity not directly caused by population or residents. Growth definitely plays an impact into how much we need to produce, we are runing low and doing a lot of engineering work to redo our surface water system. We do have a ground water well, but not used as much. Under bedrock and header system, we seem to have significant damage. we used to pull an unlimiited amount, we seem more restricted to 3 to 4 hundred gallons per minute. This is a problem now with increasing demand, where it didnt used to be. | X36: N | Y36: =IF(C36="N", "", IF(AND(C36="Y", OR(AA36="Y", AB36="Y", AC36="Y", AD36="Y")), "Y", "N")) -> Y | Z36: Y | AA36: Y | AB36: Y | AC36: N | AD36: N | AE36: Y | AF36: Largly grants and general funds, coming out of the water budget itself. Primarily funded through SDCs and rate payments. | AG36: Y | AH36: N | AI36: N | AJ36: Y | AK36: N | AL36: N | AM36: Y | AN36: N | AO36: Y | AP36: I take a look at their health plan, how many water fixtures they have, how far from the mainline they are. Goes through a calculator that abides by the plumbing code. We do a tiered system. For instance a small house will have a fixture count of 18-22, anything below 25 will be our lowest tier SDC. Next tier is 30 fixtures, one tier above that as well (3 residential tiers total). We have a few seperate tiers for commercial as well. | AQ36: N | AR36: Y | AS36: N | AT36: Y | AU36: Y | AV36: We do use Gis for all of our public works assets. We do not use it for asset valuation, mostly material type and location. | AW36: Y | AX36: N | AY36: N | AZ36: N/A | BA36: We try to incentivize multi home and commercial development. We are likely going to need to increase our rates within the next year to pay for our network. We raised our SDCs maybe 3-4 years ago. They are already on the higher side. They were pretty cheap before then. | BD36: 12256562 | BE36: FY2024 actual total expenditures, all funds (operating + capital/debt service). Source: WA State Auditor FIT, schedule1AggregationsByGovt (sections 30+35), MCAG 0652. portal.sao.wa.gov/FIT. | BF36: 12113850 | BG36: =BF36 /M36 -> 7618.7736 | BH36: 12285634 | BI36: 10219872 | BJ36: FY2024 Schedule 09 via SAO FIT API (Snapshots/Schedule9s, MCAG 0652). Col E 'Outstanding Debt' = CALCULATED: total LT principal EXCLUDING pension/OPEB/compensated absences (excluded by debt-type code — reliable). Col F 'Official Total Liabilities' = DIRECT: grand total of the Schedule 09 as filed with SAO (all liabilities incl. pension/OPEB; no pattern matching). WATER/SEWER portion ~$10,219,872 [REGEX/KEYWORD — IMPRECISE: matched on debt-description text only (no fund tag in FIT); approximate]. ~$10.3M WWTP build via ~$9.7M Dept of Ecology loan. | BK36: =BH36 / M36 -> 7726.8138 | BL36: ='log(debt) vs log(pop.) normaliz'!H36 -> 1.9546059
A37: Skamania | B37: North Bonneville | C37: N | H37: Partially Planning | L37: 1005 | M37: 985 | N37: =((M37 - L37) / L37) * 100 -> -1.9900498 | O37: {=IF(M37 > MEDIAN(_xlfn._xlws.FILTER(M:M, C:C="Y")),"Y","N")} -> N | P37: =IF(N37 >= 10.15, "Y", "N") -> N | Q37: {=IF(N37 > MEDIAN(_xlfn._xlws.FILTER(N:N, C:C="Y")), "Y", "N")} -> N | Y37: =IF(C37="N", "", IF(AND(C37="Y", OR(AA37="Y", AB37="Y", AC37="Y", AD37="Y")), "Y", "N")) | BD37: 1737117 | BE37: FY2024 actual total expenditures, all funds (operating + capital/debt service). Source: WA State Auditor FIT, schedule1AggregationsByGovt (sections 30+35), MCAG 0650. portal.sao.wa.gov/FIT. | BF37: 188892 | BG37: =BF37 /M37 -> 191.76853 | BH37: 214835 | BI37: 111198 | BJ37: FY2024 Schedule 09 via SAO FIT API (Snapshots/Schedule9s, MCAG 0650). Col E 'Outstanding Debt' = CALCULATED: total LT principal EXCLUDING pension/OPEB/compensated absences (excluded by debt-type code — reliable). Col F 'Official Total Liabilities' = DIRECT: grand total of the Schedule 09 as filed with SAO (all liabilities incl. pension/OPEB; no pattern matching). WATER/SEWER portion ~$111,198 [REGEX/KEYWORD — IMPRECISE: matched on debt-description text only (no fund tag in FIT); approximate]. | BK37: =BH37 / M37 -> 218.1066 | BL37: ='log(debt) vs log(pop.) normaliz'!H37 -> -1.5828552
A38: Wahkiakum | B38: Wahkiakum County - General Publ | C38: N | F38: Y | G38: non-planning | H38: Partially Planning | I38: N | J38: I wouldn’t say significantly, only 45 hundred in the full county | L38: 4010 | M38: 4550 | N38: =((M38 - L38) / L38) * 100 -> 13.466334 | O38: {=IF(M38 > MEDIAN(_xlfn._xlws.FILTER(M:M, C:C="Y")),"Y","N")} -> Y | P38: =IF(N38 >= 10.15, "Y", "N") -> Y | Q38: {=IF(N38 > MEDIAN(_xlfn._xlws.FILTER(N:N, C:C="Y")), "Y", "N")} -> Y | R38: Y | S38: Only one encoroporated town in the county. Wakiakum , wakikum pud #1 controls all of the water | T38: NR | U38: N | V38: N/A | W38: we arent involved | X38: N | Y38: =IF(C38="N", "", IF(AND(C38="Y", OR(AA38="Y", AB38="Y", AC38="Y", AD38="Y")), "Y", "N")) | Z38: N/A | AA38: N/A | AB38: N/A | AC38: N/A | AD38: N/A | BA38: daniel K is manager. 360- 795-3266 | BD38: 7189341 | BE38: FIGURES ARE FOR Public Utility District No. 1 of Wahkiakum County (MCAG 1804), the county's utility provider (per request). FY2024 total expenditures, all funds (FIT, sections 30+35). | BF38: 141314 | BG38: =BF38 /M38 -> 31.058022 | BH38: 560544 | BJ38: Public Utility District No. 1 of Wahkiakum County FY2024 Schedule 09 via FIT (MCAG 1804). Col E = CALCULATED debt excl. pension/OPEB/comp. absences; Col F = DIRECT filed Schedule 09 total. NOTE: a PUD is PRIMARILY AN ELECTRIC utility — most debt is electric, not water/sewer; not cleanly separable. WATER/SEWER portion: none identifiable by keyword [IMPRECISE]. | BK38: =BH38 / M38 -> 123.19648 | BL38: ='log(debt) vs log(pop.) normaliz'!H38 -> -2.2499506
A39: Wahkiakum | B39: Cathlamet | C39: N | H39: Partially Planning | L39: 500 | M39: 580 | N39: =((M39 - L39) / L39) * 100 -> 16 | O39: {=IF(M39 > MEDIAN(_xlfn._xlws.FILTER(M:M, C:C="Y")),"Y","N")} -> N | P39: =IF(N39 >= 10.15, "Y", "N") -> Y | Q39: {=IF(N39 > MEDIAN(_xlfn._xlws.FILTER(N:N, C:C="Y")), "Y", "N")} -> Y | Y39: =IF(C39="N", "", IF(AND(C39="Y", OR(AA39="Y", AB39="Y", AC39="Y", AD39="Y")), "Y", "N")) | BB39: Over text: "Hey Rowan sorry I missed your call. I got your message. I don’t deal withg the water or sewer. Our PUD has all of that now. You may want to contact them. Have a great rest of your day. Troy Gorley" | BC39: ^^Cathlamet's sewer and fresh water is now entirely handled by the PUD. | BD39: 2988781 | BE39: FY2024 actual total expenditures, all funds (operating + capital/debt service). Source: WA State Auditor FIT, schedule1AggregationsByGovt (sections 30+35), MCAG 0764. portal.sao.wa.gov/FIT. | BF39: 5462684 | BG39: =BF39 /M39 -> 9418.4207 | BH39: 5544678 | BI39: 4621496 | BJ39: FY2024 Schedule 09 via SAO FIT API (Snapshots/Schedule9s, MCAG 0764). Col E 'Outstanding Debt' = CALCULATED: total LT principal EXCLUDING pension/OPEB/compensated absences (excluded by debt-type code — reliable). Col F 'Official Total Liabilities' = DIRECT: grand total of the Schedule 09 as filed with SAO (all liabilities incl. pension/OPEB; no pattern matching). WATER/SEWER portion ~$4,621,496 [REGEX/KEYWORD — IMPRECISE: matched on debt-description text only (no fund tag in FIT); approximate]. | BK39: =BH39 / M39 -> 9559.7897 | BL39: ='log(debt) vs log(pop.) normaliz'!H39 -> 2.2306699
A40: Whitman | B40: Pullman | C40: N | H40: Partially Planning | L40: 31420 | M40: 33680 | N40: =((M40 - L40) / L40) * 100 -> 7.1928708 | O40: {=IF(M40 > MEDIAN(_xlfn._xlws.FILTER(M:M, C:C="Y")),"Y","N")} -> Y | P40: =IF(N40 >= 10.15, "Y", "N") -> N | Q40: {=IF(N40 > MEDIAN(_xlfn._xlws.FILTER(N:N, C:C="Y")), "Y", "N")} -> Y | Y40: =IF(C40="N", "", IF(AND(C40="Y", OR(AA40="Y", AB40="Y", AC40="Y", AD40="Y")), "Y", "N")) | BD40: 137148102 | BE40: FY2024 actual total expenditures, all funds (operating + capital/debt service). Source: WA State Auditor FIT, schedule1AggregationsByGovt (sections 30+35), MCAG 0820. portal.sao.wa.gov/FIT. | BF40: 12361282 | BG40: =BF40 /M40 -> 367.02144 | BH40: 21214275 | BI40: 0 | BJ40: FY2024 Schedule 09 via SAO FIT API (Snapshots/Schedule9s, MCAG 0820). Col E 'Outstanding Debt' = CALCULATED: total LT principal EXCLUDING pension/OPEB/compensated absences (excluded by debt-type code — reliable). Col F 'Official Total Liabilities' = DIRECT: grand total of the Schedule 09 as filed with SAO (all liabilities incl. pension/OPEB; no pattern matching). WATER/SEWER portion ~$2,461,643 [REGEX/KEYWORD — IMPRECISE: matched on debt-description text only (no fund tag in FIT); approximate]. W/S = 'Non Voted Utility Bond A'; Ecology loan now $0. | BK40: =BH40 / M40 -> 629.87752 | BL40: ='log(debt) vs log(pop.) normaliz'!H40 -> -0.74364617
A41: Whitman | B41: Colfax | C41: N | H41: Partially Planning | L41: 2765 | M41: 2785 | N41: =((M41 - L41) / L41) * 100 -> 0.72332731 | O41: {=IF(M41 > MEDIAN(_xlfn._xlws.FILTER(M:M, C:C="Y")),"Y","N")} -> Y | P41: =IF(N41 >= 10.15, "Y", "N") -> N | Q41: {=IF(N41 > MEDIAN(_xlfn._xlws.FILTER(N:N, C:C="Y")), "Y", "N")} -> N | Y41: =IF(C41="N", "", IF(AND(C41="Y", OR(AA41="Y", AB41="Y", AC41="Y", AD41="Y")), "Y", "N")) | BD41: 6061259 | BE41: FY2024 actual total expenditures, all funds (operating + capital/debt service). Source: WA State Auditor FIT, schedule1AggregationsByGovt (sections 30+35), MCAG 0799. portal.sao.wa.gov/FIT. | BF41: 0 | BG41: =BF41 /M41 -> 0 | BH41: 133034 | BI41: 0 | BJ41: FY2024 Schedule 09 via SAO FIT API (Snapshots/Schedule9s, MCAG 0799). Col E 'Outstanding Debt' = CALCULATED: total LT principal EXCLUDING pension/OPEB/compensated absences (excluded by debt-type code — reliable). Col F 'Official Total Liabilities' = DIRECT: grand total of the Schedule 09 as filed with SAO (all liabilities incl. pension/OPEB; no pattern matching). WATER/SEWER portion: none identifiable by keyword (may be $0, generically labeled, or held by a separate entity) [REGEX/KEYWORD — IMPRECISE]. Real debt $0: only liabilities were compensated absences (not debt). | BK41: =BH41 / M41 -> 47.768043 | BL41: ='log(debt) vs log(pop.) normaliz'!H41 -> -3.1666135
A42: Whitman | B42: Palouse | C42: Y | E42: Misty, City administrator of Palouse | F42: N | G42: Doesn’t know GMA status, redoing comprehensive plan. | H42: Partially Planning | I42: N | J42: Not significantly. Nothing over 10 percent or 15 percent. Our infrastructure is old. We cant really put a lot more pressure on it. No anexations. | L42: 1030 | M42: 1055 | N42: =((M42 - L42) / L42) * 100 -> 2.4271845 | O42: {=IF(M42 > MEDIAN(_xlfn._xlws.FILTER(M:M, C:C="Y")),"Y","N")} -> N | P42: =IF(N42 >= 10.15, "Y", "N") -> N | Q42: {=IF(N42 > MEDIAN(_xlfn._xlws.FILTER(N:N, C:C="Y")), "Y", "N")} -> N | R42: N | S42: no. | T42: N | U42: N | V42: N | W42: Not expand, just update. | X42: N | Y42: =IF(C42="N", "", IF(AND(C42="Y", OR(AA42="Y", AB42="Y", AC42="Y", AD42="Y")), "Y", "N")) -> N | Z42: NR | AA42: NR | AB42: NR | AC42: NR | AD42: NR | AE42: Y | AF42: Fund upgrades to the existing system through Public works loans, trust fund loans. Big upgrade was in 2022 around $1 million. No upfront fees, no annexation or allotments for development in the last 10 years | AG42: N | AH42: N | AI42: N | AJ42: N | AK42: N | AL42: N | AM42: Y | AN42: N | AO42: N/A | AQ42: N/A | AR42: N/A | AS42: N/A | AT42: N/A | AU42: N | AV42: No GIS tool. 2014 we paid for a survey to come in, had them mark where all our water and sewer lines are, but not super accurate. | AW42: N/A | AX42: N/A | AY42: N/A | BA42: We are a small town that can't grow. | BC42: Went well. Town has no plans for expansion, simply doesn’t allow for that contingency | BD42: 2112535 | BE42: FY2024 actual total expenditures, all funds (operating + capital/debt service). Source: WA State Auditor FIT, schedule1AggregationsByGovt (sections 30+35), MCAG 0818. portal.sao.wa.gov/FIT. | BF42: 1268804 | BG42: =BF42 /M42 -> 1202.6578 | BH42: 1301015 | BI42: 1020899 | BJ42: FY2024 Schedule 09 via SAO FIT API (Snapshots/Schedule9s, MCAG 0818). Col E 'Outstanding Debt' = CALCULATED: total LT principal EXCLUDING pension/OPEB/compensated absences (excluded by debt-type code — reliable). Col F 'Official Total Liabilities' = DIRECT: grand total of the Schedule 09 as filed with SAO (all liabilities incl. pension/OPEB; no pattern matching). WATER/SEWER portion ~$1,020,899 [REGEX/KEYWORD — IMPRECISE: matched on debt-description text only (no fund tag in FIT); approximate]. | BK42: =BH42 / M42 -> 1233.1896 | BL42: ='log(debt) vs log(pop.) normaliz'!H42 -> 0.14521788
A43: Whitman | B43: Tekoa | C43: N | H43: Partially Planning | L43: 775 | M43: 820 | N43: =((M43 - L43) / L43) * 100 -> 5.8064516 | O43: {=IF(M43 > MEDIAN(_xlfn._xlws.FILTER(M:M, C:C="Y")),"Y","N")} -> N | P43: =IF(N43 >= 10.15, "Y", "N") -> N | Q43: {=IF(N43 > MEDIAN(_xlfn._xlws.FILTER(N:N, C:C="Y")), "Y", "N")} -> Y | Y43: =IF(C43="N", "", IF(AND(C43="Y", OR(AA43="Y", AB43="Y", AC43="Y", AD43="Y")), "Y", "N")) | BD43: 2326645 | BE43: FY2023 actual total expenditures, all funds (operating + capital/debt service). Source: WA State Auditor FIT, schedule1AggregationsByGovt (sections 30+35), MCAG 0827. portal.sao.wa.gov/FIT. | BF43: 3248869 | BG43: =BF43 /M43 -> 3962.0354 | BH43: 3748653 | BI43: 2528928 | BJ43: FY2023 Schedule 09 via SAO FIT API (Snapshots/Schedule9s, MCAG 0827). Col E 'Outstanding Debt' = CALCULATED: total LT principal EXCLUDING pension/OPEB/compensated absences (excluded by debt-type code — reliable). Col F 'Official Total Liabilities' = DIRECT: grand total of the Schedule 09 as filed with SAO (all liabilities incl. pension/OPEB; no pattern matching). WATER/SEWER portion ~$2,528,928 [REGEX/KEYWORD — IMPRECISE: matched on debt-description text only (no fund tag in FIT); approximate]. | BK43: =BH43 / M43 -> 4571.528 | BL43: ='log(debt) vs log(pop.) normaliz'!H43 -> 1.4712524
A44: Whitman | B44: Rosalia | C44: N | H44: Partially Planning | L44: 555 | M44: 585 | N44: =((M44 - L44) / L44) * 100 -> 5.4054054 | O44: {=IF(M44 > MEDIAN(_xlfn._xlws.FILTER(M:M, C:C="Y")),"Y","N")} -> N | P44: =IF(N44 >= 10.15, "Y", "N") -> N | Q44: {=IF(N44 > MEDIAN(_xlfn._xlws.FILTER(N:N, C:C="Y")), "Y", "N")} -> Y | Y44: =IF(C44="N", "", IF(AND(C44="Y", OR(AA44="Y", AB44="Y", AC44="Y", AD44="Y")), "Y", "N")) | BD44: 1210429 | BE44: FY2024 actual total expenditures, all funds (operating + capital/debt service). Source: WA State Auditor FIT, schedule1AggregationsByGovt (sections 30+35), MCAG 0823. portal.sao.wa.gov/FIT. | BF44: 915259 | BG44: =BF44 /M44 -> 1564.5453 | BH44: 1095706 | BI44: 0 | BJ44: FY2024 Schedule 09 via SAO FIT API (Snapshots/Schedule9s, MCAG 0823). Col E 'Outstanding Debt' = CALCULATED: total LT principal EXCLUDING pension/OPEB/compensated absences (excluded by debt-type code — reliable). Col F 'Official Total Liabilities' = DIRECT: grand total of the Schedule 09 as filed with SAO (all liabilities incl. pension/OPEB; no pattern matching). WATER/SEWER portion: none identifiable by keyword (may be $0, generically labeled, or held by a separate entity) [REGEX/KEYWORD — IMPRECISE]. | BK44: =BH44 / M44 -> 1873.0017 | BL44: ='log(debt) vs log(pop.) normaliz'!H44 -> 0.60010857
C50: Response type Key: | E50: <FI> = Factual Information
E51: <CM> = Calculated Metric
E52: <IR> = Interviewee Response
E53: <DI> = Data interpretation
P64: Median pop grow (all) | Q64: =MEDIAN(N:N) -> 5.3517093
P66: Median pop grow (sample) | Q66: {=MEDIAN(_xlfn._xlws.FILTER(N:N, C:C="Y"))} -> 2.892562

Sheet log(debt) vs log(pop.) normaliz
A2: County | B2: Town | C2: Useful Survey Participation <DI> (Y/N) | D2: Official Total Liabilities ($) [DIRECT — official Schedule 09 filed total, all liabilities] <FI> | E2: Natural log of Debt <CM> | F2: Natural log of Population <CM> | G2: Predicted Debt <CM> | H2: Debt to Population regression residuals <CM> | M2: Slope | N2: Intercept
A3: Adams | B3: Othello | C3: Y | D3: 7816828 | E3: =LN('Full survey table'!BH3) -> 15.871789 | F3: =LN('Full survey table'!M3) -> 9.1209626 | G3: =N3 + M3 * F3 -> 16.228439 | H3: =E3 - G3 -> -0.35664911 | M3: {=SLOPE(_xlfn._xlws.FILTER(E3:E44,C3:C44="Y"),_xlfn._xlws.FILTER(F3:F44,C3:C44="Y"))} -> 1.0626646 | N3: {=INTERCEPT(_xlfn._xlws.FILTER(E3:E44,C3:C44="Y"),_xlfn._xlws.FILTER(F3:F44,C3:C44="Y"))} -> 6.5359147
A4: Adams | B4: Ritzville | C4: N | D4: 7424624 | E4: =LN('Full survey table'!BH4) -> 15.820313 | F4: =LN('Full survey table'!M4) -> 7.4899709 | G4: =N3 + M3 * F4 -> 14.495241 | H4: =E4 - G4 -> 1.3250712
A5: Asotin | B5: Clarkston [Asotin PUD] | C5: Y | D5: 5933169 | E5: =LN('Full survey table'!BH5) -> 15.596069 | F5: =LN('Full survey table'!M5) -> 8.8873765 | G5: =N3 + M3 * F5 -> 15.980215 | H5: =E5 - G5 -> -0.38414583
A6: Woodland | B6: Longview | C6: Y | D6: 63665714 | E6: =LN('Full survey table'!BH6) -> 17.969157 | F6: =LN('Full survey table'!M6) -> 10.551376 | G6: =N3 + M3 * F6 -> 17.748488 | H6: =E6 - G6 -> 0.22066871
A7: Cowlitz | B7: Kelso | C7: N | D7: 18018433 | E7: =LN('Full survey table'!BH7) -> 16.706906 | F7: =LN('Full survey table'!M7) -> 9.4556367 | G7: =N3 + M3 * F7 -> 16.584085 | H7: =E7 - G7 -> 0.12282095
A8: Cowlitz | B8: Castle Rock | C8: N | D8: 6060122 | E8: =LN('Full survey table'!BH8) -> 15.61724 | F8: =LN('Full survey table'!M8) -> 7.8099471 | G8: =N3 + M3 * F8 -> 14.835269 | H8: =E8 - G8 -> 0.78197168
A9: Cowlitz | B9: Woodland | C9: Y | D9: 7023570 | E9: =LN('Full survey table'!BH9) -> 15.764782 | F9: =LN('Full survey table'!M9) -> 8.7910299 | G9: =N3 + M3 * F9 -> 15.877831 | H9: =E9 - G9 -> -0.11304852
A10: Cowlitz | B10: Kalama | C10: N | D10: 4170942 | E10: =LN('Full survey table'!BH10) -> 15.243652 | F10: =LN('Full survey table'!M10) -> 8.0583273 | G10: =N3 + M3 * F10 -> 15.099214 | H10: =E10 - G10 -> 0.1444388
A11: Ferry | B11: Republic | C11: Y | D11: 432112 | E11: =LN('Full survey table'!BH11) -> 12.97644 | F11: =LN('Full survey table'!M11) -> 6.9127428 | G11: =N3 + M3 * F11 -> 13.881842 | H11: =E11 - G11 -> -0.90540152
A12: Grays Harbor | B12: Aberdeen | C12: Y | D12: 38656768 | E12: =LN('Full survey table'!BH12) -> 17.470232 | F12: =LN('Full survey table'!M12) -> 9.7468337 | G12: =N3 + M3 * F12 -> 16.89353 | H12: =E12 - G12 -> 0.57670278
A13: Grays Harbor | B13: Hoquiam | C13: N | D13: 25208098 | E13: =LN('Full survey table'!BH13) -> 17.042676 | F13: =LN('Full survey table'!M13) -> 9.082507 | G13: =N3 + M3 * F13 -> 16.187573 | H13: =E13 - G13 -> 0.8551027
A14: Grays Harbor | B14: Ocean Shores | C14: N | D14: 14252693 | E14: =LN('Full survey table'!BH14) -> 16.472456 | F14: =LN('Full survey table'!M14) -> 8.9398431 | G14: =N3 + M3 * F14 -> 16.035969 | H14: =E14 - G14 -> 0.43648713
A15: Grays Harbor | B15: Montesano | C15: N | D15: 3976430 | E15: =LN('Full survey table'!BH15) -> 15.195895 | F15: =LN('Full survey table'!M15) -> 8.3272426 | G15: =N3 + M3 * F15 -> 15.38498 | H15: =E15 - G15 -> -0.18908544
A16: Grays Harbor | B16: Elma | C16: Y | D16: 1840144 | E16: =LN('Full survey table'!BH16) -> 14.425354 | F16: =LN('Full survey table'!M16) -> 8.1619458 | G16: =N3 + M3 * F16 -> 15.209325 | H16: =E16 - G16 -> -0.78397098
A17: Grays Harbor | B17: Westport | C17: N | D17: 13565568 | E17: =LN('Full survey table'!BH17) -> 16.423045 | F17: =LN('Full survey table'!M17) -> 7.7514753 | G17: =N3 + M3 * F17 -> 14.773133 | H17: =E17 - G17 -> 1.6499124
A18: Grays Harbor | B18: Cosmopolis | C18: N | D18: 3400333 | E18: =LN('Full survey table'!BH18) -> 15.039384 | F18: =LN('Full survey table'!M18) -> 7.4265491 | G18: =N3 + M3 * F18 -> 14.427845 | H18: =E18 - G18 -> 0.61153861
A19: Klickitat | B19: Goldendale | C19: N | D19: 10136406 | E19: =LN('Full survey table'!BH19) -> 16.131644 | F19: =LN('Full survey table'!M19) -> 8.1647948 | G19: =N3 + M3 * F19 -> 15.212353 | H19: =E19 - G19 -> 0.91929115
A20: Klickitat | B20: White Salmon | C20: N | D20: 10849934 | E20: =LN('Full survey table'!BH20) -> 16.19967 | F20: =LN('Full survey table'!M20) -> 7.8438486 | G20: =N3 + M3 * F20 -> 14.871295 | H20: =E20 - G20 -> 1.3283748
A21: Klickitat | B21: Bingen | C21: N | D21: 5049557 | E21: =LN('Full survey table'!BH21) -> 15.434811 | F21: =LN('Full survey table'!M21) -> 6.6592939 | G21: =N3 + M3 * F21 -> 13.61251 | H21: =E21 - G21 -> 1.8223006
A22: Lincoln | B22: Davenport | C22: Y | D22: 461657 | E22: =LN('Full survey table'!BH22) -> 13.042577 | F22: =LN('Full survey table'!M22) -> 7.4558767 | G22: =N3 + M3 * F22 -> 14.459011 | H22: =E22 - G22 -> -1.4164333
A23: Lincoln | B23: Odessa | C23: N | D23: 2879663 | E23: =LN('Full survey table'!BH23) -> 14.873184 | F23: =LN('Full survey table'!M23) -> 6.7968237 | G23: =N3 + M3 * F23 -> 13.758658 | H23: =E23 - G23 -> 1.1145253
A24: Lincoln | B24: Harrington | C24: N | D24: 36817 | E24: =LN('Full survey table'!BH24) -> 10.513715 | F24: =LN('Full survey table'!M24) -> 6.075346 | G24: =N3 + M3 * F24 -> 12.99197 | H24: =E24 - G24 -> -2.4782547
A25: Lincoln | B25: Reardan | C25: N | D25: 407362 | E25: =LN('Full survey table'!BH25) -> 12.917458 | F25: =LN('Full survey table'!M25) -> 6.4846352 | G25: =N3 + M3 * F25 -> 13.426907 | H25: =E25 - G25 -> -0.50944934
A26: Lincoln | B26: Wilbur | C26: Y | D26: 82353 | E26: =LN('Full survey table'!BH26) -> 11.31877 | F26: =LN('Full survey table'!M26) -> 6.8023948 | G26: =N3 + M3 * F26 -> 13.764579 | H26: =E26 - G26 -> -2.4458085
A27: Okanogan | B27: Omak | C27: Y | D27: 10183577 | E27: =LN('Full survey table'!BH27) -> 16.136287 | F27: =LN('Full survey table'!M27) -> 8.5131852 | G27: =N3 + M3 * F27 -> 15.582575 | H27: =E27 - G27 -> 0.55371187
A28: Okanogan | B28: Okanogan (city) | C28: N | D28: 1618092 | E28: =LN('Full survey table'!BH28) -> 14.296758 | F28: =LN('Full survey table'!M28) -> 7.7915228 | G28: =N3 + M3 * F28 -> 14.81569 | H28: =E28 - G28 -> -0.51893175
A29: Okanogan | B29: Brewster | C29: N | D29: 5251721 | E29: =LN('Full survey table'!BH29) -> 15.474066 | F29: =LN('Full survey table'!M29) -> 7.5983993 | G29: =N3 + M3 * F29 -> 14.610464 | H29: =E29 - G29 -> 0.86360189
A30: Okanogan | B30: Oroville | C30: Y | D30: 1751239 | E30: =LN('Full survey table'!BH30) -> 14.375834 | F30: =LN('Full survey table'!M30) -> 7.5038407 | G30: =N3 + M3 * F30 -> 14.50998 | H30: =E30 - G30 -> -0.13414635
A31: Okanogan | B31: Tonasket | C31: Y | D31: 3170033 | E31: =LN('Full survey table'!BH31) -> 14.969253 | F31: =LN('Full survey table'!M31) -> 6.9893353 | G31: =N3 + M3 * F31 -> 13.963234 | H31: =E31 - G31 -> 1.0060189
A32: Okanogan | B32: Pateros | C32: Y | D32: 1823648 | E32: =LN('Full survey table'!BH32) -> 14.416349 | F32: =LN('Full survey table'!M32) -> 6.3969297 | G32: =N3 + M3 * F32 -> 13.333705 | H32: =E32 - G32 -> 1.0826442
A33: Okanogan | B33: Twisp | C33: N | D33: 9620144 | E33: =LN('Full survey table'!BH33) -> 16.07937 | F33: =LN('Full survey table'!M33) -> 6.9985096 | G33: =N3 + M3 * F33 -> 13.972983 | H33: =E33 - G33 -> 2.1063868
A34: Okanogan | B34: Winthrop | C34: Y | D34: 1593864 | E34: =LN('Full survey table'!BH34) -> 14.281672 | F34: =LN('Full survey table'!M34) -> 6.3801225 | G34: =N3 + M3 * F34 -> 13.315845 | H34: =E34 - G34 -> 0.96582691
A35: Skamania | B35: Skamania County - General Public | C35: Y | D35: 15525458 | E35: =LN('Full survey table'!BH35) -> 16.557992 | F35: =LN('Full survey table'!M35) -> 9.3988925 | G35: =N3 + M3 * F35 -> 16.523785 | H35: =E35 - G35 -> 0.034206895
A36: Skamania | B36: Stevenson | C36: Y | D36: 12285634 | E36: =LN('Full survey table'!BH36) -> 16.323941 | F36: =LN('Full survey table'!M36) -> 7.3714893 | G36: =N3 + M3 * F36 -> 14.369335 | H36: =E36 - G36 -> 1.9546059
A37: Skamania | B37: North Bonneville | C37: N | D37: 214835 | E37: =LN('Full survey table'!BH37) -> 12.277626 | F37: =LN('Full survey table'!M37) -> 6.8926416 | G37: =N3 + M3 * F37 -> 13.860481 | H37: =E37 - G37 -> -1.5828552
A38: Wahkiakum | B38: Wahkiakum County - General Publ | C38: N | D38: 560544 | E38: =LN('Full survey table'!BH38) -> 13.236663 | F38: =LN('Full survey table'!M38) -> 8.4228825 | G38: =N3 + M3 * F38 -> 15.486614 | H38: =E38 - G38 -> -2.2499506
A39: Wahkiakum | B39: Cathlamet | C39: N | D39: 5544678 | E39: =LN('Full survey table'!BH39) -> 15.528349 | F39: =LN('Full survey table'!M39) -> 6.3630281 | G39: =N3 + M3 * F39 -> 13.297679 | H39: =E39 - G39 -> 2.2306699
A40: Whitman | B40: Pullman | C40: N | D40: 21214275 | E40: =LN('Full survey table'!BH40) -> 16.870185 | F40: =LN('Full survey table'!M40) -> 10.424659 | G40: =N3 + M3 * F40 -> 17.613831 | H40: =E40 - G40 -> -0.74364617
A41: Whitman | B41: Colfax | C41: N | D41: 133034 | E41: =LN('Full survey table'!BH41) -> 11.79836 | F41: =LN('Full survey table'!M41) -> 7.9320032 | G41: =N3 + M3 * F41 -> 14.964973 | H41: =E41 - G41 -> -3.1666135
A42: Whitman | B42: Palouse | C42: Y | D42: 1301015 | E42: =LN('Full survey table'!BH42) -> 14.078655 | F42: =LN('Full survey table'!M42) -> 6.961296 | G42: =N3 + M3 * F42 -> 13.933437 | H42: =E42 - G42 -> 0.14521788
A43: Whitman | B43: Tekoa | C43: N | D43: 3748653 | E43: =LN('Full survey table'!BH43) -> 15.136907 | F43: =LN('Full survey table'!M43) -> 6.7093043 | G43: =N3 + M3 * F43 -> 13.665655 | H43: =E43 - G43 -> 1.4712524
A44: Whitman | B44: Rosalia | C44: N | D44: 1095706 | E44: =LN('Full survey table'!BH44) -> 13.906909 | F44: =LN('Full survey table'!M44) -> 6.3716118 | G44: =N3 + M3 * F44 -> 13.306801 | H44: =E44 - G44 -> 0.60010857

Sheet GMA & Pop fact check
C1: Q2: Knowledge of GMA status? | D1: Q3: Population growth in last 10 years?
A2: County | B2: Town | C2: Fact Check (Post-Survey): Actual County GMA status | D2: Pre-growth population (2015, per OFM) | E2: Current population (2025, per OFM) | F2: Notes / Survey Comparison
A3: Adams | B3: Othello | C3: Partially Planning | D3: 7780 | E3: 9210 | F3: Survey had 7,500 / 9,000 (close to OFM 7,780 / 9,210)
A4: Adams | B4: Ritzville | C4: Partially Planning | D4: 1670 | E4: 1790
A5: Asotin | B5: Clarkston | C5: Partially Planning | D5: 7235 | E5: 7240
A6: Cowlitz | B6: Longview | C6: *Pending | D6: 37130 | E6: 38310
A7: Cowlitz | B7: Kelso | C7: *Pending | D7: 11950 | E7: 12850
A8: Cowlitz | B8: Castle Rock | C8: *Pending | D8: 2175 | E8: 2470
A9: Cowlitz | B9: Woodland | C9: *Pending | D9: 5845 | E9: 6585 | F9: Woodland straddles Cowlitz/Clark; figures are full-city totals
A10: Cowlitz | B10: Kalama | C10: *Pending | D10: 2500 | E10: 3165
A11: Ferry | B11: Republic | C11: *Partially Planning | D11: 1090 | E11: 1000 | F11: *Ferry County is the only "voluntary GMA" county that later opted out (RCW 36.70A.040(2)(b))
A12: Grays Harbor | B12: Aberdeen | C12: Partially Planning | D12: 16780 | E12: 17200
A13: Grays Harbor | B13: Hoquiam | C13: Partially Planning | D13: 8575 | E13: 8810
A14: Grays Harbor | B14: Ocean Shores | C14: Partially Planning | D14: 5935 | E14: 7755
A15: Grays Harbor | B15: Montesano | C15: Partially Planning | D15: 4095 | E15: 4135
A16: Grays Harbor | B16: Elma | C16: Partially Planning | D16: 3135 | E16: 3535 | F16: Survey had ~3,500 / ~3,500 (2015 was actually 3,135; 2025 is 3,535)
A17: Grays Harbor | B17: Westport | C17: Partially Planning | D17: 2110 | E17: 2360
A18: Grays Harbor | B18: Cosmopolis | C18: Partially Planning | D18: 1640 | E18: 1680
A19: Klickitat | B19: Goldendale | C19: Partially Planning | D19: 3425 | E19: 3500
A20: Klickitat | B20: White Salmon | C20: Partially Planning | D20: 2420 | E20: 2565
A21: Klickitat | B21: Bingen | C21: Partially Planning | D21: 735 | E21: 780
A22: Lincoln | B22: Davenport | C22: Partially Planning | D22: 1685 | E22: 1720 | F22: Survey had 1,250 for current — incorrect; actual OFM 2025 is 1,720
A23: Lincoln | B23: Odessa | C23: Partially Planning | D23: 905 | E23: 875
A24: Lincoln | B24: Harrington | C24: Partially Planning | D24: 420 | E24: 430
A25: Lincoln | B25: Reardan | C25: Partially Planning | D25: 570 | E25: 645
A26: Lincoln | B26: Wilbur | C26: Partially Planning | D26: 880 | E26: 895
A27: Okanogan | B27: Omak | C27: Partially Planning | D27: 4900 | E27: 4985
A28: Okanogan | B28: Okanogan (city) | C28: Partially Planning | D28: 2580 | E28: 2425
A29: Okanogan | B29: Brewster | C29: Partially Planning | D29: 2395 | E29: 2005
A30: Okanogan | B30: Oroville | C30: Partially Planning | D30: 1695 | E30: 1820
A31: Okanogan | B31: Tonasket | C31: Partially Planning | D31: 1110 | E31: 1090 | F31: Survey had ~1,100 / ~1,100 — correct as rounded; OFM 1,110 / 1,090
A32: Okanogan | B32: Pateros | C32: Partially Planning | D32: 525 | E32: 610 | F32: Survey had 590 / 600. OFM shows 525 (2015) → 610 (2025). 2015 figure differs due to a state-certified special census
A33: Okanogan | B33: Twisp | C33: Partially Planning | D33: 945 | E33: 1110
A34: Okanogan | B34: Winthrop | C34: Partially Planning | D34: 435 | E34: 605
A35: Skamania | B35: Skamania County - General Publi | C35: Partially Planning | D35: 11430 | E35: 12150 | F35: Full county population (2015 → 2025)
A36: Skamania | B36: Stevenson | C36: Partially Planning | D36: 1530 | E36: 1600
A37: Skamania | B37: North Bonneville | C37: Partially Planning | D37: 1005 | E37: 985
A38: Wahkiakum | B38: Wahkiakum County - General Publ | C38: Partially Planning | D38: 3980 | E38: 4550 | F38: Survey had 45,000 for full county — incorrect by ~10x. OFM: 3,980 (2015) → 4,550 (2025)
A39: Wahkiakum | B39: Cathlamet | C39: Partially Planning | D39: 490 | E39: 580
A40: Whitman | B40: Pullman | C40: Partially Planning | D40: 32110 | E40: 34380
A41: Whitman | B41: Colfax | C41: Partially Planning | D41: 2790 | E41: 2790
A42: Whitman | B42: Palouse | C42: Partially Planning | D42: 1030 | E42: 1060
A43: Whitman | B43: Tekoa | C43: Partially Planning | D43: 785 | E43: 820
A44: Whitman | B44: Rosalia | C44: Partially Planning | D44: 560 | E44: 585

Sheet GMA & Pop. Bib.
A1: Bibliography — Sources for Fact-Checked Table
A2: All citations support data in the "Fact Checked" sheet. Compiled May 25, 2026.
A4: # | B4: Citation | C4: Publisher / Author | D4: Date | E4: URL | F4: Used For
A5: 1 | B5: "A Guide to the Periodic Update Process under the Growth Management Act." Explicitly lists the 11 partially-planning counties: Adams, Asotin, Cowlitz, Ferry, Grays Harbor, Klickitat, Lincoln, Okanogan, Skamania, Wahkiakum, and Whitman. | C5: Washington State Department of Commerce (hosted by Yakima County) | D5: Accessed May 25, 2026 | E5: https://www.yakimacounty.us/DocumentCenter/View/35541/GMA-UPDATE-tab---A-Guide-to-the-Periodic-Update-Process-under-the-GMA | F5: Column C — GMA status for all 11 counties in the table
A6: 2 | B6: "Comprehensive Planning under the Growth Management Act" (slide deck). Confirms Whitman County is partially planning; explains regional variation in GMA planning requirements. | C6: Washington State Department of Commerce (hosted by Whitman County) | D6: June 25, 2025 | E6: https://www.whitmancounty.gov/DocumentCenter/View/10602/Comprehensive-Planning-Under-the-Growth-Management-Act---2025-06-25-PDF | F6: Column C — corroboration that Whitman is partially planning; framework for fully vs. partially planning distinction
A7: 3 | B7: "Growth Management Act Basics." Notes that Ferry County is the only voluntary GMA county to later opt out of fully planning, under RCW 36.70A.040(2)(b). | C7: Municipal Research and Services Center of Washington (MRSC) | D7: Updated February 25, 2026 | E7: https://mrsc.org/explore-topics/planning/gma/growth-management-act-basics | F7: Column C — explanation of Ferry County's partially-planning status (uniquely, after opt-out)
A8: 4 | B8: Chapter 36.70A RCW — Growth Management—Planning by Selected Counties and Cities. Statutory basis for the GMA, including RCW 36.70A.040 (thresholds for required planning) and RCW 36.70A.060/.170 (critical areas and resource land requirements applicable to all counties). | C8: Washington State Legislature | D8: Current as of 2026 | E8: https://app.leg.wa.gov/RCW/default.aspx?cite=36.70A | F8: Column C — statutory authority underlying GMA categorization
A9: 5 | B9: "2015 Population Trends," Table 4: Populations of Cities, Towns and Counties: April 1, 2010, to April 1, 2015. Official April 1, 2015 population estimates for all Washington cities, towns, and counties. | C9: Washington State Office of Financial Management (OFM), Forecasting & Research Division | D9: September 2015 | E9: https://ofm.wa.gov/washington-data-research/population-demographics/population-estimates/historical-estimates-april-1-population-and-housing-state-counties-and-cities | F9: Column D — Pre-growth (2015) population for every town in the table
A10: 6 | B10: "April 1, 2025 Population of Cities, Towns and Counties — Used for Allocation of Selected State Revenues." Official April 1, 2025 population estimates per RCW 43.62.030. | C10: Washington State Office of Financial Management (OFM) | D10: Released June 27, 2025 | E10: https://ofm.wa.gov/wp-content/uploads/sites/default/files/public/dataresearch/pop/april1/ofm_april1_population_final.pdf | F10: Column E — Current (2025) population for every town in the table
A11: 7 | B11: "Washington population growth slowing" — OFM press release accompanying the April 1, 2025 estimates. Reports statewide population of 8,115,100 and provides context for current-decade growth trends. | C11: Washington State Office of Financial Management (OFM) | D11: June 27, 2025 | E11: https://ofm.wa.gov/about/news/2025/06/washington-population-growth-slowing | F11: Column E — supporting context for the official 2025 estimates
A12: 8 | B12: "April 1 official population estimates" — OFM landing page describing the annual population estimates program established under RCW 43.62.020 and RCW 43.62.030. | C12: Washington State Office of Financial Management (OFM) | D12: Accessed May 25, 2026 | E12: https://ofm.wa.gov/washington-data-research/population-demographics/population-estimates/april-1-official-population-estimates | F12: Columns D and E — methodology and statutory authority for OFM's population estimates
A13: 9 | B13: "About the GMA." Provides a complete list of the 29 historically fully-planning GMA counties (now 28 after Ferry's opt-out); the 11 counties NOT on this list are by elimination the partially-planning counties. | C13: Futurewise | D13: Accessed May 25, 2026 | E13: https://futurewise.org/about-the-gma/ | F13: Column C — cross-check on the partially-planning county list
A14: 10 | B14: "Long Range Planning in Washington State." Department of Commerce overview describing the 18 required + 11 voluntary fully-planning counties (totaling the 28 currently-planning jurisdictions, with the other 11 partially planning). | C14: Washington State Department of Commerce (hosted by City of Poulsbo) | D14: Accessed May 25, 2026 | E14: https://poulsbo.gov/wp-content/uploads/2018/12/PlanninginWAState.pdf | F14: Column C — cross-check on the fully-vs.-partially planning framework
A15: 11 | B15: WA HB 1241 Senate Bill Report (Ways & Means, 2021). Establishes the periodic comprehensive plan update deadlines for the partially-planning counties (June 30, 2027 cycle). | C15: Washington State Legislature | D15: 2021 legislative session | E15: https://app.leg.wa.gov/documents/billdocs/2021-22/Htm/Bill%20Reports/Senate/1241-S.E%20SBR%20WM%20OC%2021.htm | F15: Column C — confirms grouping of partially-planning counties in current update cycle

Sheet Contacts
A1: County | B1: City/Town | C1: Pop. tier | D1: Contact Name | E1: Title | F1: Email | G1: Phone | H1: Alt Phone | I1: Website/Source | J1: Cross-reference | K1: Outreach Status | L1: Date Contacted | M1: Follow-up Date | N1: Notes | O1: Column1
A2: Adams | B2: Othello | C2: Mid (~8k) | D2: Robin Adolphsen, PE | E2: Public Works Director / City Engineer | F2: radolphsen@othellowa.gov | G2: (509) 488-6997 | H2: (509) 488-5686 | I2: othellowa.gov; MRSC | J2: $ | K2: Connected | L2: 46150 | N2: third survey
A3: Adams | B3: Ritzville | C3: Small (~1.7k) | D3: Dave Breazeale | E3: Public Works Director | F3: dave.breazeale@ritzville-wa.us | G3: (509) 659-1930 | I3: ritzville-wa.us | J3: $ | K3: Called, emailed | L3: 5-8-26, 5-18-26 (expect email back)
A4: Asotin | B4: Clarkston | C4: Mid (~7k) | D4: Mike Dimmick, Bob Sischo (better contact for the PUD) | E4: Public Works Director | F4: mdimmick@clarkston-wa.com | G4: (509) 758-1662 | I4: clarkston-wa.com | J4: $ | K4: Called, Connected | L4: 5-8-26 *(go to tab to see...), connected 5-13-26 | N4: Good survey with the Public utilities district director Bob Sischo (people who actually handle water utiliteis in Asotin, not the public works director in this case.)
A5: Cowlitz | B5: Longview | C5: Large (~38k) | D5: Chris Collins | E5: Public Works Director | F5: chris.collins@ci.longview.wa.us | G5: (360) 442-5201 | I5: mylongview.com | J5: $, phone # fixed & filled in email | K5: Connected | L5: 5-11-26, 5-18-26, 5-21-26 | N5: write here after the car interview
A6: Cowlitz | B6: Kelso | C6: Mid (~12k) | D6: Devin Mackin | E6: Public Works Manager | F6: dmackin@kelso.gov | G6: (360) 577-3360 | I6: kelso.gov | J6: $ email not found | K6: Called, emailed | L6: 5-11-26, 5-18-26 (email back)
A7: Cowlitz | B7: Castle Rock | C7: Small (~2.2k) | D7: Tyler Stone | E7: Public Works Director | F7: tstone@ci.castle-rock.wa.us | G7: (360) 274-7478 | I7: ci.castle-rock.wa.us | J7: $ | K7: Called, emailed | L7: 5-11-26, 5-18-26 (email back)
A8: Cowlitz | B8: Woodland | C8: Mid (~6.5k) | D8: Riley Bunnell | E8: Public Works Director | F8: bunnellr@ci.woodland.wa.us | G8: (360) 225-7999 ext. 201 | I8: ci.woodland.wa.us | J8: $, email added | K8: Connected | L8: 5-11-26 call, connected 5-12-26 | N8: Good
A9: Cowlitz | B9: Kalama | C9: Small (~2.7k) | D9: Kelly Rasmussen | E9: Director of Public Works | F9: krasmussen@cityofkalama.com | G9: (360) 673-3706 | I9: cityofkalama.com | J9: $ | K9: Called, emailed | L9: 5-11-26, 5-18-26 (email back)
A10: Ferry | B10: Republic | C10: Small (~1.1k) | D10: Todd Cole | E10: Public Works Director | F10: publicworks@republicwa.org | G10: (509) 775-2929 | H10: (509) 207-5403 cell | I10: republicwa.org | J10: $, hard to verify if info is correct | K10: Connected | L10: 46153 | N10: All went well, first survey.
A11: Grays Harbor | B11: Aberdeen | C11: Mid (~16k) | D11: Rick Sangder | E11: Public Works Director | G11: (360) 537-3228 | I11: aberdeenwa.gov | J11: $ | K11: Connected | L11: 46153 | N11: Went well, second survey
A12: Grays Harbor | B12: Hoquiam | C12: Mid (~8.6k) | D12: Eric Lawrence, Corrine Schmid | E12: Public Works Superintendent, Finance director | F12: elawrence@cityofhoquiam.com | G12: (360) 538-3966 | I12: cityofhoquiam.com | J12: $ | K12: Called, emailed (Corrine) | L12: 5-11-26, 5-18-26 (email back)
A13: Grays Harbor | B13: Ocean Shores | C13: Small (~6.7k) | D13: Ricardo Victoriano | E13: Public Works Director | F13: rvictoriano@osgov.com | G13: (360) 940-7535 | I13: osgov.com -> https://www.osgov.com/contact/index.php | J13: $, fixed person, phone #, and email | K13: Called, emailed | L13: 5-11-26, 5-18-26 (email back)
A14: Grays Harbor | B14: Montesano | C14: Small (~4.1k) | D14: Mike Olden, PE | E14: PW & Community Development Director | F14: molden@montesano.us | G14: (360) 249-3021 ext. 202 | I14: montesano.us | J14: $ | K14: Not a fit | L14: 5-11-26 contact attempts, 5/18/26 refusal confirmed | M14: Has declined participation over email. No ball.
A15: Grays Harbor | B15: Elma | C15: Small (~3.4k) | D15: Rick Eaton | E15: Public Works Director | F15: pwdirector@cityofelma.com | G15: (360) 200-8402 | I15: cityofelma.com; MRSC | J15: $, phone # fixed | K15: Connected | L15: 5-11-26 (call back) | N15: fourth done.
A16: Grays Harbor | B16: Westport | C16: Small (~2.2k) | D16: Tom Cappa | E16: City Administrator (handles PW) | F16: ca@ci.westport.wa.us | G16: (360) 268-0131 OR 360-268-0131 | I16: ci.westport.wa.us | J16: $, info hard to verify | K16: Called, emailed | L16: 5-12-26, 5-18-26 (email back)
A17: Grays Harbor | B17: Cosmopolis | C17: Small (~1.6k) | D17: Donnie Fowler | E17: Public Works Lead | F17: DFowler@cosmopoliswa.gov | G17: (360) 533-4280 | I17: cosmopoliswa.gov | J17: $, email fixed | K17: Emailed | L17: ** 5-12-26 (COULD NOT LEAVE A VOICEMAIL)
A18: Klickitat | B18: Goldendale | C18: Small (~3.5k) | D18: Doug Frantum | E18: Public works director | F18: communications@ci.goldendale.wa.us | G18: (509) 773-3771 | I18: ci.goldendale.wa.us -> https://www.goldendalesentinel.com/legals/legals-for-november-23rd-2022/article_74b84240-6b7d-11ed-b5ce-13e9fa68a218.html#:~:text=DATE%20OF%20FIRST%20PUBLICATION:%20November,(4512%2C%204602%2C%204701) | J18: $, fixed name | K18: Not contacted
A19: Klickitat | B19: White Salmon | C19: Small (~3k) | D19: Chris True | E19: Public Works Director | G19: (509) 493-1133 x500 | I19: ChrisT@whitesalmonwa.gov | J19: $, email and phone # fixed | K19: Not contacted
A20: Klickitat | B20: Bingen | C20: Small (~750) | D20: David Spratt | E20: Public Works Superintendent | F20: publicworks@bingenwashington.org | G20: 541-490-5407 | I20: bingenwashington.org; MRSC | J20: $, number has been updated multiple times within the past few years, could be wrong | K20: Not contacted
A21: Lincoln | B21: Davenport | C21: Small (~1.7k) | D21: Dave Orvis | E21: Public Works Director | G21: (509)-725-7041 | I21: davenportwa.us | K21: Connected | L21: 46154 | N21: Survey was not suited to the town's situation. May need to circle back on this county due to how its lack of public utilities district.
A22: Lincoln | B22: Odessa | C22: Small (~1k) | D22: Gerald Greenwalt | E22: Public Works Director | F22: pwd@odessawa.org | G22: (509) 988-2401 | H22: (509) 988-3093 | I22: odessawa.org; MRSC | J22: $ | K22: Called, emailed | L22: 5-14-26, 5-18-26 (email back)
A23: Lincoln | B23: Harrington | C23: Small (~400) | D23: (unnamed) | E23: — see notes | F23: clerk@harrington.city | G23: (509) 253-4345 | I23: harrington.city; MRSC | K23: Emailed | L23: 5-14-26, may email/ call back
A24: Lincoln | B24: Reardan | C24: Small (~400) | D24: Tony DeSautel | E24: Town Clerk/Treasurer | F24: clerk@townofreardan.com | G24: (509) 499-5070 | I24: https://reardanwa.gov/index.asp?SEC=55D012BF-68BF-4417-BD1B-7CDF35B24375 | J24: $, no email listed | K24: Emailed | L24: 5-14-26, may email/ call back
A25: Lincoln | B25: Wilbur | C25: Small (~800) | D25: Eric Morris, Melissa Bulger | E25: Public Works Foreman, Clerk Treasurer | F25: pw@wilburwa.com , deputyclerk@wilburwa.com | G25: (509) 647-5821 (ask for Melissa) | H25: (509) 641-2008 | I25: wilburwa.gov | J25: $ | K25: Connected | L25: 46156 | N25: went well. Interestingly the only partial planning GMA town that utilizes impact fees
A26: Okanogan | B26: Omak | C26: Mid (~5k) | D26: Wayne Beetchenow | E26: Public Works Director | F26: publicworks@omakcity.com | G26: (509) 826-1170 | I26: omakcity.com | J26: $ | K26: Connected | N26: went alright, short and to the point
A27: Okanogan | B27: Okanogan (city) | C27: Small (~2.5k) | D27: Shawn Davisson | E27: Director of Public Works | G27: (509) 422-3600 ext. 17 | I27: okanogancity.com | J27: $ | K27: Called, emailed | L27: 5-12-26, may email/ call back
A28: Okanogan | B28: Brewster | C28: Small (~2.4k) | D28: Lee Webster | E28: Public Works Director | F28: Lee.Webster@brewsterwa.us | G28: (509) 689-3464 | H28: (509) 689-3705 | I28: brewster-wa.com; Rep. Engell legislative update | J28: $, department # update & personal email | K28: Called, emailed | L28: 5-12-26, 5-18-26 (email back)
A29: Okanogan | B29: Oroville | C29: Small (~1.7k) | D29: Steve Thompson | E29: City Superintendent | F29: PublicWorks@orovillewa.gov | G29: (509) 476-2106 | I29: oroville-wa.com; MRSC | J29: $ | K29: Connected | N29: Short and to the point
A30: Okanogan | B30: Tonasket | C30: Small (~1k) | D30: Darren Johnson | E30: City / Public Works Superintendent | F30: djohnson.tonasket@nvinet.com | G30: (509) 322-7432 | I30: tonasketwa.gov; MRSC | J30: $ | K30: Connected | N30: went well.
A31: Okanogan | B31: Pateros | C31: Small (~600) | D31: Jord Wilson | E31: City Administrator / Public Works Supervisor | F31: jwilson@pateros.us | G31: (509) 499-9670 | H31: (509) 923-2571 | I31: pateros.com | J31: $ | K31: Connected | L31: 5-13-26, 5-18-26 | N31: went well.
A32: Okanogan | B32: Twisp | C32: Small (~1k) | D32: Andrew Denham | E32: Assistant Public Works Director | F32: pwasdirector@townoftwisp.com | I32: townoftwisp.com | J32: $ | K32: Emailed | L32: 5-13-26 (may email or call back)
A33: Okanogan | B33: Winthrop | C33: Small (~500) | D33: Jake Gates | E33: Public Works Superintendent | F33: jacob@townofwinthrop.com | G33: (509) 996-2320 [department #] | I33: townofwinthrop.com; MRSC | J33: $, no main phone # listed | K33: Connected | L33: 5-13-26 connected | N33: Went well. Make sure to go by Jake not Jacob.
A34: Skamania | B34: Skamania County - General Public Works (for unincorporated towns) | D34: David Waymire,Melanie Sharp from Skamania PUD | E34: Public Works & Community Development Director, Water manager of Skamania PUD | F34: publicworks@co.skamania.wa.us | G34: (509) 427-3909 | H34: (509) 427-3910 [department #] | I34: https://www.skamaniacounty.org/departments-offices/public-works | J34: $ | K34: Connected | L34: 5-13-26 (connect David), 5-18-26, 5-19-26, 5-20-26 (connect Melanie) | N34: Skamania county public utilities district. Both towns manage their own. Gneral water utilities for other communities is the skamnaia county public utilities district. 5094275126. city of bonneville Cody rosander (5094275970). Not sure who to contact for bonneville. | O34: Melanie: Wanted to mention another thing. We recorded a public meeting explaining how we do our charges. On webpage: ____
A35: Skamania | B35: Stevenson | C35: Small (~1.6k) | D35: Cody Rosander, (no longer Carolyn Sourek) | E35: Public Works Director | F35: cody@ci.stevenson.wa.us | G35: (509) 427-5970 | H35: (509) 427-5970 [department #] | I35: ci.stevenson.wa.us; council minutes June 2024 | J35: $, no main phone # listed | K35: Connected | L35: 5-13-26, 5-18-26 emailed, 5-27-26 connected | N35: ***
A36: Skamania | B36: North Bonneville | C36: Small (~1.4k) | D36: Bryan Henrichsen | E36: Public Works Supervisor | F36: bryanh@northbonneville.net | G36: 541-490-2370 | I36: https://northbonneville.net/government/ | J36: $, fixed person, phone #, and email | K36: Called, emailed | L36: 5-13-26, 5-18-26 (email back)
A37: Wahkiakum | B37: Wahkiakum County - General Public Works (for unincorporated towns) | D37: Chuck Beyer (doesn’t handle water utils), David K. | E37: Public Works Director, PUD General Manager | G37: 360-795-3301 | I37: https://co.wahkiakum.wa.us/Directory.aspx?DID=23 | J37: $, no email listed | K37: Called | L37: 5-13-26, called both. Emailed Dan K on 5-19-26
A38: Wahkiakum | B38: Cathlamet | C38: Small (~520) | D38: Troy Gorley | E38: Utility / Maintenance | F38: troy@townofcathlamet.com | G38: (360) 795-3203 ext. 3 | H38: (360) 849-9484 | I38: townofcathlamet.com | J38: $ | K38: Connected | L38: 5-14-26, texted me back | N38: ^^Cathlamet's sewer and fresh water is now entirely handled by the PUD.
A39: Whitman | B39: Pullman | C39: Large (~33k) | D39: Frank Mulcahy | E39: Public Works Director | G39: (509) 338-3220 [department #] | I39: pullman-wa.gov (Dec 2025 announcement) | J39: $, no email available | K39: Called, emailed | L39: 5-14-26, 5-18-26 (email back)
A40: Whitman | B40: Colfax | C40: Small (~2.8k) | D40: Matt Hammer | E40: City Administrator / Public Works Director | F40: pwdir@colfaxwa.org | G40: (509) 397-4606 | I40: https://colfaxwa.org/public-works | J40: $, phone # updated | K40: Called, emailed | L40: 5-14-26, 5-18-26 (email back)
A41: Whitman | B41: Palouse | C41: Small (~1k) | D41: Mike Wolf, Misty (better contact) | E41: Maintenance Supervisor | G41: (509) 878-1811 | H41: (509) 878-1345 days/emergency | I41: palousewa.gov | J41: $, hard to verify if info is correct | K41: Connected | L41: 5-14-26, 5-18-26 connected | N41: Went well. Town has no plans for expansion, simply doesn’t allow for that contingency
A42: Whitman | B42: Tekoa | C42: Small (~800) | D42: Steven Thomas | E42: Public Work's | F42: tekoapublicworksdept@gmail.com | G42: (509) 284-3861 | I42: https://tekoawa.com/public-work-s-department | J42: $, name updated | K42: Called, emailed | L42: Called, emailed
A43: Whitman | B43: Rosalia | C43: Small (~650) | D43: Jacob Billington, Barb Leighton (better contact) | E43: Maintenance Supervisor | F43: maintenance@rosaliatown.org | G43: 509-523-5991. | I43: townofrosalia.net | J43: $, no phone # listed | K43: Emailed | L43: 5-14-26 (may email or call back)
A50: Columbia
A51: Garfield
E56: Attempted contact with 40 out of 43 public works directors, so far

Sheet Othello
A1: County | B1: City/Town | C1: Pop. tier | D1: Contact Name | E1: Title | F1: Email | G1: Phone | H1: Alt Phone | I1: Website/Source | J1: Cross-reference | K1: Outreach Status | L1: Date Contacted | M1: Follow-up Date | N1: Notes
A2: Adams | B2: Othello | C2: Mid (~8k) | D2: Robin Adolphsen, PE | E2: Public Works Director / City Engineer | F2: radolphsen@othellowa.gov | G2: (509) 488-6997 | H2: (509) 488-5686 | I2: othellowa.gov; MRSC | J2: $ | K2: Not contacted
A5: 1. Alright, for starters what is your formal title in relation to [city] , [name]? 2. Do you happen to know the GMA status of your county? 3. Would you say the population of [city] has grown significantly in the last 10 years? 4. Does your town sell or provide water to any neighboring towns? 5. Has your department needed to expand the water infrastructure for your city at any point in the last 10 years? 6. How does your department raise funds for expansions of water infrastructure? Do you levy any upfront fees, like system development charges or capacity fee charges? 7. How are those funding methods typically calculated? For instance, do certain factors change how much the customer or developer on your water network pays? 8. Does your department utilize a GIS tool for your town’s water meters? If so, is this used when calculating fees and bills? 9. Is there anything you would like to add that you think may be helpful on this matter?
A22: Questions | B22: Y/N | C22: Notes / transcription
A23: Q1 | B23: Y | C23: public works director for Othello
A24: Q2 | B24: N
A25: Q3 | B25: Y | C25: 9,000 now, were closer to 7,500
A26: Q4 | B26: N
A27: Q5 | B27: Y | C27: developments are responsible for adding infrastructure not us, but we have added 2 new wells.
A28: Q6 | B28: Y | C28: fees for developers are 2% for whatever the infrastructure cost is.
A29: Q7 | B29: N | C29: These were calculated prior to me, not sure how this was developed. Part of our development fees, (not sure what formal name is for these)
A30: Q8 | B30: N
A31: Q9

Sheet Ritzville
A1: County | B1: City/Town | C1: Pop. tier | D1: Contact Name | E1: Title | F1: Email | G1: Phone | H1: Alt Phone | I1: Website/Source | J1: Cross-reference | K1: Outreach Status | L1: Date Contacted | M1: Follow-up Date | N1: Notes
A2: Adams | B2: Ritzville | C2: Small (~1.7k) | D2: Dave Breazeale | E2: Public Works Director | F2: dave.breazeale@ritzville-wa.us | G2: (509) 659-1930 | I2: ritzville-wa.us | J2: $ | K2: Not contacted
A5: 1. Alright, for starters what is your formal title in relation to [city] , [name]? 2. Do you happen to know the GMA status of your county? 3. Would you say the population of [city] has grown significantly in the last 10 years? 4. Does your town sell or provide water to any neighboring towns? 5. Has your department needed to expand the water infrastructure for your city at any point in the last 10 years? 6. How does your department raise funds for expansions of water infrastructure? Do you levy any upfront fees, like system development charges or capacity fee charges? 7. How are those funding methods typically calculated? For instance, do certain factors change how much the customer or developer on your water network pays? 8. Does your department utilize a GIS tool for your town’s water meters? If so, is this used when calculating fees and bills? 9. Is there anything you would like to add that you think may be helpful on this matter?
A22: Questions | B22: Y/N | C22: Notes / transcription
A23: Q1
A24: Q2
A25: Q3
A26: Q4
A27: Q5
A28: Q6
A29: Q7
A30: Q8
A31: Q9

Sheet Clarkston
A1: County | B1: City/Town | C1: Pop. tier | D1: Contact Name | E1: Title | F1: Email | G1: Phone | H1: Alt Phone | I1: Website/Source | J1: Cross-reference | K1: Outreach Status | L1: Date Contacted | M1: Follow-up Date | N1: Notes
A2: Asotin | B2: Clarkston | C2: Mid (~7k) | D2: Mike Dimmick | E2: Public Works Director | F2: mdimmick@clarkston-wa.com | G2: (509) 758-1662 | I2: clarkston-wa.com | J2: $ | K2: Not contacted
A5: Water in clarkston is handled by the "utility district" located within Asotin, their number is 509-758-1010 [Bob Sischo]
A6: They are also busy and may call back at some point, since you left a voice mail
A9: 1. Alright, for starters what is your formal title in relation to [city] , [name]? 2. Do you happen to know the GMA status of your county? 3. Would you say the population of [city] has grown significantly in the last 10 years? 4. Does your town sell or provide water to any neighboring towns? 5. Has your department needed to expand the water infrastructure for your city at any point in the last 10 years? 6. How does your department raise funds for expansions of water infrastructure? Do you levy any upfront fees, like system development charges or capacity fee charges? 7. How are those funding methods typically calculated? For instance, do certain factors change how much the customer or developer on your water network pays? 8. Does your department utilize a GIS tool for your town’s water meters? If so, is this used when calculating fees and bills? 9. Is there anything you would like to add that you think may be helpful on this matter?
A26: Questions | B26: Y/N | C26: Notes / transcription | D26: Column1
A27: Q1 | C27: Bob Sischo, Director of finance and administration for the public utilities district of Asotin. Handles water utilities for all of the towns & communities in Asotin.
A28: Q2 | B28: N
A29: Q3 | B29: N | C29: Some influx during COVID, nothing significant though in terms of population growth. Large geographic county, population base is well centered in Asotin (city) and Clarkston.
A30: Q4 | B30: Y, utilities district does | C30: Based upon their consumption beyond their alloted amount. Asotin has a water system that gives alloted amounts of water to residents, excess is handled byt the utilities district.
A31: Q5 | B31: N | C31: No, a couple of subdivisions but nothing major
A32: Q6 | C32: Development pays for development approach. If someone require a subdivions, the developer is required to devlop it for us, then they hand it to us. We don’t put up funds or anything like that. SDCs are wrapped into the connection fees, but we arent really building out, so we never have capacity issues, only at 50%.
A33: Q7 | B33: Y | C33: Connection fees are based more consumption, and cost of the connection. What is it costing us in terms of maintence? We arent dealing with capacity or urban sprawl, so our fees can be almost entirely around our cost base and maintenance projections.
A34: Q8 | B34: Y | C34: Yes, kind of for asset valuation. Mostly to maintain our system, pressure zones.
A35: Q9
D41: Klickitat is on the electrical side of things PUD, would be good to talk to.

Sheet Longview
A1: County | B1: City/Town | C1: Pop. tier | D1: Contact Name | E1: Title | F1: Email | G1: Phone | H1: Alt Phone | I1: Website/Source | J1: Cross-reference | K1: Outreach Status | L1: Date Contacted | M1: Follow-up Date | N1: Notes
A2: Cowlitz | B2: Longview | C2: Large (~38k) | D2: Chris Collins | E2: Public Works Director | F2: chris.collins@ci.longview.wa.us | G2: (360) 442-5201 | I2: mylongview.com | J2: $, phone # fixed & filled in email | K2: Not contacted
A5: 1. Alright, for starters what is your formal title in relation to [city] , [name]? 2. Do you happen to know the GMA status of your county? 3. Would you say the population of [city] has grown significantly in the last 10 years? 4. Does your town sell or provide water to any neighboring towns? 5. Has your department needed to expand the water infrastructure for your city at any point in the last 10 years? 6. How does your department raise funds for expansions of water infrastructure? Do you levy any upfront fees, like system development charges or capacity fee charges? 7. How are those funding methods typically calculated? For instance, do certain factors change how much the customer or developer on your water network pays? 8. Does your department utilize a GIS tool for your town’s water meters? If so, is this used when calculating fees and bills? 9. Is there anything you would like to add that you think may be helpful on this matter?
A22: Questions | B22: Y/N | C22: Notes / transcription
A23: Q1 | B23: Y | C23: public works director, as well as asistant city manager
A24: Q2 | B24: Y | C24: non gma
A25: Q3 | B25: N | C25: not significant growth, about 1 percent average per anum growth
A26: Q4 | B26: Y | C26: we provide water to beacon hill water sewer district, they are a 15 percent owner, their ditribution is tied to ours we charge them for their distribution. We have an agreement with kelso for high well water. We have an inter connect where they can pull water from our system at a retail rate (whenever we have excess).
A27: Q5 | B27: Y | C27: Yes we have, a little more than 10 years ago we switched to ground wells from surface waters. We expanded our sytem to accomodate for that .
A28: Q6 | C28: If its developer driven they pay for it. If its infrastructure investment then we pay it. We issue debt to pay for those large expenses, or we pull from capital reserves.
A29: Q7 | B29: Y | C29: we have sdcs on sewer, no impact, connection charges on water. SDCs are calculated off of ERUs and connection charges are calculated off of size of connection. So charges for freshwater are based on size, sewer is standardized
A30: Q8 | B30: Y | C30: Yes we use a Gis tool. We have an asset management system. Its lucidy, a work order and asset management program (Not gis). As far as our system value, we produce and maintain water and sewer system plans that go into more detail on the value of the system. that is the doc that guides more of our long erm planning.
A31: Q9

Sheet Kelso
A1: County | B1: City/Town | C1: Pop. tier | D1: Contact Name | E1: Title | F1: Email | G1: Phone | H1: Alt Phone | I1: Website/Source | J1: Cross-reference | K1: Outreach Status | L1: Date Contacted | M1: Follow-up Date | N1: Notes
A2: Cowlitz | B2: Kelso | C2: Mid (~12k) | D2: Devin Mackin | E2: Public Works Manager | G2: (360) 577-3360 | I2: kelso.gov | J2: $ email not found | K2: Not contacted
A5: 1. Alright, for starters what is your formal title in relation to [city] , [name]? 2. Do you happen to know the GMA status of your county? 3. Would you say the population of [city] has grown significantly in the last 10 years? 4. Does your town sell or provide water to any neighboring towns? 5. Has your department needed to expand the water infrastructure for your city at any point in the last 10 years? 6. How does your department raise funds for expansions of water infrastructure? Do you levy any upfront fees, like system development charges or capacity fee charges? 7. How are those funding methods typically calculated? For instance, do certain factors change how much the customer or developer on your water network pays? 8. Does your department utilize a GIS tool for your town’s water meters? If so, is this used when calculating fees and bills? 9. Is there anything you would like to add that you think may be helpful on this matter?
A22: Questions | B22: Y/N | C22: Notes / transcription
A23: Q1
A24: Q2
A25: Q3
A26: Q4
A27: Q5
A28: Q6
A29: Q7
A30: Q8
A31: Q9

Sheet Castle Rock
A1: County | B1: City/Town | C1: Pop. tier | D1: Contact Name | E1: Title | F1: Email | G1: Phone | H1: Alt Phone | I1: Website/Source | J1: Cross-reference | K1: Outreach Status | L1: Date Contacted | M1: Follow-up Date | N1: Notes
A2: Cowlitz | B2: Castle Rock | C2: Small (~2.2k) | D2: Tyler Stone | E2: Public Works Director | F2: tstone@ci.castle-rock.wa.us | G2: (360) 274-7478 | I2: ci.castle-rock.wa.us | J2: $ | K2: Not contacted
A5: 1. Alright, for starters what is your formal title in relation to [city] , [name]? 2. Do you happen to know the GMA status of your county? 3. Would you say the population of [city] has grown significantly in the last 10 years? 4. Does your town sell or provide water to any neighboring towns? 5. Has your department needed to expand the water infrastructure for your city at any point in the last 10 years? 6. How does your department raise funds for expansions of water infrastructure? Do you levy any upfront fees, like system development charges or capacity fee charges? 7. How are those funding methods typically calculated? For instance, do certain factors change how much the customer or developer on your water network pays? 8. Does your department utilize a GIS tool for your town’s water meters? If so, is this used when calculating fees and bills? 9. Is there anything you would like to add that you think may be helpful on this matter?
A22: Questions | B22: Y/N | C22: Notes / transcription
A23: Q1
A24: Q2
A25: Q3
A26: Q4
A27: Q5
A28: Q6
A29: Q7
A30: Q8
A31: Q9

Sheet Woodland
A1: County | B1: City/Town | C1: Pop. tier | D1: Contact Name | E1: Title | F1: Email | G1: Phone | H1: Alt Phone | I1: Website/Source | J1: Cross-reference | K1: Outreach Status | L1: Date Contacted | M1: Follow-up Date | N1: Notes
A2: Cowlitz | B2: Woodland | C2: Mid (~6.5k) | D2: Riley Bunnell | E2: Public Works Director | F2: bunnellr@ci.woodland.wa.us | G2: (360) 225-7999 ext. 201 | I2: ci.woodland.wa.us | J2: $, email added | K2: Not contacted
A5: 1. Alright, for starters what is your formal title in relation to [city] , [name]? 2. Do you happen to know the GMA status of your county? 3. Would you say the population of [city] has grown significantly in the last 10 years? 4. Does your town sell or provide water to any neighboring towns? 5. Has your department needed to expand the water infrastructure for your city at any point in the last 10 years? 6. How does your department raise funds for expansions of water infrastructure? Do you levy any upfront fees, like system development charges or capacity fee charges? 7. How are those funding methods typically calculated? For instance, do certain factors change how much the customer or developer on your water network pays? 8. Does your department utilize a GIS tool for your town’s water meters? If so, is this used when calculating fees and bills? 9. Is there anything you would like to add that you think may be helpful on this matter?
A22: Questions | B22: Y/N | C22: Notes / transcription | D22: Column1
A23: Q1
A24: Q2 | B24: pending | C24: pending status for GMA.
A25: Q3 | B25: Y | C25: Yes.
A26: Q4 | B26: Y | C26: We do service for a small housing development in clark county
A27: Q5 | C27: City of woodland has not done any internal expansion, but residential has (for connections and water sewage infrastructure). The water main is private, they then relinquish infrastructure to our department. They charge SDCs to new developers, we do not.
A28: Q6 | B28: N | C28: City does not pay for any of the expansion costs, all developer driven
A29: Q7 | B29: N, N/A | C29: (they don’t handle these, so I didn’t ask because its not their jurisdiction in this case)
A30: Q8 | B30: Y | C30: We use GIS ezeree. We are looking to update. We just use it informationally, no asset valuation, unless its sewer INI
A31: Q9 | C31: would recommend to look at capital improvement list, what are the current system constraints? Put a denomination next to what projects are most importanmt. Every 5 years we do a third party review for capital improvement projects. FCJ they come in as a third party.

Sheet Kalama
A1: County | B1: City/Town | C1: Pop. tier | D1: Contact Name | E1: Title | F1: Email | G1: Phone | H1: Alt Phone | I1: Website/Source | J1: Cross-reference | K1: Outreach Status | L1: Date Contacted | M1: Follow-up Date | N1: Notes
A2: Cowlitz | B2: Kalama | C2: Small (~2.7k) | D2: Kelly Rasmussen | E2: Director of Public Works | F2: krasmussen@cityofkalama.com | G2: (360) 673-3706 | I2: cityofkalama.com | J2: $ | K2: Not contacted
A5: 1. Alright, for starters what is your formal title in relation to [city] , [name]? 2. Do you happen to know the GMA status of your county? 3. Would you say the population of [city] has grown significantly in the last 10 years? 4. Does your town sell or provide water to any neighboring towns? 5. Has your department needed to expand the water infrastructure for your city at any point in the last 10 years? 6. How does your department raise funds for expansions of water infrastructure? Do you levy any upfront fees, like system development charges or capacity fee charges? 7. How are those funding methods typically calculated? For instance, do certain factors change how much the customer or developer on your water network pays? 8. Does your department utilize a GIS tool for your town’s water meters? If so, is this used when calculating fees and bills? 9. Is there anything you would like to add that you think may be helpful on this matter?
A22: Questions | B22: Y/N | C22: Notes / transcription
A23: Q1
A24: Q2
A25: Q3
A26: Q4
A27: Q5
A28: Q6
A29: Q7
A30: Q8
A31: Q9

Sheet Republic
A1: County | B1: City/Town | C1: Pop. tier | D1: Contact Name | E1: Title | F1: Email | G1: Phone | H1: Alt Phone | I1: Website/Source | J1: Cross-reference | K1: Outreach Status | L1: Date Contacted | M1: Follow-up Date | N1: Notes
A2: Ferry | B2: Republic | C2: Small (~1.1k) | D2: Todd Cole | E2: Public Works Director | F2: publicworks@republicwa.org | G2: (509) 775-2929 | H2: (509) 207-5403 cell | I2: republicwa.org | J2: $, hard to verify if info is correct | K2: Not contacted
A5: 1. Alright, for starters what is your formal title in relation to [city] , [name]? 2. Do you happen to know the GMA status of your county? 3. Would you say the population of [Republic] has grown significantly in the last 10 years? 4. Does your town sell or provide water to any neighboring towns? 5. Has your department needed to expand the water infrastructure for your city at any point in the last 10 years? 6. How does your department raise funds for expansions of water infrastructure? Do you levy any upfront fees, like system development charges or capacity fee charges? 7. How are those funding methods typically calculated? For instance, do certain factors change how much the customer or developer on your water network pays? 8. Does your department utilize a GIS tool for your town’s water meters? If so, is this used when calculating fees and bills? 9. Is there anything you would like to add that you think may be helpful on this matter?
A22: Questions | B22: Y/N | C22: Notes / transcription
A23: Q1 | B23: Y | C23: Public works director, Republic
A24: Q2 | B24: N | C24: Doesn’t know, new to position. [they are ___]
A25: Q3 | B25: N | C25: No
A26: Q4 | B26: N | C26: No
A27: Q5 | B27: N | C27: No, using about 60% of capacity
A28: Q6 | B28: unclear | C28: Engineering firm, in spokane, they do it. We get charged for their development. County tax vbas, hotel motel tax, typically sewer water rates pay for everything.
A29: Q7 | B29: N/A | C29: N/A
A30: Q8 | B30: Y | C30: Just recently got GIS set up. Primarily for locating, no bluetooth meters. Only had it about 8-9 months. Mainly for locatig valves for streets in valves. We pay a monthly, only 3 grand payment, 1300 residence 600 meters. Poorest county in state.
A31: Q9 | C31: Been public works director for year in a half 60 with 40 years in construction, think its helped a lot with problem solving skills. 125 year old town, 6-7 years ago case of embezzlment, now we get audited every year. Young mayor, fantastic city clerk. main source of leaks is steel pipes, pumpibng 130m gallons a year, wasting 27%. 6 inch pvc, wasting a lot of money on contractors.

Sheet Aberdeen
A1: County | B1: City/Town | C1: Pop. tier | D1: Contact Name | E1: Title | F1: Email | G1: Phone | H1: Alt Phone | I1: Website/Source | J1: Cross-reference | K1: Outreach Status | L1: Date Contacted | M1: Follow-up Date | N1: Notes
A2: Grays Harbor | B2: Aberdeen | C2: Mid (~16k) | D2: Rick Sangder | E2: Public Works Director | G2: (360) 537-3228 | I2: aberdeenwa.gov | J2: $ | K2: Not contacted
A5: 1. Alright, for starters what is your formal title in relation to [city] , [name]? 2. Do you happen to know the GMA status of your county? 3. Would you say the population of [city] has grown significantly in the last 10 years? 4. Does your town sell or provide water to any neighboring towns? 5. Has your department needed to expand the water infrastructure for your city at any point in the last 10 years? 6. How does your department raise funds for expansions of water infrastructure? Do you levy any upfront fees, like system development charges or capacity fee charges? 7. How are those funding methods typically calculated? For instance, do certain factors change how much the customer or developer on your water network pays? 8. Does your department utilize a GIS tool for your town’s water meters? If so, is this used when calculating fees and bills? 9. Is there anything you would like to add that you think may be helpful on this matter?
E7: no latecomers agrement
A22: Questions | B22: Y/N | C22: Notes / transcription
A23: Q1 | B23: Y | C23: Public works director of Aberdeen
A24: Q2 | B24: N | C24: [They are ___]
A25: Q3 | B25: N | C25: Maybe 500 new ppl, lots of new development though, around 40 new projects
A26: Q4 | B26: N | C26: not curently, in negotiation to buy / be in same contract as cosmopolis' water system
A27: Q5 | B27: N
A28: Q6 | B28: Y | C28: Future growth covered completely by rates. About 2,000 acres of timber, town considered a small landowner. Can harvest every other year. We are upgrading roads to support this. Planning on selling and using timber to draw interest which would then go to water, but could be used more generally. They do SDC by meter, its about 35 hundred dollars. Depends on size of meter. No latecomers agreement
A29: Q7 | B29: N | C29: primarily based on meter size. 6 inch lines for fire dept. , developers pay in full for additional costs associated with fire protection developments if necessary.
A30: Q8 | B30: Y | C30: yes, we use it for location. Havent used for asset valuation yet, but they can. If meter is not used for 6 months, its worth more to take it out. Not an expert on this. AMES software is more for the valuation stuff
A31: Q9

Sheet Hoquiam
A1: County | B1: City/Town | C1: Pop. tier | D1: Contact Name | E1: Title | F1: Email | G1: Phone | H1: Alt Phone | I1: Website/Source | J1: Cross-reference | K1: Outreach Status | L1: Date Contacted | M1: Follow-up Date | N1: Notes
A2: Grays Harbor | B2: Hoquiam | C2: Mid (~8.6k) | D2: Eric Lawrence | E2: Public Works Superintendent | F2: elawrence@cityofhoquiam.com | G2: (360) 538-3966 | I2: cityofhoquiam.com | J2: $ | K2: Not contacted
A5: 1. Alright, for starters what is your formal title in relation to [city] , [name]? 2. Do you happen to know the GMA status of your county? 3. Would you say the population of [city] has grown significantly in the last 10 years? 4. Does your town sell or provide water to any neighboring towns? 5. Has your department needed to expand the water infrastructure for your city at any point in the last 10 years? 6. How does your department raise funds for expansions of water infrastructure? Do you levy any upfront fees, like system development charges or capacity fee charges? 7. How are those funding methods typically calculated? For instance, do certain factors change how much the customer or developer on your water network pays? 8. Does your department utilize a GIS tool for your town’s water meters? If so, is this used when calculating fees and bills? 9. Is there anything you would like to add that you think may be helpful on this matter?
A22: Questions | B22: Y/N | C22: Notes / transcription
A23: Q1
A24: Q2
A25: Q3
A26: Q4
A27: Q5
A28: Q6
A29: Q7
A30: Q8
A31: Q9

Sheet Ocean Shores
A1: County | B1: City/Town | C1: Pop. tier | D1: Contact Name | E1: Title | F1: Email | G1: Phone | H1: Alt Phone | I1: Website/Source | J1: Cross-reference | K1: Outreach Status | L1: Date Contacted | M1: Follow-up Date | N1: Notes
A2: Grays Harbor | B2: Ocean Shores | C2: Small (~6.7k) | D2: Ricardo Victoriano | E2: Public Works Director | F2: rvictoriano@osgov.com | G2: (360) 940-7535 | I2: osgov.com -> https://www.osgov.com/contact/index.php | J2: $, fixed person, phone #, and email | K2: Not contacted
A5: 1. Alright, for starters what is your formal title in relation to [city] , [name]? 2. Do you happen to know the GMA status of your county? 3. Would you say the population of [city] has grown significantly in the last 10 years? 4. Does your town sell or provide water to any neighboring towns? 5. Has your department needed to expand the water infrastructure for your city at any point in the last 10 years? 6. How does your department raise funds for expansions of water infrastructure? Do you levy any upfront fees, like system development charges or capacity fee charges? 7. How are those funding methods typically calculated? For instance, do certain factors change how much the customer or developer on your water network pays? 8. Does your department utilize a GIS tool for your town’s water meters? If so, is this used when calculating fees and bills? 9. Is there anything you would like to add that you think may be helpful on this matter?
A22: Questions | B22: Y/N | C22: Notes / transcription
A23: Q1
A24: Q2
A25: Q3
A26: Q4
A27: Q5
A28: Q6
A29: Q7
A30: Q8
A31: Q9

Sheet Montesano
A1: County | B1: City/Town | C1: Pop. tier | D1: Contact Name | E1: Title | F1: Email | G1: Phone | H1: Alt Phone | I1: Website/Source | J1: Cross-reference | K1: Outreach Status | L1: Date Contacted | M1: Follow-up Date | N1: Notes
A2: Grays Harbor | B2: Montesano | C2: Small (~4.1k) | D2: Mike Olden, PE | E2: PW & Community Development Director | F2: molden@montesano.us | G2: (360) 249-3021 ext. 202 | I2: montesano.us | J2: $ | K2: Not contacted
G3: 249 3939, email: molden@montesano.us
A5: 1. Alright, for starters what is your formal title in relation to [city] , [name]? 2. Do you happen to know the GMA status of your county? 3. Would you say the population of [city] has grown significantly in the last 10 years? 4. Does your town sell or provide water to any neighboring towns? 5. Has your department needed to expand the water infrastructure for your city at any point in the last 10 years? 6. How does your department raise funds for expansions of water infrastructure? Do you levy any upfront fees, like system development charges or capacity fee charges? 7. How are those funding methods typically calculated? For instance, do certain factors change how much the customer or developer on your water network pays? 8. Does your department utilize a GIS tool for your town’s water meters? If so, is this used when calculating fees and bills? 9. Is there anything you would like to add that you think may be helpful on this matter?
A22: Questions | B22: Y/N | C22: Notes / transcription
A23: Q1
A24: Q2
A25: Q3
A26: Q4
A27: Q5
A28: Q6
A29: Q7
A30: Q8
A31: Q9

Sheet Elma
A1: County | B1: City/Town | C1: Pop. tier | D1: Contact Name | E1: Title | F1: Email | G1: Phone | H1: Alt Phone | I1: Website/Source | J1: Cross-reference | K1: Outreach Status | L1: Date Contacted | M1: Follow-up Date | N1: Notes
A2: Grays Harbor | B2: Elma | C2: Small (~3.4k) | D2: Rick Eaton | E2: Public Works Director | F2: pwdirector@cityofelma.com | G2: (360) 200-8402 | I2: cityofelma.com; MRSC | J2: $, phone # fixed | K2: Not contacted
A5: 1. Alright, for starters what is your formal title in relation to [city] , [name]? 2. Do you happen to know the GMA status of your county? 3. Would you say the population of [city] has grown significantly in the last 10 years? 4. Does your town sell or provide water to any neighboring towns? 5. Has your department needed to expand the water infrastructure for your city at any point in the last 10 years? 6. How does your department raise funds for expansions of water infrastructure? Do you levy any upfront fees, like system development charges or capacity fee charges? 7. How are those funding methods typically calculated? For instance, do certain factors change how much the customer or developer on your water network pays? 8. Does your department utilize a GIS tool for your town’s water meters? If so, is this used when calculating fees and bills? 9. Is there anything you would like to add that you think may be helpful on this matter?
A22: Questions | B22: Y/N | C22: Notes / transcription
A23: Q1 | B23: Y | C23: Public works director of Elma
A24: Q2 | B24: Y | C24: non growth management act
A25: Q3 | B25: N | C25: not gone up much, still around 35 hundred people
A26: Q4 | B26: N | C26: No other towns, do provide outside of city limits though within where the service area limits extend.
A27: Q5 | B27: Y | C27: mostly to accommodate some development, no water rights expansion, mostly connections
A28: Q6 | B28: Y | C28: couple different ways. Contributions to our capital accounts. Connection fees. We seek out grants from state revolving. Try to get as much free money as we can.
A29: Q7 | C29: Was calculated before I took this position. Now we just do yearly increases for inflation. Normally you would figure out operating costs diovided by each connection, then charge that for each new connection. These are capital facility fees
A30: Q8 | C30: Currently in development of GIS. Will use both for billing and for geographical understanding of the meters
A31: Q9 | C31: Something to take into account in general, most of that expansion is on the developer to cover in terms of fees. If infrastructre isnt there the developer pays. Especially happens in small municipalities.

Sheet Westport
A1: County | B1: City/Town | C1: Pop. tier | D1: Contact Name | E1: Title | F1: Email | G1: Phone | H1: Alt Phone | I1: Website/Source | J1: Cross-reference | K1: Outreach Status | L1: Date Contacted | M1: Follow-up Date | N1: Notes
A2: Grays Harbor | B2: Westport | C2: Small (~2.2k) | D2: Tom Cappa | E2: City Administrator (handles PW) | G2: (360) 268-0131 OR 360-268-0131 | I2: ci.westport.wa.us | J2: $, info hard to verify | K2: Not contacted
A5: 1. Alright, for starters what is your formal title in relation to [city] , [name]? 2. Do you happen to know the GMA status of your county? 3. Would you say the population of [city] has grown significantly in the last 10 years? 4. Does your town sell or provide water to any neighboring towns? 5. Has your department needed to expand the water infrastructure for your city at any point in the last 10 years? 6. How does your department raise funds for expansions of water infrastructure? Do you levy any upfront fees, like system development charges or capacity fee charges? 7. How are those funding methods typically calculated? For instance, do certain factors change how much the customer or developer on your water network pays? 8. Does your department utilize a GIS tool for your town’s water meters? If so, is this used when calculating fees and bills? 9. Is there anything you would like to add that you think may be helpful on this matter?
A22: Questions | B22: Y/N | C22: Notes / transcription
A23: Q1
A24: Q2
A25: Q3
A26: Q4
A27: Q5
A28: Q6
A29: Q7
A30: Q8
A31: Q9

Sheet Cosmopolis
A1: County | B1: City/Town | C1: Pop. tier | D1: Contact Name | E1: Title | F1: Email | G1: Phone | H1: Alt Phone | I1: Website/Source | J1: Cross-reference | K1: Outreach Status | L1: Date Contacted | M1: Follow-up Date | N1: Notes
A2: Grays Harbor | B2: Cosmopolis | C2: Small (~1.6k) | D2: Donnie Fowler | E2: Public Works Lead | F2: DFowler@cosmopoliswa.gov | G2: (360) 533-4280 | I2: cosmopoliswa.gov | J2: $, email fixed | K2: Not contacted
A6: 1. Alright, for starters what is your formal title in relation to [city] , [name]? 2. Do you happen to know the GMA status of your county? 3. Would you say the population of [city] has grown significantly in the last 10 years? 4. Does your town sell or provide water to any neighboring towns? 5. Has your department needed to expand the water infrastructure for your city at any point in the last 10 years? 6. How does your department raise funds for expansions of water infrastructure? Do you levy any upfront fees, like system development charges or capacity fee charges? 7. How are those funding methods typically calculated? For instance, do certain factors change how much the customer or developer on your water network pays? 8. Does your department utilize a GIS tool for your town’s water meters? If so, is this used when calculating fees and bills? 9. Is there anything you would like to add that you think may be helpful on this matter?
A23: Questions | B23: Y/N | C23: Notes / transcription
A24: Q1
A25: Q2
A26: Q3
A27: Q4
A28: Q5
A29: Q6
A30: Q7
A31: Q8
A32: Q9

Sheet Goldendale
A1: County | B1: City/Town | C1: Pop. tier | D1: Contact Name | E1: Title | F1: Email | G1: Phone | H1: Alt Phone | I1: Website/Source | J1: Cross-reference | K1: Outreach Status | L1: Date Contacted | M1: Follow-up Date | N1: Notes
A2: Klickitat | B2: Goldendale | C2: Small (~3.5k) | D2: Doug Frantum | E2: Public works director | F2: communications@ci.goldendale.wa.us | G2: (509) 773-3771 | I2: ci.goldendale.wa.us -> https://www.goldendalesentinel.com/legals/legals-for-november-23rd-2022/article_74b84240-6b7d-11ed-b5ce-13e9fa68a218.html#:~:text=DATE%20OF%20FIRST%20PUBLICATION:%20November,(4512%2C%204602%2C%204701) | J2: $, fixed name | K2: Not contacted
A5: 1. Alright, for starters what is your formal title in relation to [city] , [name]? 2. Do you happen to know the GMA status of your county? 3. Would you say the population of [city] has grown significantly in the last 10 years? 4. Does your town sell or provide water to any neighboring towns? 5. Has your department needed to expand the water infrastructure for your city at any point in the last 10 years? 6. How does your department raise funds for expansions of water infrastructure? Do you levy any upfront fees, like system development charges or capacity fee charges? 7. How are those funding methods typically calculated? For instance, do certain factors change how much the customer or developer on your water network pays? 8. Does your department utilize a GIS tool for your town’s water meters? If so, is this used when calculating fees and bills? 9. Is there anything you would like to add that you think may be helpful on this matter?
A22: Questions | B22: Y/N | C22: Notes / transcription
A23: Q1
A24: Q2
A25: Q3
A26: Q4
A27: Q5
A28: Q6
A29: Q7
A30: Q8
A31: Q9

Sheet White Salmon
A1: County | B1: City/Town | C1: Pop. tier | D1: Contact Name | E1: Title | F1: Email | G1: Phone | H1: Alt Phone | I1: Website/Source | J1: Cross-reference | K1: Outreach Status | L1: Date Contacted | M1: Follow-up Date | N1: Notes
A2: Klickitat | B2: White Salmon | C2: Small (~3k) | D2: Chris True | E2: Public Works Director | G2: (509) 493-1133 x500 | I2: ChrisT@whitesalmonwa.gov | J2: $, email and phone # fixed | K2: Not contacted
A5: 1. Alright, for starters what is your formal title in relation to [city] , [name]? 2. Do you happen to know the GMA status of your county? 3. Would you say the population of [city] has grown significantly in the last 10 years? 4. Does your town sell or provide water to any neighboring towns? 5. Has your department needed to expand the water infrastructure for your city at any point in the last 10 years? 6. How does your department raise funds for expansions of water infrastructure? Do you levy any upfront fees, like system development charges or capacity fee charges? 7. How are those funding methods typically calculated? For instance, do certain factors change how much the customer or developer on your water network pays? 8. Does your department utilize a GIS tool for your town’s water meters? If so, is this used when calculating fees and bills? 9. Is there anything you would like to add that you think may be helpful on this matter?
A22: Questions | B22: Y/N | C22: Notes / transcription
A23: Q1
A24: Q2
A25: Q3
A26: Q4
A27: Q5
A28: Q6
A29: Q7
A30: Q8
A31: Q9

Sheet Bingen
A1: County | B1: City/Town | C1: Pop. tier | D1: Contact Name | E1: Title | F1: Email | G1: Phone | H1: Alt Phone | I1: Website/Source | J1: Cross-reference | K1: Outreach Status | L1: Date Contacted | M1: Follow-up Date | N1: Notes
A2: Klickitat | B2: Bingen | C2: Small (~750) | D2: David Spratt | E2: Public Works Superintendent | F2: publicworks@bingenwashington.org | G2: 541-490-5407 | I2: bingenwashington.org; MRSC | J2: $, number has been updated multiple times within the past few years, could be wrong | K2: Not contacted
A5: 1. Alright, for starters what is your formal title in relation to [city] , [name]? 2. Do you happen to know the GMA status of your county? 3. Would you say the population of [city] has grown significantly in the last 10 years? 4. Does your town sell or provide water to any neighboring towns? 5. Has your department needed to expand the water infrastructure for your city at any point in the last 10 years? 6. How does your department raise funds for expansions of water infrastructure? Do you levy any upfront fees, like system development charges or capacity fee charges? 7. How are those funding methods typically calculated? For instance, do certain factors change how much the customer or developer on your water network pays? 8. Does your department utilize a GIS tool for your town’s water meters? If so, is this used when calculating fees and bills? 9. Is there anything you would like to add that you think may be helpful on this matter?
A22: Questions | B22: Y/N | C22: Notes / transcription
A23: Q1
A24: Q2
A25: Q3
A26: Q4
A27: Q5
A28: Q6
A29: Q7
A30: Q8
A31: Q9

Sheet Davenport
A1: County | B1: City/Town | C1: Pop. tier | D1: Contact Name | E1: Title | F1: Email | G1: Phone | H1: Alt Phone | I1: Website/Source | J1: Cross-reference | K1: Outreach Status | L1: Date Contacted | M1: Follow-up Date | N1: Notes
A2: Lincoln | B2: Davenport | C2: Small (~1.7k) | D2: Dave Orvis | E2: Public Works Director | G2: (509)-725-7041 | I2: davenportwa.us | K2: Not contacted
A5: 1. Alright, for starters what is your formal title in relation to [city] , [name]? 2. Do you happen to know the GMA status of your county? 3. Would you say the population of [city] has grown significantly in the last 10 years? 4. Does your town sell or provide water to any neighboring towns? 5. Has your department needed to expand the water infrastructure for your city at any point in the last 10 years? 6. How does your department raise funds for expansions of water infrastructure? Do you levy any upfront fees, like system development charges or capacity fee charges? 7. How are those funding methods typically calculated? For instance, do certain factors change how much the customer or developer on your water network pays? 8. Does your department utilize a GIS tool for your town’s water meters? If so, is this used when calculating fees and bills? 9. Is there anything you would like to add that you think may be helpful on this matter?
E6: mostly farming. We do irrigation.
E9: generalized money amount or working in right of way
E12: trying to sepearate farming from franchise agreements
E15: franchising is working with a contractor under contract to do all work within a county right of way, good for 10 years.
E17: only water we deal with is irrigation. On a well or a shared well. Wells are privatley owned
E20: Case by case on piping size, no rates based on piping size.
A22: Questions | B22: Y/N | C22: Notes / transcription | E22: "approaches" piping. Working within the right of way fee, an approach fee. A farmers approach costs less than a house (50 for farmers 100 for residential, 150 for businesses rough numbers)
A23: Q1 | C23: Public Works director for Davenport
A24: Q2 | B24: ? | C24: (didn’t ask) | E24: usually issue around 100 right of way permits, fairly limited. After covid had a lot of people move over here.
A25: Q3 | B25: Y (kinda) | C25: Had a good amount of people move here for political reasons during and after COVID. usually issue around 100 "right of way"/ "approach" permits a year, which is fairly limited. 70 percent of the land is farm land, very large county, bigger than rhode island or delaware, only around 1,250 people
A26: Q4 | B26: N | C26: We do not sell water to other towns. | E26: I deal with county oads pits and quarry, health department deals with this. Budget is around 8 million, mostly do septic
A27: Q5 | B27: N | C27: This town does not have a utilities system for freshwater in the traditional sense (therefore they never are the ones dealing with infrastructure expansions directly). The health department deals with the Sewage. We do deal with irrigation. We franchise with a utilities / engineering corp. that privately owns the water infrastructure. Franchising is working with a contractor under contract to do all work within a county right of way, good for 10 years.
A28: Q6 | C28: We connect development to the private water network via "approaches" on a case by case basis. Piping size is simply based on what is best for the surrounding area (making sure we arent erroding any roads). We charge a "right of way fee" for new approaches based on the type of development ($50 for farmers $100 for residential, $150 for businesses rough numbers) | E28: 70 percent of the land is farm land, very large county, bigger than rhode island or delaware, only around 1,250
A29: Q7
A30: Q8 | B30: N | C30: No GIS tool, because there are no meters | E30: No industry, limited money in the area.
A31: Q9
E32: new meters installed in town. Health dept number: 5097251001

Sheet Odessa
A1: County | B1: City/Town | C1: Pop. tier | D1: Contact Name | E1: Title | F1: Email | G1: Phone | H1: Alt Phone | I1: Website/Source | J1: Cross-reference | K1: Outreach Status | L1: Date Contacted | M1: Follow-up Date | N1: Notes
A2: Lincoln | B2: Odessa | C2: Small (~1k) | D2: Gerald Greenwalt | E2: Public Works Director | F2: pwd@odessawa.org | G2: (509) 988-2401 | H2: (509) 988-3093 | I2: odessawa.org; MRSC | J2: $ | K2: Not contacted
A5: 1. Alright, for starters what is your formal title in relation to [city] , [name]? 2. Do you happen to know the GMA status of your county? 3. Would you say the population of [city] has grown significantly in the last 10 years? 4. Does your town sell or provide water to any neighboring towns? 5. Has your department needed to expand the water infrastructure for your city at any point in the last 10 years? 6. How does your department raise funds for expansions of water infrastructure? Do you levy any upfront fees, like system development charges or capacity fee charges? 7. How are those funding methods typically calculated? For instance, do certain factors change how much the customer or developer on your water network pays? 8. Does your department utilize a GIS tool for your town’s water meters? If so, is this used when calculating fees and bills? 9. Is there anything you would like to add that you think may be helpful on this matter?
A22: Questions | B22: Y/N | C22: Notes / transcription
A23: Q1
A24: Q2
A25: Q3
A26: Q4
A27: Q5
A28: Q6
A29: Q7
A30: Q8
A31: Q9

Sheet Harrington
A1: County | B1: City/Town | C1: Pop. tier | D1: Contact Name | E1: Title | F1: Email | G1: Phone | H1: Alt Phone | I1: Website/Source | J1: Cross-reference | K1: Outreach Status | L1: Date Contacted | M1: Follow-up Date | N1: Notes
A2: Lincoln | B2: Harrington | C2: Small (~400) | D2: (unnamed) | E2: — see notes | F2: clerk@harrington.city | G2: (509) 253-4345 | I2: harrington.city; MRSC | K2: Not contacted
A5: 1. Alright, for starters what is your formal title in relation to [city] , [name]? 2. Do you happen to know the GMA status of your county? 3. Would you say the population of [city] has grown significantly in the last 10 years? 4. Does your town sell or provide water to any neighboring towns? 5. Has your department needed to expand the water infrastructure for your city at any point in the last 10 years? 6. How does your department raise funds for expansions of water infrastructure? Do you levy any upfront fees, like system development charges or capacity fee charges? 7. How are those funding methods typically calculated? For instance, do certain factors change how much the customer or developer on your water network pays? 8. Does your department utilize a GIS tool for your town’s water meters? If so, is this used when calculating fees and bills? 9. Is there anything you would like to add that you think may be helpful on this matter?
A22: Questions | B22: Y/N | C22: Notes / transcription
A23: Q1
A24: Q2
A25: Q3
A26: Q4
A27: Q5
A28: Q6
A29: Q7
A30: Q8
A31: Q9

Sheet Reardan
A1: County | B1: City/Town | C1: Pop. tier | D1: Contact Name | E1: Title | F1: Email | G1: Phone | H1: Alt Phone | I1: Website/Source | J1: Cross-reference | K1: Outreach Status | L1: Date Contacted | M1: Follow-up Date | N1: Notes
A2: Lincoln | B2: Reardan | C2: Small (~600) | D2: Tony DeSautel | E2: Town Clerk/Treasurer | F2: clerk@townofreardan.com | G2: (509) 499-5070 | I2: https://reardanwa.gov/index.asp?SEC=55D012BF-68BF-4417-BD1B-7CDF35B24375 | J2: $, no email listed | K2: Not contacted
A5: 1. Alright, for starters what is your formal title in relation to [city] , [name]? 2. Do you happen to know the GMA status of your county? 3. Would you say the population of [city] has grown significantly in the last 10 years? 4. Does your town sell or provide water to any neighboring towns? 5. Has your department needed to expand the water infrastructure for your city at any point in the last 10 years? 6. How does your department raise funds for expansions of water infrastructure? Do you levy any upfront fees, like system development charges or capacity fee charges? 7. How are those funding methods typically calculated? For instance, do certain factors change how much the customer or developer on your water network pays? 8. Does your department utilize a GIS tool for your town’s water meters? If so, is this used when calculating fees and bills? 9. Is there anything you would like to add that you think may be helpful on this matter?
A22: Questions | B22: Y/N | C22: Notes / transcription
A23: Q1
A24: Q2
A25: Q3
A26: Q4
A27: Q5
A28: Q6
A29: Q7
A30: Q8
A31: Q9

Sheet Wilbur
A1: County | B1: City/Town | C1: Pop. tier | D1: Contact Name | E1: Title | F1: Email | G1: Phone | H1: Alt Phone | I1: Website/Source | J1: Cross-reference | K1: Outreach Status | L1: Date Contacted | M1: Follow-up Date | N1: Notes
A2: Lincoln | B2: Wilbur | C2: Small (~800) | D2: Eric Morris, Melissa Bulger | E2: Public Works Foreman, Clerk Treasurer | F2: pw@wilburwa.com , deputyclerk@wilburwa.com | G2: (509) 647-5821 (ask for Melissa) | H2: (509) 641-2008 | I2: wilburwa.gov | J2: $ | K2: Not contacted
E3: Called Eric, told me to call alt number (because they do the budgeting not him)
A5: 1. Alright, for starters what is your formal title in relation to [city] , [name]? 2. Do you happen to know the GMA status of your county? 3. Would you say the population of [city] has grown significantly in the last 10 years? 4. Does your town sell or provide water to any neighboring towns? 5. Has your department needed to expand the water infrastructure for your city at any point in the last 10 years? 6. How does your department raise funds for expansions of water infrastructure? Do you levy any upfront fees, like system development charges or capacity fee charges? 7. How are those funding methods typically calculated? For instance, do certain factors change how much the customer or developer on your water network pays? 8. Does your department utilize a GIS tool for your town’s water meters? If so, is this used when calculating fees and bills? 9. Is there anything you would like to add that you think may be helpful on this matter?
A22: Questions | B22: Y/N | C22: Notes / transcription
A23: Q1 | C23: clerk treasurer, Melissa Bulger
A24: Q2 | B24: Y | C24: Partial planning
A25: Q3 | B25: N | C25: No. Very minimal growth
A26: Q4 | B26: N. | C26: No
A27: Q5 | B27: Y | C27: always hooking up new construction, nothing significant though. New units, newconnections, nothing else.
A28: Q6 | B28: Y | C28: We implemented an impact fee. They are specifically to go to future expansoin in water, sewer and streets. Things are starting to get expoensive so they are worth planning for. | D28: ***This is significant, they are the only town in a partial planning county that utilizes impact fees out of everyone I called so far (5-14-26)
A29: Q7 | C29: WE went off of what is similar to the county
A30: Q8 | B30: Y | C30: We do have a GIS system, not sued for basic water metering, mostly used for construction. Never used for asset valuation
A31: Q9 | C31: When I do the budgetting for water, what we are looking at is how expenditures are chantging over the last year. Anything that we can forsee, like gas prices jumping, anything we think will be an impact we try to add that as a thought process for our budget.

Sheet Omak
A1: County | B1: City/Town | C1: Pop. tier | D1: Contact Name | E1: Title | F1: Email | G1: Phone | H1: Alt Phone | I1: Website/Source | J1: Cross-reference | K1: Outreach Status | L1: Date Contacted | M1: Follow-up Date | N1: Notes
A2: Okanogan | B2: Omak | C2: Mid (~5k) | D2: Wayne Beetchenow | E2: Public Works Director | F2: publicworks@omakcity.com | G2: (509) 826-1170 | I2: omakcity.com | J2: $ | K2: Not contacted
A5: 1. Alright, for starters what is your formal title in relation to [city] , [name]? 2. Do you happen to know the GMA status of your county? 3. Would you say the population of [city] has grown significantly in the last 10 years? 4. Does your town sell or provide water to any neighboring towns? 5. Has your department needed to expand the water infrastructure for your city at any point in the last 10 years? 6. How does your department raise funds for expansions of water infrastructure? Do you levy any upfront fees, like system development charges or capacity fee charges? 7. How are those funding methods typically calculated? For instance, do certain factors change how much the customer or developer on your water network pays? 8. Does your department utilize a GIS tool for your town’s water meters? If so, is this used when calculating fees and bills? 9. Is there anything you would like to add that you think may be helpful on this matter?
A22: Questions | B22: Y/N | C22: Notes / transcription
A23: Q1 | B23: Y
A24: Q2 | B24: N
A25: Q3 | B25: N
A26: Q4 | B26: N
A27: Q5 | B27: Y | C27: Developer driven. Just new connections
A28: Q6 | B28: Y | C28: Developers develop it to our standards then we take it over. We use development fees for commissions, not sure what it is exactly though (between SDCs and CFCs).
A29: Q7 | B29: N
A30: Q8 | B30: Y | C30: We use G works for assets, GIS is a part of that too
A31: Q9 | C31: [very short and to the point]

Sheet Okanogan (city)
A1: County | B1: City/Town | C1: Pop. tier | D1: Contact Name | E1: Title | F1: Email | G1: Phone | H1: Alt Phone | I1: Website/Source | J1: Cross-reference | K1: Outreach Status | L1: Date Contacted | M1: Follow-up Date | N1: Notes
A2: Okanogan | B2: Okanogan (city) | C2: Small (~2.5k) | D2: Shawn Davisson | E2: Director of Public Works | F2: publicworks@okanagancity.com | G2: (509) 422-3600 ext. 17 | I2: okanogancity.com | J2: $ | K2: Not contacted
A5: 1. Alright, for starters what is your formal title in relation to [city] , [name]? 2. Do you happen to know the GMA status of your county? 3. Would you say the population of [city] has grown significantly in the last 10 years? 4. Does your town sell or provide water to any neighboring towns? 5. Has your department needed to expand the water infrastructure for your city at any point in the last 10 years? 6. How does your department raise funds for expansions of water infrastructure? Do you levy any upfront fees, like system development charges or capacity fee charges? 7. How are those funding methods typically calculated? For instance, do certain factors change how much the customer or developer on your water network pays? 8. Does your department utilize a GIS tool for your town’s water meters? If so, is this used when calculating fees and bills? 9. Is there anything you would like to add that you think may be helpful on this matter?
A22: Questions | B22: Y/N | C22: Notes / transcription
A23: Q1
A24: Q2
A25: Q3
A26: Q4
A27: Q5
A28: Q6
A29: Q7
A30: Q8
A31: Q9

Sheet Brewster
A1: County | B1: City/Town | C1: Pop. tier | D1: Contact Name | E1: Title | F1: Email | G1: Phone | H1: Alt Phone | I1: Website/Source | J1: Cross-reference | K1: Outreach Status | L1: Date Contacted | M1: Follow-up Date | N1: Notes
A2: Okanogan | B2: Brewster | C2: Small (~2.4k) | D2: Lee Webster | E2: Public Works Director | F2: Lee.Webster@brewsterwa.us | G2: (509) 689-3464 | H2: (509) 689-3705 | I2: brewster-wa.com; Rep. Engell legislative update | J2: $, department # update & personal email | K2: Not contacted
A5: 1. Alright, for starters what is your formal title in relation to [city] , [name]? 2. Do you happen to know the GMA status of your county? 3. Would you say the population of [city] has grown significantly in the last 10 years? 4. Does your town sell or provide water to any neighboring towns? 5. Has your department needed to expand the water infrastructure for your city at any point in the last 10 years? 6. How does your department raise funds for expansions of water infrastructure? Do you levy any upfront fees, like system development charges or capacity fee charges? 7. How are those funding methods typically calculated? For instance, do certain factors change how much the customer or developer on your water network pays? 8. Does your department utilize a GIS tool for your town’s water meters? If so, is this used when calculating fees and bills? 9. Is there anything you would like to add that you think may be helpful on this matter?
A22: Questions | B22: Y/N | C22: Notes / transcription
A23: Q1
A24: Q2
A25: Q3
A26: Q4
A27: Q5
A28: Q6
A29: Q7
A30: Q8
A31: Q9

Sheet Oroville
A1: County | B1: City/Town | C1: Pop. tier | D1: Contact Name | E1: Title | F1: Email | G1: Phone | H1: Alt Phone | I1: Website/Source | J1: Cross-reference | K1: Outreach Status | L1: Date Contacted | M1: Follow-up Date | N1: Notes
A2: Okanogan | B2: Oroville | C2: Small (~1.7k) | D2: Steve Thompson | E2: City Superintendent | F2: PublicWorks@orovillewa.gov | G2: (509) 476-2106 | I2: oroville-wa.com; MRSC | J2: $ | K2: Not contacted
A5: 1. Alright, for starters what is your formal title in relation to [city] , [name]? 2. Do you happen to know the GMA status of your county? 3. Would you say the population of [city] has grown significantly in the last 10 years? 4. Does your town sell or provide water to any neighboring towns? 5. Has your department needed to expand the water infrastructure for your city at any point in the last 10 years? 6. How does your department raise funds for expansions of water infrastructure? Do you levy any upfront fees, like system development charges or capacity fee charges? 7. How are those funding methods typically calculated? For instance, do certain factors change how much the customer or developer on your water network pays? 8. Does your department utilize a GIS tool for your town’s water meters? If so, is this used when calculating fees and bills? 9. Is there anything you would like to add that you think may be helpful on this matter?
A22: Questions | B22: Y/N | C22: Notes / transcription
A23: Q1 | C23: city superintendent
A24: Q2 | B24: Y | C24: we are following it but we don’t have to
A25: Q3 | B25: N | C25: No
A26: Q4 | B26: N | C26: Provide some to the county but not other towns
A27: Q5 | B27: N | C27: Renewing mainlines. We have a graph that is supposed to run a larger line
A28: Q6 | B28: Y | C28: We charge upront fees (SDC or CFC), Not sure exactly what they are though
A29: Q7 | B29: N | C29: Doesn’t know
A30: Q8 | B30: Y | C30: mainly for geographic understanding, not as much for asset valuation
A31: Q9

Sheet Tonasket
A1: County | B1: City/Town | C1: Pop. tier | D1: Contact Name | E1: Title | F1: Email | G1: Phone | H1: Alt Phone | I1: Website/Source | J1: Cross-reference | K1: Outreach Status | L1: Date Contacted | M1: Follow-up Date | N1: Notes
A2: Okanogan | B2: Tonasket | C2: Small (~1k) | D2: Darren Johnson | E2: City / Public Works Superintendent | F2: djohnson.tonasket@nvinet.com | G2: (509) 322-7432 | I2: tonasketwa.gov; MRSC | J2: $ | K2: Not contacted
A6: 1. Alright, for starters what is your formal title in relation to [city] , [name]? 2. Do you happen to know the GMA status of your county? 3. Would you say the population of [city] has grown significantly in the last 10 years? 4. Does your town sell or provide water to any neighboring towns? 5. Has your department needed to expand the water infrastructure for your city at any point in the last 10 years? 6. How does your department raise funds for expansions of water infrastructure? Do you levy any upfront fees, like system development charges or capacity fee charges? 7. How are those funding methods typically calculated? For instance, do certain factors change how much the customer or developer on your water network pays? 8. Does your department utilize a GIS tool for your town’s water meters? If so, is this used when calculating fees and bills? 9. Is there anything you would like to add that you think may be helpful on this matter?
A23: Questions | B23: Y/N | C23: Notes / transcription
A24: Q1 | C24: City superintendent
A25: Q2 | B25: N | C25: 1,000 - 1,100 people
A26: Q3 | B26: N | C26: No, population stays right where its at. If anything it may have gone down because apple warehouses have shutdown and moved to chelan and wenatchee
A27: Q4 | B27: N | C27: We do sell to people that are off grid, so they get a water permit and get some amount of water at a time. We don’t sell to any towns or organizations though.
A28: Q5 | B28: N | C28: No.
A29: Q6 | B29: Y | C29: There is a hookup fee. Varies by pipe size.
A30: Q7 | B30: Y | C30: Standard fee for 3 quarter inch, then you pay the difference on if you want a bigger size. Called a Connection Fee.
A31: Q8 | B31: Y (in progress) | C31: In the progress of putting something like that together. Probably will be used both for assets and for meters. Used to be hand read meters, now we use radio read which makes GIS necessary.
A32: Q9

Sheet Pateros
A1: County | B1: City/Town | C1: Pop. tier | D1: Contact Name | E1: Title | F1: Email | G1: Phone | H1: Alt Phone | I1: Website/Source | J1: Cross-reference | K1: Outreach Status | L1: Date Contacted | M1: Follow-up Date | N1: Notes
A2: Okanogan | B2: Pateros | C2: Small (~600) | D2: Jord Wilson | E2: City Manager | F2: jwilson@pateros.us | G2: (509) 499-9670 | H2: (509) 923-2571 | I2: pateros.com | J2: $ | K2: Not contacted
A5: 1. Alright, for starters what is your formal title in relation to [city] , [name]? 2. Do you happen to know the GMA status of your county? 3. Would you say the population of [city] has grown significantly in the last 10 years? 4. Does your town sell or provide water to any neighboring towns? 5. Has your department needed to expand the water infrastructure for your city at any point in the last 10 years? 6. How does your department raise funds for expansions of water infrastructure? Do you levy any upfront fees, like system development charges or capacity fee charges? 7. How are those funding methods typically calculated? For instance, do certain factors change how much the customer or developer on your water network pays? 8. Does your department utilize a GIS tool for your town’s water meters? If so, is this used when calculating fees and bills? 9. Is there anything you would like to add that you think may be helpful on this matter?
A22: Questions | B22: Y/N | C22: Notes / transcription
A23: Q1 | B23: Y | C23: Jord, City Manager
A24: Q2 | B24: Y | C24: not required to comply to gma
A25: Q3 | B25: N | C25: 10 people have come, so no. We have around 600 people total.
A26: Q4 | B26: N | C26: no.
A27: Q5 | B27: Y | C27: one major expansion. Finished it in 2019
A28: Q6 | B28: Y | C28: off the top of my head, It was a $7.2 million project, we borrowed 1 million. The rest was through legislative appropriations and grants. No levying of upfront devlopment fees. We are maxed out on developmnet, due to our geography (mountains on one side, water on the other). We only have about 40 acres left for potential development.
A29: Q7 | B29: N/A | C29: N/A
A30: Q8 | B30: Y | C30: Yes we use a GIS, we have an asset management program. We have GIS locations on them. We also use a radio read for meters. We have asset management in our Gis, but we don’t really use it for budgetting. We mainly use it as a historical tool to know what happened in the ground
A31: Q9 | C31: [nothing more to add]

Sheet Twisp
A1: County | B1: City/Town | C1: Pop. tier | D1: Contact Name | E1: Title | F1: Email | G1: Phone | H1: Alt Phone | I1: Website/Source | J1: Cross-reference | K1: Outreach Status | L1: Date Contacted | M1: Follow-up Date | N1: Notes
A2: Okanogan | B2: Twisp | C2: Small (~1k) | D2: Andrew Denham | E2: Assistant Public Works Director | F2: pwasdirector@townoftwisp.com | I2: townoftwisp.com | J2: $ | K2: Not contacted
A6: 1. Alright, for starters what is your formal title in relation to [city] , [name]? 2. Do you happen to know the GMA status of your county? 3. Would you say the population of [city] has grown significantly in the last 10 years? 4. Does your town sell or provide water to any neighboring towns? 5. Has your department needed to expand the water infrastructure for your city at any point in the last 10 years? 6. How does your department raise funds for expansions of water infrastructure? Do you levy any upfront fees, like system development charges or capacity fee charges? 7. How are those funding methods typically calculated? For instance, do certain factors change how much the customer or developer on your water network pays? 8. Does your department utilize a GIS tool for your town’s water meters? If so, is this used when calculating fees and bills? 9. Is there anything you would like to add that you think may be helpful on this matter?
A23: Questions | B23: Y/N | C23: Notes / transcription
A24: Q1
A25: Q2
A26: Q3
A27: Q4
A28: Q5
A29: Q6
A30: Q7
A31: Q8
A32: Q9

Sheet Winthrop
A1: County | B1: City/Town | C1: Pop. tier | D1: Contact Name | E1: Title | F1: Email | G1: Phone | H1: Alt Phone | I1: Website/Source | J1: Cross-reference | K1: Outreach Status | L1: Date Contacted | M1: Follow-up Date | N1: Notes
A2: Okanogan | B2: Winthrop | C2: Small (~500) | D2: Jake Gates | E2: Public Works Superintendent | F2: jacob@townofwinthrop.com | G2: 509-341-4130 | H2: (509) 996-2320 [department #] | I2: townofwinthrop.com; MRSC | J2: $, no main phone # listed | K2: Not contacted
A5: 1. Alright, for starters what is your formal title in relation to [city] , [name]? 2. Do you happen to know the GMA status of your county? 3. Would you say the population of [city] has grown significantly in the last 10 years? 4. Does your town sell or provide water to any neighboring towns? 5. Has your department needed to expand the water infrastructure for your city at any point in the last 10 years? 6. How does your department raise funds for expansions of water infrastructure? Do you levy any upfront fees, like system development charges or capacity fee charges? 7. How are those funding methods typically calculated? For instance, do certain factors change how much the customer or developer on your water network pays? 8. Does your department utilize a GIS tool for your town’s water meters? If so, is this used when calculating fees and bills? 9. Is there anything you would like to add that you think may be helpful on this matter?
A22: Questions | B22: Y/N | C22: Notes / transcription
A23: Q1 | C23: superintendent, same as director
A24: Q2 | B24: N | C24: not growth management
A25: Q3 | B25: Y | C25: grown by 3 percent
A26: Q4 | B26: N | C26: Sell bulk water to wells and people whos water goes dry
A27: Q5 | B27: Y | C27: We are in the process of expanding right now. Expanding by 263 connections last year, working on a second well, and arights for a third well, second well goes in in the summer
A28: Q6 | C28: We use system development charges, we also upped our rate by 12 dollars. For the water distribution we take out loans from federal, we take as many grants as we can, but it’s a small population so hard to get that funding
A29: Q7 | C29: Through ERUs, just ERUs
A30: Q8 | B30: Y | C30: Presently working on that. WE will mostly be using for asset valuation.
A31: Q9

Sheet Skamania County - General Publi
A1: County | B1: City/Town | C1: Pop. tier | D1: Contact Name | E1: Title | F1: Email | G1: Phone | H1: Alt Phone | I1: Website/Source | J1: Cross-reference | K1: Outreach Status | L1: Date Contacted | M1: Follow-up Date | N1: Notes
A2: Skamania | B2: Skamania County - General Public Works (for unincorporated towns) | D2: David Waymire | E2: Public Works & Community Development Director | F2: publicworks@co.skamania.wa.us | G2: (509) 427-3909 | H2: (509) 427-3910 [department #] | I2: https://www.skamaniacounty.org/departments-offices/public-works | J2: $ | K2: Not contacted
A5: 1. Alright, for starters what is your formal title in relation to [city] , [name]? 2. Do you happen to know the GMA status of your county? 3. Would you say the population of [city] has grown significantly in the last 10 years? 4. Does your town sell or provide water to any neighboring towns? 5. Has your department needed to expand the water infrastructure for your city at any point in the last 10 years? 6. How does your department raise funds for expansions of water infrastructure? Do you levy any upfront fees, like system development charges or capacity fee charges? 7. How are those funding methods typically calculated? For instance, do certain factors change how much the customer or developer on your water network pays? 8. Does your department utilize a GIS tool for your town’s water meters? If so, is this used when calculating fees and bills? 9. Is there anything you would like to add that you think may be helpful on this matter?
F20: David W.
A21: Melanie Sharp
A22: Questions | B22: Y/N | C22: Notes / transcription | D22: Column1 | F22: Questions | G22: Y/N | H22: Notes / transcription
A23: Q1 | C23: water manager | F23: Q1
A24: Q2 | C24: non Gma | D24: we only carson and underwood | F24: Q2
A25: Q3 | C25: growth is not significant in comparison. | F25: Q3
A26: Q4 | C26: no. | F26: Q4
A27: Q5 | C27: yes. Continually expanding. Mostly just new connections | F27: Q5
A28: Q6 | C28: service areaa boundary isnt expanding. Upgrades to tatment planst, connection fees. | F28: Q6
A29: Q7 | C29: we cost of service analysis, huge number of variables. Calculated based off of grrowth primarily. We use system development fees | F29: Q7
A30: Q8 | C30: yes, we use a gis tool for water metering. Used for customer billing in all of our enterprise software system | F30: Q8
A31: Q9 | C31: our fees are pretty high. Big variety of SDCs. We do whole electric systm, water is more localized. Stevenson and north boonnevile ddo their own. Skamania landing has their own water system. Rural systems do their own thing. They sometimes hire out contracotrs if they are real small. We are taking a preactive approach for repairs and older things breaking. | F31: Q9 | H31: Skamania county public utilities district. Both towns manage their own. Gneral water utilities for other communities is the skamnaia county public utilities district. 5094275126. city of bonneville Cody rosander (5094275970). Not sure who to contact for bonneville.

Sheet Stevenson
A1: County | B1: City/Town | C1: Pop. tier | D1: Contact Name | E1: Title | F1: Email | G1: Phone | H1: Alt Phone | I1: Website/Source | J1: Cross-reference | K1: Outreach Status | L1: Date Contacted | M1: Follow-up Date | N1: Notes
A2: Skamania | B2: Stevenson | C2: Small (~1.6k) | D2: Cody Rosander, (no longer Carolyn Sourek) | E2: Public Works Director | G2: (509) 427-5970 | H2: (509) 427-5970 [department #] | I2: ci.stevenson.wa.us; council minutes June 2024 | J2: $, no main phone # listed | K2: Not contacted
A5: 1. Alright, for starters what is your formal title in relation to [city] , [name]? 2. Do you happen to know the GMA status of your county? 3. Would you say the population of [city] has grown significantly in the last 10 years? 4. Does your town sell or provide water to any neighboring towns? 5. Has your department needed to expand the water infrastructure for your city at any point in the last 10 years? 6. How does your department raise funds for expansions of water infrastructure? Do you levy any upfront fees, like system development charges or capacity fee charges? 7. How are those funding methods typically calculated? For instance, do certain factors change how much the customer or developer on your water network pays? 8. Does your department utilize a GIS tool for your town’s water meters? If so, is this used when calculating fees and bills? 9. Is there anything you would like to add that you think may be helpful on this matter?
A22: Questions | B22: Y/N | C22: Notes / transcription
A23: Q1 | B23: Y | C23: Public works director of Stevenson
A24: Q2 | B24: N | C24: Found old census, still didn’t really understand what is meant by this. [giving him full wording "Growth management Act" didn’t change that]
A25: Q3 | B25: Y | C25: yes its grown pretty significantly.
A26: Q4 | B26: N | C26: we have hydrant meters, not necessarily selling to other towns, but ppl can purchase water and we have out of boundary connections. We have some grandfathered in in connections that otherwise wouldnt be allowed today | D26: Edge case
A27: Q5 | B27: Y ,water main, sources | C27: We've done a water main expansion. We replaced it with bigger size pipe. We are currently a surface level facility, with a failing water intake, loosing capacity not directly caused by population or residents. Growth definitely plays an impact into how much we need to produce, we are runing low and doing a lot of engineering work to redo our surface water system. We do have a ground water well, but not used as much. Under bedrock and header system, we seem to have significant damage. we used to pull an unlimiited amount, we seem more restricted to 3 to 4 hundred gallons per minute. This is a problem now with increasing demand, where it didnt used to be.
A28: Q6 | B28: G, SDC, rates | C28: Largly grants and general funds, coming out of the water budget itself. Primarily funded through SDCs and rate payments.
A29: Q7 | B29: Y, cost analysis, fixture count | C29: I take a look at their health plan, how many water fixtures they have, how far from the mainline they are. Goes through a calculator that abides by the plumbing code. We do a tiered system. For instance a small house will have a fixture count of 18-22, anything below 25 will be our lowest tier SDC. Next tier is 30 fixtures, one tier above that as well (3 residential tiers total). We have a few seperate tiers for commercial as well.
A30: Q8 | B30: Y, N (for asset val) | C30: We do use Gis for all of our public works assets. We do not use it for asset valuation, mostly material type and location.
A31: Q9 | C31: We try to incentivize multi home and commercial development. We are likely going to need to increase our rates within the next year to pay for our network. We raised our SDCs maybe 3-4 years ago. They are already on the higher side. They were pretty cheap before then.

Sheet North Bonneville
A1: County | B1: City/Town | C1: Pop. tier | D1: Contact Name | E1: Title | F1: Email | G1: Phone | H1: Alt Phone | I1: Website/Source | J1: Cross-reference | K1: Outreach Status | L1: Date Contacted | M1: Follow-up Date | N1: Notes
A2: Skamania | B2: North Bonneville | C2: Small (~1.4k) | D2: Bryan Henrichsen | E2: — see notes | F2: bryanh@northbonneville.net | G2: 541-490-2370 | I2: https://northbonneville.net/government/ | J2: $, fixed person, phone #, and email | K2: Not contacted
A5: 1. Alright, for starters what is your formal title in relation to [city] , [name]? 2. Do you happen to know the GMA status of your county? 3. Would you say the population of [city] has grown significantly in the last 10 years? 4. Does your town sell or provide water to any neighboring towns? 5. Has your department needed to expand the water infrastructure for your city at any point in the last 10 years? 6. How does your department raise funds for expansions of water infrastructure? Do you levy any upfront fees, like system development charges or capacity fee charges? 7. How are those funding methods typically calculated? For instance, do certain factors change how much the customer or developer on your water network pays? 8. Does your department utilize a GIS tool for your town’s water meters? If so, is this used when calculating fees and bills? 9. Is there anything you would like to add that you think may be helpful on this matter?
A22: Questions | B22: Y/N | C22: Notes / transcription
A23: Q1
A24: Q2
A25: Q3
A26: Q4
A27: Q5
A28: Q6
A29: Q7
A30: Q8
A31: Q9

Sheet Wahkiakum County - General Publ
A1: County | B1: City/Town | C1: Pop. tier | D1: Contact Name | E1: Title | F1: Email | G1: Phone | H1: Alt Phone | I1: Website/Source | J1: Cross-reference | K1: Outreach Status | L1: Date Contacted | M1: Follow-up Date | N1: Notes
A2: Wahkiakum | B2: Wahkiakum County - General Public Works (for unincorporated towns) | D2: Chuck Beyer | E2: Public Works Director | G2: 360-795-3301 | I2: https://co.wahkiakum.wa.us/Directory.aspx?DID=23 | J2: $, no email listed | K2: Not contacted
A4: Dan Kay is manager. 360- 795-3266
A6: 1. Alright, for starters what is your formal title in relation to [city] , [name]? 2. Do you happen to know the GMA status of your county? 3. Would you say the population of [city] has grown significantly in the last 10 years? 4. Does your town sell or provide water to any neighboring towns? 5. Has your department needed to expand the water infrastructure for your city at any point in the last 10 years? 6. How does your department raise funds for expansions of water infrastructure? Do you levy any upfront fees, like system development charges or capacity fee charges? 7. How are those funding methods typically calculated? For instance, do certain factors change how much the customer or developer on your water network pays? 8. Does your department utilize a GIS tool for your town’s water meters? If so, is this used when calculating fees and bills? 9. Is there anything you would like to add that you think may be helpful on this matter?
F21: Chuck (main, but doesn't do water)
A23: Questions | B23: Y/N | C23: Notes / transcription | F23: Questions | G23: Y/N | H23: Notes / transcription | I23: Column1
A24: Q1 | F24: Q1 | G24: Y
A25: Q2 | F25: Q2 | G25: Y | H25: non-planning
A26: Q3 | F26: Q3 | H26: I wouldn’t say significantly, only 45 hundered in the full county
A27: Q4 | F27: Q4 | H27: Only one encoroporated town in the county. Wakiakum , wakikum pud #1 controls all of the water
A28: Q5 | F28: Q5 | H28: we arent involved
A29: Q6 | F29: Q6 | I29: daniel K is manager. 360- 795-3266
A30: Q7 | F30: Q7
A31: Q8 | F31: Q8
A32: Q9 | F32: Q9

Sheet Cathlamet
A1: County | B1: City/Town | C1: Pop. tier | D1: Contact Name | E1: Title | F1: Email | G1: Phone | H1: Alt Phone | I1: Website/Source | J1: Cross-reference | K1: Outreach Status | L1: Date Contacted | M1: Follow-up Date | N1: Notes
A2: Wahkiakum | B2: Cathlamet | C2: Small (~520) | D2: Troy Gorley | E2: Utility / Maintenance | F2: troy@townofcathlamet.com | G2: (360) 795-3203 ext. 3 | H2: (360) 849-9484 | I2: townofcathlamet.com | J2: $ | K2: Not contacted
A5: 1. Alright, for starters what is your formal title in relation to [city] , [name]? 2. Do you happen to know the GMA status of your county? 3. Would you say the population of [city] has grown significantly in the last 10 years? 4. Does your town sell or provide water to any neighboring towns? 5. Has your department needed to expand the water infrastructure for your city at any point in the last 10 years? 6. How does your department raise funds for expansions of water infrastructure? Do you levy any upfront fees, like system development charges or capacity fee charges? 7. How are those funding methods typically calculated? For instance, do certain factors change how much the customer or developer on your water network pays? 8. Does your department utilize a GIS tool for your town’s water meters? If so, is this used when calculating fees and bills? 9. Is there anything you would like to add that you think may be helpful on this matter?
A22: Questions | B22: Y/N | C22: Notes / transcription
A23: Q1
A24: Q2
A25: Q3
A26: Q4
A27: Q5
A28: Q6
A29: Q7
A30: Q8
A31: Q9 | C31: Over text: "Hey Rowan sorry I missed your call. I got your message. I don’t deal withg the water or sewer. Our PUD has all of that now. You may want to contact them. Have a great rest of your day. Troy Gorley"

Sheet Pullman
A1: County | B1: City/Town | C1: Pop. tier | D1: Contact Name | E1: Title | F1: Email | G1: Phone | H1: Alt Phone | I1: Website/Source | J1: Cross-reference | K1: Outreach Status | L1: Date Contacted | M1: Follow-up Date | N1: Notes
A2: Whitman | B2: Pullman | C2: Large (~33k) | D2: Frank Mulcahy | E2: Public Works Director | G2: (509) 338-3220 [department #] | I2: pullman-wa.gov (Dec 2025 announcement) | J2: $, no email available | K2: Not contacted
A5: 1. Alright, for starters what is your formal title in relation to [city] , [name]? 2. Do you happen to know the GMA status of your county? 3. Would you say the population of [city] has grown significantly in the last 10 years? 4. Does your town sell or provide water to any neighboring towns? 5. Has your department needed to expand the water infrastructure for your city at any point in the last 10 years? 6. How does your department raise funds for expansions of water infrastructure? Do you levy any upfront fees, like system development charges or capacity fee charges? 7. How are those funding methods typically calculated? For instance, do certain factors change how much the customer or developer on your water network pays? 8. Does your department utilize a GIS tool for your town’s water meters? If so, is this used when calculating fees and bills? 9. Is there anything you would like to add that you think may be helpful on this matter?
A22: Questions | B22: Y/N | C22: Notes / transcription
A23: Q1
A24: Q2
A25: Q3
A26: Q4
A27: Q5
A28: Q6
A29: Q7
A30: Q8
A31: Q9

Sheet Colfax
A1: County | B1: City/Town | C1: Pop. tier | D1: Contact Name | E1: Title | F1: Email | G1: Phone | H1: Alt Phone | I1: Website/Source | J1: Cross-reference | K1: Outreach Status | L1: Date Contacted | M1: Follow-up Date | N1: Notes
A2: Whitman | B2: Colfax | C2: Small (~2.8k) | D2: Matt Hammer | E2: City Administrator / Public Works Director | F2: pwdir@colfaxwa.org | G2: (509) 397-4606 | I2: https://colfaxwa.org/public-works | J2: $, phone # updated | K2: Not contacted
A5: 1. Alright, for starters what is your formal title in relation to [city] , [name]? 2. Do you happen to know the GMA status of your county? 3. Would you say the population of [city] has grown significantly in the last 10 years? 4. Does your town sell or provide water to any neighboring towns? 5. Has your department needed to expand the water infrastructure for your city at any point in the last 10 years? 6. How does your department raise funds for expansions of water infrastructure? Do you levy any upfront fees, like system development charges or capacity fee charges? 7. How are those funding methods typically calculated? For instance, do certain factors change how much the customer or developer on your water network pays? 8. Does your department utilize a GIS tool for your town’s water meters? If so, is this used when calculating fees and bills? 9. Is there anything you would like to add that you think may be helpful on this matter?
A22: Questions | B22: Y/N | C22: Notes / transcription
A23: Q1
A24: Q2
A25: Q3
A26: Q4
A27: Q5
A28: Q6
A29: Q7
A30: Q8
A31: Q9

Sheet Palouse
A1: County | B1: City/Town | C1: Pop. tier | D1: Contact Name | E1: Title | F1: Email | G1: Phone | H1: Alt Phone | I1: Website/Source | J1: Cross-reference | K1: Outreach Status | L1: Date Contacted | M1: Follow-up Date | N1: Notes
A2: Whitman | B2: Palouse | C2: Small (~1k) | D2: Mike Wolf, Misty (better contact) | E2: Maintenance Supervisor | G2: (509) 878-1811 | H2: (509) 878-1345 days/emergency | I2: palousewa.gov | J2: $, hard to verify if info is correct | K2: Not contacted
A5: 1. Alright, for starters what is your formal title in relation to [city] , [name]? 2. Do you happen to know the GMA status of your county? 3. Would you say the population of [city] has grown significantly in the last 10 years? 4. Does your town sell or provide water to any neighboring towns? 5. Has your department needed to expand the water infrastructure for your city at any point in the last 10 years? 6. How does your department raise funds for expansions of water infrastructure? Do you levy any upfront fees, like system development charges or capacity fee charges? 7. How are those funding methods typically calculated? For instance, do certain factors change how much the customer or developer on your water network pays? 8. Does your department utilize a GIS tool for your town’s water meters? If so, is this used when calculating fees and bills? 9. Is there anything you would like to add that you think may be helpful on this matter?
E8: Misty. Call 11 AM, Monday. Same number
A22: Questions | B22: Y/N | C22: Notes / transcription
A23: Q1 | C23: Misty, City administrator of Palouse
A24: Q2 | B24: N | C24: Doesn’t know GMA status, redoing comprehensive plan.
A25: Q3 | B25: N | C25: Not significantly. Nothing over 10 percent or 15 percent. Our infrastructure is old. We cant really put a lot more pressure on it. No anexations.
A26: Q4 | B26: N | C26: no.
A27: Q5 | B27: N ~ | C27: Not expand, just update.
A28: Q6 | C28: Fund upgrades to the existing system through Public works loans, trust fund loans. Big upgrade was in 2022 around $1 million. No upfront fees, no annexation or allotments for development in the last 10 years
A29: Q7 | B29: N, N/A | C29: N/A
A30: Q8 | B30: N | C30: No GIS tool. 2014 we paid for a survey to come in, had them mark where all our water and sewer lines are, but not super accurate.
A31: Q9 | C31: We are a small town that can't grow.

Sheet Tekoa
A1: County | B1: City/Town | C1: Pop. tier | D1: Contact Name | E1: Title | F1: Email | G1: Phone | H1: Alt Phone | I1: Website/Source | J1: Cross-reference | K1: Outreach Status | L1: Date Contacted | M1: Follow-up Date | N1: Notes
A2: Whitman | B2: Tekoa | C2: Small (~800) | D2: Steven Thomas | E2: Public Work's | F2: tekoapublicworksdept@gmail.com | G2: (509) 284-3861 | I2: https://tekoawa.com/public-work-s-department | J2: $, name updated | K2: Not contacted
